Workbook

Sheet Leverage finale
B2: Fiscal Year end January 31 | V2: COMMENTS
B3: In million | C3: Year | D3: 2018 | E3: 2019 | F3: 2020 | G3: 2021 | H3: 2022 | I3: 2023 | J3: 2024 | K3: 2025 | L3: 2026 | M3: 2027 | N3: 2028 | O3: 2029 | P3: 2030 | Q3: 2031 | R3: 2032 | S3: 2033 | T3: 2034 | U3: 2035 | AC3: Coverage ratio | AE3: Rating | AF3: Spread | AG3: Default probability | AJ3: Year 2025 | AK3: Iteration 0 | AL3: Iteration 1 | AM3: Iteration 2 | AN3: Iteration 3 | AO3: Iteration 4 | AP3: Iteration 5 | AQ3: Iteration 6 | AR3: Iteration 7 | AS3: Iteration 8 | AT3: Iteration 9 | AU3: Iteration 10
B4: Value of unlevered firm | AC4: > | AD4: ≤ to | AJ4: Trailing interest coverage ratio | AL4: =MAX(MIN($J$13/AK8,100000),-100000) -> 2.8643704 | AM4: =MAX(MIN($J$13/AL8,100000),-100000) -> 1.7744273 | AN4: =MAX(MIN($J$13/AM8,100000),-100000) -> 1.2181805 | AO4: =MAX(MIN($J$13/AN8,100000),-100000) -> 0.90935939 | AP4: =MAX(MIN($J$13/AO8,100000),-100000) -> 0.90935939 | AQ4: =MAX(MIN($J$13/AP8,100000),-100000) -> 0.90935939 | AR4: =MAX(MIN($J$13/AQ8,100000),-100000) -> 0.90935939 | AS4: =MAX(MIN($J$13/AR8,100000),-100000) -> 0.90935939 | ... AU4: =MAX(MIN($J$13/AT8,100000),-100000) -> 0.90935939
B5: Revenue growth | D5: 0 | E5: =+(E6-D6)/D6 -> 0.2601518 | F5: =+(F6-E6)/E6 -> 0.28730613 | G5: =+(G6-F6)/F6 -> 0.24295239 | H5: =+(H6-G6)/G6 -> 0.24656503 | I5: =+(I6-H6)/H6 -> 0.18345161 | J5: =+(J6-I6)/I6 -> 0.1117951 | K5: =+(K6-J6)/J6 -> 0.087156095 | L5: 0.12 | M5: 0.11 | N5: 0.097363199 | O5: 0.098704465 | P5: 0.092072049 | Q5: 0.08 | R5: 0.06 | S5: 0.06 | T5: 0.05 | U5: 0.04 | V5: We combined market and industry analysis with expectations derived from S&P Capital IQ via the CEDIF database. | AC5: -100000 | AD5: 0.199999 | AE5: D | AF5: 0.12 | AG5: 0.9 | AJ5: Credit rating | AL5: =VLOOKUP(AL4,$AC$5:$AG$17,3) -> BBB | AM5: =VLOOKUP(AM4,$AC$5:$AG$17,3) -> B+ | AN5: =VLOOKUP(AN4,$AC$5:$AG$17,3) -> CCC | AO5: =VLOOKUP(AO4,$AC$5:$AG$17,3) -> CCC | AP5: =VLOOKUP(AP4,$AC$5:$AG$17,3) -> CCC | AQ5: =VLOOKUP(AQ4,$AC$5:$AG$17,3) -> CCC | AR5: =VLOOKUP(AR4,$AC$5:$AG$17,3) -> CCC | AS5: =VLOOKUP(AS4,$AC$5:$AG$17,3) -> CCC | ... AU5: =VLOOKUP(AU4,$AC$5:$AG$17,3) -> CCC
B6: Revenue | D6: 10540 | E6: 13282 | F6: 17098 | G6: 21252 | H6: 26492 | I6: 31352 | J6: 34857 | K6: 37895 | L6: =+K6*(1+L5) -> 42442.4 | M6: =+L6*(1+M5) -> 47111.064 | N6: =+M6*(1+N5) -> 51697.948 | O6: =+N6*(1+O5) -> 56800.766 | P6: =+O6*(1+P5) -> 62030.529 | Q6: =+P6*(1+Q5) -> 66992.971 | R6: =+Q6*(1+R5) -> 71012.55 | S6: =+R6*(1+S5) -> 75273.303 | ... U6: =+T6*(1+U5) -> 82198.446 | AC6: 0.2 | AD6: 0.649999 | AE6: C | AF6: 0.105 | AG6: 0.3 | AJ6: Credit spread | AL6: =VLOOKUP(AL4,$AC$4:$AG$17,4) -> 0.025 | AM6: =VLOOKUP(AM4,$AC$4:$AG$17,4) -> 0.055 | AN6: =VLOOKUP(AN4,$AC$4:$AG$17,4) -> 0.0875 | AO6: =VLOOKUP(AO4,$AC$4:$AG$17,4) -> 0.0875 | AP6: =VLOOKUP(AP4,$AC$4:$AG$17,4) -> 0.0875 | AQ6: =VLOOKUP(AQ4,$AC$4:$AG$17,4) -> 0.0875 | AR6: =VLOOKUP(AR4,$AC$4:$AG$17,4) -> 0.0875 | AS6: =VLOOKUP(AS4,$AC$4:$AG$17,4) -> 0.0875 | ... AU6: =VLOOKUP(AU4,$AC$4:$AG$17,4) -> 0.0875
B7: Cost of Goods Sold | D7: 2773 | E7: 3451 | F7: 4235 | G7: 5438 | H7: 7026 | I7: 8360 | J7: 8541 | K7: 8643 | L7: =L6-L9*L6 -> 8284.7565 | M7: =M6-M9*M6 -> 9078.302 | N7: =N6-N9*N6 -> 9972.5341 | O7: =O6-O9*O6 -> 11604.397 | P7: =P6-P9*P6 -> 12064.938 | Q7: =Q6-Q9*Q6 -> 13030.133 | R7: =R6-R9*R6 -> 13811.941 | S7: =S6-S9*S6 -> 14640.657 | ... U7: =U6-U9*U6 -> 15987.598 | AC7: 0.65 | AD7: 0.799999 | AE7: CC | AF7: 0.095 | AG7: 0.2 | AJ7: Yield on debt | AL7: =AL6+$C$64 -> 0.0657 | AM7: =AM6+$C$64 -> 0.0957 | AN7: =AN6+$C$64 -> 0.1282 | AO7: =AO6+$C$64 -> 0.1282 | AP7: =AP6+$C$64 -> 0.1282 | AQ7: =AQ6+$C$64 -> 0.1282 | AR7: =AR6+$C$64 -> 0.1282 | AS7: =AS6+$C$64 -> 0.1282 | ... AU7: =AU6+$C$64 -> 0.1282
B8: % of revenues | D8: =+D7/D6 -> 0.26309298 | E8: =+E7/E6 -> 0.25982533 | F8: =+F7/F6 -> 0.24768979 | G8: =+G7/G6 -> 0.2558818 | H8: =+H7/H6 -> 0.26521214 | I8: =+I7/I6 -> 0.26664966 | J8: =+J7/J6 -> 0.24502969 | K8: =+K7/K6 -> 0.22807758 | ... U8: =+U7/U6 -> 0.1945 | AC8: 0.8 | AD8: 1.249999 | AE8: CCC | AF8: 0.0875 | AG8: 0.099 | AJ8: Interest paid | AK8: =$C$64*$C$55 -> 1749.4246 | AL8: =$C$55*AL7 -> 2824.0098 | AM8: =$C$55*AM7 -> 4113.5119 | AN8: =$C$55*AN7 -> 5510.4726 | AO8: =$C$55*AO7 -> 5510.4726 | AP8: =$C$55*AP7 -> 5510.4726 | AQ8: =$C$55*AQ7 -> 5510.4726 | AR8: =$C$55*AR7 -> 5510.4726 | AS8: =$C$55*AS7 -> 5510.4726 | ... AU8: =$C$55*AU7 -> 5510.4726
B9: Gross Profit Margin % | D9: =+D10/D6 -> 0.73690702 | E9: =+E10/E6 -> 0.74017467 | F9: =+F10/F6 -> 0.75231021 | G9: =+G10/G6 -> 0.7441182 | H9: =+H10/H6 -> 0.73478786 | I9: =+I10/I6 -> 0.73335034 | J9: =+J10/J6 -> 0.75497031 | K9: 0.8054 | L9: 0.8048 | M9: 0.8073 | N9: 0.8071 | O9: 0.7957 | P9: 0.8055 | Q9: 0.8055 | R9: 0.8055 | S9: 0.8055 | T9: 0.8055 | U9: 0.8055 | V9: data from Capital IQ | AC9: 1.25 | AD9: 1.499999 | AE9: B- | AF9: 0.0675 | AG9: 0.07 | AJ9: Prob of default | AL9: =VLOOKUP(AL4,$AC$5:$AG$17,5) -> 0.004 | AM9: =VLOOKUP(AM4,$AC$5:$AG$17,5) -> 0.03 | AN9: =VLOOKUP(AN4,$AC$5:$AG$17,5) -> 0.099 | AO9: =VLOOKUP(AO4,$AC$5:$AG$17,5) -> 0.099 | AP9: =VLOOKUP(AP4,$AC$5:$AG$17,5) -> 0.099 | AQ9: =VLOOKUP(AQ4,$AC$5:$AG$17,5) -> 0.099 | AR9: =VLOOKUP(AR4,$AC$5:$AG$17,5) -> 0.099 | AS9: =VLOOKUP(AS4,$AC$5:$AG$17,5) -> 0.099 | ... AU9: =VLOOKUP(AU4,$AC$5:$AG$17,5) -> 0.099
B10: Gross Profit | D10: =+D6-D7 -> 7767 | E10: =+E6-E7 -> 9831 | F10: =+F6-F7 -> 12863 | G10: =+G6-G7 -> 15814 | H10: =+H6-H7 -> 19466 | I10: =+I6-I7 -> 22992 | J10: =+J6-J7 -> 26316 | K10: =+K6-K7 -> 29252 | ... U10: =+U6-U7 -> 66210.849 | AC10: 1.5 | AD10: 1.749999 | AE10: B | AF10: 0.06 | AG10: 0.052 | AJ10: Cost of debt | AL10: =(1-AL9+AL9*$C$68)*(1+AL7)-1 -> 0.063184948 | AM10: =(1-AM9+AM9*$C$68)*(1+AM7)-1 -> 0.07630611 | AN10: =(1-AN9+AN9*$C$68)*(1+AN7)-1 -> 0.062301838 | AO10: =(1-AO9+AO9*$C$68)*(1+AO7)-1 -> 0.062301838 | AP10: =(1-AP9+AP9*$C$68)*(1+AP7)-1 -> 0.062301838 | AQ10: =(1-AQ9+AQ9*$C$68)*(1+AQ7)-1 -> 0.062301838 | AR10: =(1-AR9+AR9*$C$68)*(1+AR7)-1 -> 0.062301838 | AS10: =(1-AS9+AS9*$C$68)*(1+AS7)-1 -> 0.062301838 | ... AU10: =(1-AU9+AU9*$C$68)*(1+AU7)-1 -> 0.062301838
B11: Total operating expenses | D11: 7313 | E11: 9296 | F11: 12566 | G11: 15359 | H11: 18918 | I11: 21962 | J11: 21305 | K11: 22047 | L11: =+L6*L12 -> 26788.241 | M11: =+M6*M12 -> 28646.201 | N11: =+N6*N12 -> 31380.922 | O11: =+O6*O12 -> 34955.739 | P11: =+P6*P12 -> 37848.373 | Q11: =+Q6*Q12 -> 40923.148 | R11: =+R6*R12 -> 43469.72 | S11: =+S6*S12 -> 45995.9 | ... U11: =+U6*U12 -> 50265.544 | AC11: 1.75 | AD11: 1.999999 | AE11: B+ | AF11: 0.055 | AG11: 0.03
B12: Total operating expenses as % of revenues | D12: =+D11/D6 -> 0.69383302 | E12: =+E11/E6 -> 0.69989459 | F12: =+F11/F6 -> 0.73493976 | G12: =+G11/G6 -> 0.72270845 | H12: =+H11/H6 -> 0.71410237 | I12: =+I11/I6 -> 0.70049758 | J12: =+J11/J6 -> 0.61121152 | K12: =+K11/K6 -> 0.58179179 | L12: =+AVERAGE(I12:K12) -> 0.63116696 | M12: =+AVERAGE(J12:L12) -> 0.60805676 | N12: =+AVERAGE(K12:M12) -> 0.60700517 | O12: =+AVERAGE(L12:N12) -> 0.61540963 | P12: =+AVERAGE(M12:O12) -> 0.61015719 | Q12: =+AVERAGE(N12:P12) -> 0.61085733 | R12: =+AVERAGE(O12:Q12) -> 0.61214138 | S12: =+AVERAGE(P12:R12) -> 0.61105197 | ... U12: =+AVERAGE(R12:T12) -> 0.61151453 | AC12: 2.5 | AD12: 2.999999 | AE12: BBB | AF12: 0.025 | AG12: 0.004
B13: Taxable Income (EBIT) | D13: =+D10-D11 -> 454 | E13: =+E10-E11 -> 535 | F13: =+F10-F11 -> 297 | G13: =+G10-G11 -> 455 | H13: =+H10-H11 -> 548 | I13: =+I10-I11 -> 1030 | J13: =+J10-J11 -> 5011 | K13: =+K10-K11 -> 7205 | ... U13: =+U10-U11 -> 15945.305 | AC13: 3 | AD13: 4.249999 | AE13: A- | AF13: 0.0165 | AG13: 0.003 | AJ13: Year 2026 | AK13: Iteration 0 | AL13: Iteration 1 | AM13: Iteration 2 | AN13: Iteration 3 | AO13: Iteration 4 | AP13: Iteration 5 | AQ13: Iteration 6 | AR13: Iteration 7 | AS13: Iteration 8 | AT13: Iteration 9 | AU13: Iteration 10
B14: EBIT as % of revenues | D14: =+D13/D6 -> 0.043074004 | E14: =+E13/E6 -> 0.040280078 | F14: =+F13/F6 -> 0.017370453 | G14: =+G13/G6 -> 0.02140975 | H14: =+H13/H6 -> 0.02068549 | I14: =+I13/I6 -> 0.032852769 | J14: =+J13/J6 -> 0.14375879 | K14: =+K13/K6 -> 0.19013062 | ... U14: =+U13/U6 -> 0.19398547 | AC14: 4.25 | AD14: 5.499999 | AE14: A | AF14: 0.014 | AG14: 0.002 | AJ14: Trailing interest coverage ratio | AL14: =MAX(MIN($K$13/AK18,100000),-100000) -> 3.7900932 | AM14: =MAX(MIN($K$13/AL18,100000),-100000) -> 2.6967971 | AN14: =MAX(MIN($K$13/AM18,100000),-100000) -> 2.3478964 | AO14: =MAX(MIN($K$13/AN18,100000),-100000) -> 1.6118787 | AP14: =MAX(MIN($K$13/AO18,100000),-100000) -> 1.531845 | AQ14: =MAX(MIN($K$13/AP18,100000),-100000) -> 1.531845 | AR14: =MAX(MIN($K$13/AQ18,100000),-100000) -> 1.531845 | AS14: =MAX(MIN($K$13/AR18,100000),-100000) -> 1.531845 | ... AU14: =MAX(MIN($K$13/AT18,100000),-100000) -> 1.531845
B15: EBT | D15: 420 | E15: 983 | F15: 706 | G15: 2561 | H15: 1532 | I15: 660 | J15: 4950 | K15: 7438 | L15: =+L16*L6 -> 9144.5422 | M15: =+M16*M6 -> 10940.366 | N15: =+N16*N6 -> 13329.427 | O15: =+O16*O6 -> 14275.853 | P15: =+P16*P6 -> 16154.791 | Q15: =+Q16*Q6 -> 17869.743 | R15: =+R16*R6 -> 19304.548 | S15: =+S16*S6 -> 20788.183 | ... U15: =+U16*U6 -> 24741.726 | V15: data from Capital IQ (GAAP) | AC15: 5.5 | AD15: 6.499999 | AE15: A+ | AF15: 0.013 | AG15: 0.0015 | AJ15: Credit rating | AL15: =VLOOKUP(AL14,$AC$5:$AG$17,3) -> A- | AM15: =VLOOKUP(AM14,$AC$5:$AG$17,3) -> BBB | AN15: =VLOOKUP(AN14,$AC$5:$AG$17,3) -> B+ | AO15: =VLOOKUP(AO14,$AC$5:$AG$17,3) -> B | AP15: =VLOOKUP(AP14,$AC$5:$AG$17,3) -> B | AQ15: =VLOOKUP(AQ14,$AC$5:$AG$17,3) -> B | AR15: =VLOOKUP(AR14,$AC$5:$AG$17,3) -> B | AS15: =VLOOKUP(AS14,$AC$5:$AG$17,3) -> B | ... AU15: =VLOOKUP(AU14,$AC$5:$AG$17,3) -> B
B16: EBT % of revenues | D16: =+D15/D6 -> 0.039848197 | E16: =+E15/E6 -> 0.074009938 | F16: =+F15/F6 -> 0.041291379 | G16: =+G15/G6 -> 0.12050631 | H16: =+H15/H6 -> 0.057828778 | I16: =+I15/I6 -> 0.021051289 | J16: =+J15/J6 -> 0.14200878 | K16: =+K15/K6 -> 0.19627919 | L16: 0.21545771 | M16: 0.23222498 | N16: 0.25783281 | O16: 0.25133205 | P16: 0.2604329 | Q16: 0.26674056 | R16: 0.271847 | S16: 0.27616941 | T16: 0.27962481 | U16: 0.30099992 | AC16: 6.5 | AD16: 8.499999 | AE16: AA | AF16: 0.0115 | AG16: 0.0005 | AJ16: Credit spread | AL16: =VLOOKUP(AL14,$AC$5:$AG$17,4) -> 0.0165 | AM16: =VLOOKUP(AM14,$AC$5:$AG$17,4) -> 0.025 | AN16: =VLOOKUP(AN14,$AC$5:$AG$17,4) -> 0.055 | AO16: =VLOOKUP(AO14,$AC$5:$AG$17,4) -> 0.06 | AP16: =VLOOKUP(AP14,$AC$5:$AG$17,4) -> 0.06 | AQ16: =VLOOKUP(AQ14,$AC$5:$AG$17,4) -> 0.06 | AR16: =VLOOKUP(AR14,$AC$5:$AG$17,4) -> 0.06 | AS16: =VLOOKUP(AS14,$AC$5:$AG$17,4) -> 0.06 | ... AU16: =VLOOKUP(AU14,$AC$5:$AG$17,4) -> 0.06
B17: Taxes | D17: -60 | E17: 127 | F17: -580 | G17: 1511 | H17: -88 | I17: -452 | J17: -814 | K17: -1241 | L17: =+L15*L19 -> -1507.4398 | M17: =+M15*M19 -> -1803.4739 | N17: =+N15*N19 -> -2197.3007 | O17: =+O15*O19 -> -2353.3151 | P17: =+P15*P19 -> -2663.0501 | Q17: =+Q15*Q19 -> -2945.7529 | R17: =+R15*R19 -> -3182.2746 | S17: =+S15*S19 -> -3426.8456 | ... U17: =+U15*U19 -> -4078.5706 | AC17: 8.5 | AD17: 100000 | AE17: AAA | AF17: 0.0065 | AG17: 0.0001 | AJ17: Yield on debt | AL17: =AL16+$C$64 -> 0.0572 | AM17: =AM16+$C$64 -> 0.0657 | AN17: =AN16+$C$64 -> 0.0957 | AO17: =AO16+$C$64 -> 0.1007 | AP17: =AP16+$C$64 -> 0.1007 | AQ17: =AQ16+$C$64 -> 0.1007 | AR17: =AR16+$C$64 -> 0.1007 | AS17: =AS16+$C$64 -> 0.1007 | ... AU17: =AU16+$C$64 -> 0.1007
B18: Net income | D18: =+D15+D17 -> 360 | E18: =+E15+E17 -> 1110 | F18: =+F15+F17 -> 126 | G18: =+G15+G17 -> 4072 | H18: =+H15+H17 -> 1444 | I18: =+I15+I17 -> 208 | J18: =+J15+J17 -> 4136 | K18: =+K15+K17 -> 6197 | ... U18: =+U15+U17 -> 20663.155 | V18: data from Capital IQ (GAAP) | AJ18: Interest paid | AK18: =+$D$55*$C$64 -> 1901.0087 | AL18: =$D$55*AL17 -> 2671.6879 | AM18: =$D$55*AM17 -> 3068.7044 | AN18: =$D$55*AN17 -> 4469.9393 | AO18: =$D$55*AO17 -> 4703.4785 | AP18: =$D$55*AP17 -> 4703.4785 | AQ18: =$D$55*AQ17 -> 4703.4785 | AR18: =$D$55*AR17 -> 4703.4785 | AS18: =$D$55*AS17 -> 4703.4785 | ... AU18: =$D$55*AU17 -> 4703.4785
B19: Effective Tax Rate | D19: =+D17/D15 -> -0.14285714 | E19: =+E17/E15 -> 0.12919634 | F19: =+F17/F15 -> -0.82152975 | G19: =+G17/G15 -> 0.5900039 | H19: =+H17/H15 -> -0.057441253 | I19: =+I17/I15 -> -0.68484848 | J19: =+J17/J15 -> -0.16444444 | K19: =+K17/K15 -> -0.16684593 | L19: =+AVERAGE($D$19:$K$19) -> -0.16484584 | M19: =+AVERAGE($D$19:$K$19) -> -0.16484584 | N19: =+AVERAGE($D$19:$K$19) -> -0.16484584 | O19: =+AVERAGE($D$19:$K$19) -> -0.16484584 | P19: =+AVERAGE($D$19:$K$19) -> -0.16484584 | Q19: =+AVERAGE($D$19:$K$19) -> -0.16484584 | R19: =+AVERAGE($D$19:$K$19) -> -0.16484584 | S19: =+AVERAGE($D$19:$K$19) -> -0.16484584 | ... U19: =+AVERAGE($D$19:$K$19) -> -0.16484584 | V19: We assumed that the effective tax rate for 2026–2035 corresponds to the average ETR observed in the previous years. | AJ19: Prob of default | AL19: =VLOOKUP(AL14,$AC$5:$AG$17,5) -> 0.003 | AM19: =VLOOKUP(AM14,$AC$5:$AG$17,5) -> 0.004 | AN19: =VLOOKUP(AN14,$AC$5:$AG$17,5) -> 0.03 | AO19: =VLOOKUP(AO14,$AC$5:$AG$17,5) -> 0.052 | AP19: =VLOOKUP(AP14,$AC$5:$AG$17,5) -> 0.052 | AQ19: =VLOOKUP(AQ14,$AC$5:$AG$17,5) -> 0.052 | AR19: =VLOOKUP(AR14,$AC$5:$AG$17,5) -> 0.052 | AS19: =VLOOKUP(AS14,$AC$5:$AG$17,5) -> 0.052 | ... AU19: =VLOOKUP(AU14,$AC$5:$AG$17,5) -> 0.052
B20: Cash flow from operations | D20: 2738 | E20: 3398 | F20: 4331 | G20: 4801 | H20: 6000 | I20: 7111 | J20: 10234 | K20: 13092 | L20: =+L21*L6 -> 11073.199 | M20: =+M21*M6 -> 12291.25 | N20: =+N21*N6 -> 13487.966 | O20: =+O21*O6 -> 14819.288 | P20: =+P21*P6 -> 16183.73 | Q20: =+Q21*Q6 -> 17478.429 | R20: =+R21*R6 -> 18527.135 | S20: =+S21*S6 -> 19638.763 | ... U20: =+U21*U6 -> 21445.529 | AJ20: Cost of debt | AL20: =(1-AL19+AL19*$C$68)*(1+AL17)-1 -> 0.055328756 | AM20: =(1-AM19+AM19*$C$68)*(1+AM17)-1 -> 0.063184948 | AN20: =(1-AN19+AN19*$C$68)*(1+AN17)-1 -> 0.07630611 | AO20: =(1-AO19+AO19*$C$68)*(1+AO17)-1 -> 0.066930524 | AP20: =(1-AP19+AP19*$C$68)*(1+AP17)-1 -> 0.066930524 | AQ20: =(1-AQ19+AQ19*$C$68)*(1+AQ17)-1 -> 0.066930524 | AR20: =(1-AR19+AR19*$C$68)*(1+AR17)-1 -> 0.066930524 | AS20: =(1-AS19+AS19*$C$68)*(1+AS17)-1 -> 0.066930524 | ... AU20: =(1-AU19+AU19*$C$68)*(1+AU17)-1 -> 0.066930524
B21: Cash flow from Operations as % of revenues | D21: =+D20/D6 -> 0.2597723 | E21: =+E20/E6 -> 0.25583496 | F21: =+F20/F6 -> 0.25330448 | G21: =+G20/G6 -> 0.22590815 | H21: =+H20/H6 -> 0.22648347 | I21: =+I20/I6 -> 0.22681169 | J21: =+J20/J6 -> 0.29359956 | K21: =+K20/K6 -> 0.34548093 | L21: =+AVERAGE($D$21:$K$21) -> 0.26089944 | M21: =+L21 -> 0.26089944 | N21: =+M21 -> 0.26089944 | O21: =+N21 -> 0.26089944 | P21: =+O21 -> 0.26089944 | Q21: =+P21 -> 0.26089944 | R21: =+Q21 -> 0.26089944 | S21: =+R21 -> 0.26089944 | T21: =+S21 -> 0.26089944 | U21: =+T21 -> 0.26089944 | V21: We used the average percentage of CFFO/revenues for projections
B22: Increase in gross PPE | D22: 417 | E22: 431 | F22: 342 | G22: 238 | H22: 802 | I22: 1188 | J22: 437 | K22: 77 | L22: =(1+AVERAGE($E$23:$K$23))*K22 -> 87.098816 | M22: =(1+AVERAGE($E$23:$K$23))*L22 -> 98.522127 | N22: =(1+AVERAGE($E$23:$K$23))*M22 -> 111.44364 | O22: =(1+AVERAGE($E$23:$K$23))*N22 -> 126.05986 | P22: =(1+AVERAGE($E$23:$K$23))*O22 -> 142.59305 | Q22: =(1+AVERAGE($E$23:$K$23))*P22 -> 161.29462 | R22: =(1+AVERAGE($E$23:$K$23))*Q22 -> 182.44897 | S22: =(1+AVERAGE($E$23:$K$23))*R22 -> 206.37778 | ... U22: =(1+AVERAGE($E$23:$K$23))*T22 -> 264.06205 | V22: We calculated the average percentage increase and then applied it as PPE(t-1) × (1 + average increase
B23: % increase | E23: =+(E22-D22)/D22 -> 0.033573141 | F23: =+(F22-E22)/E22 -> -0.20649652 | G23: =+(G22-F22)/F22 -> -0.30409357 | H23: =+(H22-G22)/G22 -> 2.3697479 | I23: =+(I22-H22)/H22 -> 0.48129676 | J23: =+(J22-I22)/I22 -> -0.63215488 | K23: =+(K22-J22)/J22 -> -0.82379863 | L23: =+(L22-K22)/K22 -> 0.13115346 | ... U23: =+(U22-T22)/T22 -> 0.13115346 | AJ23: Year 2027 | AK23: Iteration 0 | AL23: Iteration 1 | AM23: Iteration 2 | AN23: Iteration 3 | AO23: Iteration 4 | AP23: Iteration 5 | AQ23: Iteration 6 | AR23: Iteration 7 | AS23: Iteration 8 | AT23: Iteration 9 | AU23: Iteration 10
B24: Free Cash Flow | D24: =+D20-D22 -> 2321 | E24: =+E20-E22 -> 2967 | F24: =+F20-F22 -> 3989 | G24: =+G20-G22 -> 4563 | H24: =+H20-H22 -> 5198 | I24: =+I20-I22 -> 5923 | J24: =+J20-J22 -> 9797 | K24: =+K20-K22 -> 13015 | ... U24: =+U20-U22 -> 21181.467 | AJ24: Trailing interest coverage ratio | AL24: =MAX(MIN($L$13/AK28,100000),-100000) -> 3.5713553 | AM24: =MAX(MIN($L$13/AL28,100000),-100000) -> 2.5411566 | AN24: =MAX(MIN($L$13/AM28,100000),-100000) -> 2.2123921 | AO24: =MAX(MIN($L$13/AN28,100000),-100000) -> 1.5188522 | AP24: =MAX(MIN($L$13/AO28,100000),-100000) -> 1.4434375 | AQ24: =MAX(MIN($L$13/AP28,100000),-100000) -> 1.3433841 | AR24: =MAX(MIN($L$13/AQ28,100000),-100000) -> 1.3433841 | AS24: =MAX(MIN($L$13/AR28,100000),-100000) -> 1.3433841 | ... AU24: =MAX(MIN($L$13/AT28,100000),-100000) -> 1.3433841
B25: Terminal Value | U25: =+U24*(1+C69)/(C63-C69) -> 375893.93 | AJ25: Credit rating | AL25: =VLOOKUP(AL24,$AC$5:$AG$17,3) -> A- | AM25: =VLOOKUP(AM24,$AC$5:$AG$17,3) -> BBB | AN25: =VLOOKUP(AN24,$AC$5:$AG$17,3) -> B+ | AO25: =VLOOKUP(AO24,$AC$5:$AG$17,3) -> B | AP25: =VLOOKUP(AP24,$AC$5:$AG$17,3) -> B- | AQ25: =VLOOKUP(AQ24,$AC$5:$AG$17,3) -> B- | AR25: =VLOOKUP(AR24,$AC$5:$AG$17,3) -> B- | AS25: =VLOOKUP(AS24,$AC$5:$AG$17,3) -> B- | ... AU25: =VLOOKUP(AU24,$AC$5:$AG$17,3) -> B-
B26: Total Free Cash Flow | D26: =+D24 -> 2321 | E26: =+E24 -> 2967 | F26: =+F24 -> 3989 | G26: =+G24 -> 4563 | H26: =+H24 -> 5198 | I26: =+I24 -> 5923 | J26: =+J24 -> 9797 | K26: =+K24 -> 13015 | ... P26: =+P24 -> 16041.137 | Q26: =+Q24+Q25 -> 17317.134 | R26: =+R24+R25 -> 18344.686 | S26: =+S24+S25 -> 19432.385 | T26: =+T24+T25 -> 20387.256 | U26: =+U24+U25 -> 397075.39 | AJ26: Credit spread | AL26: =VLOOKUP(AL24,$AC$5:$AG$17,4) -> 0.0165 | AM26: =VLOOKUP(AM24,$AC$5:$AG$17,4) -> 0.025 | AN26: =VLOOKUP(AN24,$AC$5:$AG$17,4) -> 0.055 | AO26: =VLOOKUP(AO24,$AC$5:$AG$17,4) -> 0.06 | AP26: =VLOOKUP(AP24,$AC$5:$AG$17,4) -> 0.0675 | AQ26: =VLOOKUP(AQ24,$AC$5:$AG$17,4) -> 0.0675 | AR26: =VLOOKUP(AR24,$AC$5:$AG$17,4) -> 0.0675 | AS26: =VLOOKUP(AS24,$AC$5:$AG$17,4) -> 0.0675 | ... AU26: =VLOOKUP(AU24,$AC$5:$AG$17,4) -> 0.0675
B27: Value of unlevered firm (at February of every year) | K27: =+NPV($C$63,K26:U26) -> 244180.8 | L27: =+NPV($C$63,L26:U26) -> 253770.6 | M27: =+NPV($C$63,M26:U26) -> 266277.06 | N27: =+NPV($C$63,N26:U26) -> 278734.66 | O27: =+NPV($C$63,O26:U26) -> 291161.72 | P27: =+NPV($C$63,P26:U26) -> 303422.5 | Q27: =+NPV($C$63,Q26:U26) -> 315470.4 | R27: =+NPV($C$63,R26:U26) -> 327357.63 | S27: =+NPV($C$63,S26:U26) -> 339317.75 | T27: =+NPV($C$63,T26:U26) -> 351297.37 | U27: =+NPV($C$63,U26) -> 363431.12 | AJ27: Yield on debt | AL27: =AL26+$C$64 -> 0.0572 | AM27: =AM26+$C$64 -> 0.0657 | AN27: =AN26+$C$64 -> 0.0957 | AO27: =AO26+$C$64 -> 0.1007 | AP27: =AP26+$C$64 -> 0.1082 | AQ27: =AQ26+$C$64 -> 0.1082 | AR27: =AR26+$C$64 -> 0.1082 | AS27: =AS26+$C$64 -> 0.1082 | ... AU27: =AU26+$C$64 -> 0.1082
J28: EXCESS CASH | K28: ='Excess Cash'!I5 -> 3739.2 | L28: =K28*(1+$C$64) -> 3891.3854 | M28: =L28*(1+$C$64) -> 4049.7648 | N28: =M28*(1+$C$64) -> 4214.5903 | O28: =N28*(1+$C$64) -> 4386.1241 | P28: =O28*(1+$C$64) -> 4564.6393 | Q28: =P28*(1+$C$64) -> 4750.4202 | R28: =Q28*(1+$C$64) -> 4943.7623 | S28: =R28*(1+$C$64) -> 5144.9734 | ... U28: =T28*(1+$C$64) -> 5572.2968 | AJ28: Interest paid | AK28: =$C$64*$E$55 -> 2063.4751 | AL28: =$E$55*AL27 -> 2900.0191 | AM28: =$E$55*AM27 -> 3330.966 | AN28: =$E$55*AN27 -> 4851.955 | AO28: =$E$55*AO27 -> 5105.4532 | AP28: =$E$55*AP27 -> 5485.7005 | AQ28: =$E$55*AQ27 -> 5485.7005 | AR28: =$E$55*AR27 -> 5485.7005 | AS28: =$E$55*AS27 -> 5485.7005 | ... AU28: =$E$55*AU27 -> 5485.7005
I29: Adj. Value of Unlevered Firm | K29: =K28+K27 -> 247920 | L29: =L28+L27 -> 257661.98 | M29: =M28+M27 -> 270326.82 | N29: =N28+N27 -> 282949.25 | O29: =O28+O27 -> 295547.85 | P29: =P28+P27 -> 307987.14 | Q29: =Q28+Q27 -> 320220.82 | R29: =R28+R27 -> 332301.39 | ... U29: =U28+U27 -> 369003.41 | AJ29: Prob of default | AL29: =VLOOKUP(AL24,$AC$5:$AG$17,5) -> 0.003 | AM29: =VLOOKUP(AM24,$AC$5:$AG$17,5) -> 0.004 | AN29: =VLOOKUP(AN24,$AC$5:$AG$17,5) -> 0.03 | AO29: =VLOOKUP(AO24,$AC$5:$AG$17,5) -> 0.052 | AP29: =VLOOKUP(AP24,$AC$5:$AG$17,5) -> 0.07 | AQ29: =VLOOKUP(AQ24,$AC$5:$AG$17,5) -> 0.07 | AR29: =VLOOKUP(AR24,$AC$5:$AG$17,5) -> 0.07 | AS29: =VLOOKUP(AS24,$AC$5:$AG$17,5) -> 0.07 | ... AU29: =VLOOKUP(AU24,$AC$5:$AG$17,5) -> 0.07
AJ30: Cost of debt | AL30: =(1-AL29+AL29*$C$68)*(1+AL27)-1 -> 0.055328756 | AM30: =(1-AM29+AM29*$C$68)*(1+AM27)-1 -> 0.063184948 | AN30: =(1-AN29+AN29*$C$68)*(1+AN27)-1 -> 0.07630611 | AO30: =(1-AO29+AO29*$C$68)*(1+AO27)-1 -> 0.066930524 | AP30: =(1-AP29+AP29*$C$68)*(1+AP27)-1 -> 0.06243134 | AQ30: =(1-AQ29+AQ29*$C$68)*(1+AQ27)-1 -> 0.06243134 | AR30: =(1-AR29+AR29*$C$68)*(1+AR27)-1 -> 0.06243134 | AS30: =(1-AS29+AS29*$C$68)*(1+AS27)-1 -> 0.06243134 | ... AU30: =(1-AU29+AU29*$C$68)*(1+AU27)-1 -> 0.06243134
B32: Value of Interest Tax Shields | K32: 2025 | L32: 2026 | M32: 2027 | N32: 2028 | O32: 2029 | P32: 2030 | Q32: 2031 | R32: 2032 | S32: 2033 | T32: 2034 | U32: 2035
B33: Interest paid | K33: =+AU8 -> 5510.4726 | L33: =+AU18 -> 4703.4785 | M33: =+AU28 -> 5485.7005 | N33: =+AU38 -> 3633.3287 | O33: =+AU48 -> 3357.4592 | P33: =+AU58 -> 4023.1017 | Q33: =+BA8 -> 0 | R33: =+BA18 -> 0 | S33: =+BA28 -> 0 | T33: =+BA38 -> 0 | U33: =+AZ58 -> 0 | AJ33: Year 2028 | AK33: Iteration 0 | AL33: Iteration 1 | AM33: Iteration 2 | AN33: Iteration 3 | AO33: Iteration 4 | AP33: Iteration 5 | AQ33: Iteration 6 | AR33: Iteration 7 | AS33: Iteration 8 | AT33: Iteration 9 | AU33: Iteration 10
B34: PV Interest tax shields | K34: =$C$62*$K$33 -> 908.37851 | L34: =$C$62*$K$33 -> 908.37851 | M34: =$C$62*$K$33 -> 908.37851 | N34: =$C$62*$K$33 -> 908.37851 | O34: =$C$62*$K$33 -> 908.37851 | P34: =$C$62*$K$33 -> 908.37851 | Q34: =$C$62*$K$33 -> 908.37851 | R34: =$C$62*$K$33 -> 908.37851 | ... U34: =$C$62*$K$33 -> 908.37851 | AJ34: Trailing interest coverage ratio | AL34: =MAX(MIN($M$13/AK38,100000),-100000) -> 4.1703527 | AM34: =MAX(MIN($M$13/AL38,100000),-100000) -> 2.9673663 | AN34: =MAX(MIN($M$13/AM38,100000),-100000) -> 2.5834605 | AO34: =MAX(MIN($M$13/AN38,100000),-100000) -> 2.5834605 | AP34: =MAX(MIN($M$13/AO38,100000),-100000) -> 2.5834605 | AQ34: =MAX(MIN($M$13/AP38,100000),-100000) -> 2.5834605 | AR34: =MAX(MIN($M$13/AQ38,100000),-100000) -> 2.5834605 | AS34: =MAX(MIN($M$13/AR38,100000),-100000) -> 2.5834605 | ... AU34: =MAX(MIN($M$13/AT38,100000),-100000) -> 2.5834605
U35: =C62*M55 -> 12421.155 | AJ35: Credit rating | AL35: =VLOOKUP(AL34,$AC$5:$AG$17,3) -> A- | AM35: =VLOOKUP(AM34,$AC$5:$AG$17,3) -> BBB | AN35: =VLOOKUP(AN34,$AC$5:$AG$17,3) -> BBB | AO35: =VLOOKUP(AO34,$AC$5:$AG$17,3) -> BBB | AP35: =VLOOKUP(AP34,$AC$5:$AG$17,3) -> BBB | AQ35: =VLOOKUP(AQ34,$AC$5:$AG$17,3) -> BBB | AR35: =VLOOKUP(AR34,$AC$5:$AG$17,3) -> BBB | AS35: =VLOOKUP(AS34,$AC$5:$AG$17,3) -> BBB | ... AU35: =VLOOKUP(AU34,$AC$5:$AG$17,3) -> BBB
B36: Total value of tax shields | K36: =K34+K35 -> 908.37851 | L36: =L34+L35 -> 908.37851 | M36: =M34+M35 -> 908.37851 | N36: =N34+N35 -> 908.37851 | O36: =O34+O35 -> 908.37851 | P36: =P34+P35 -> 908.37851 | Q36: =Q34+Q35 -> 908.37851 | R36: =R34+R35 -> 908.37851 | ... U36: =U34+U35 -> 13329.534 | AJ36: Credit spread | AL36: =VLOOKUP(AL34,$AC$4:$AG$17,4) -> 0.0165 | AM36: =VLOOKUP(AM34,$AC$4:$AG$17,4) -> 0.025 | AN36: =VLOOKUP(AN34,$AC$4:$AG$17,4) -> 0.025 | AO36: =VLOOKUP(AO34,$AC$4:$AG$17,4) -> 0.025 | AP36: =VLOOKUP(AP34,$AC$4:$AG$17,4) -> 0.025 | AQ36: =VLOOKUP(AQ34,$AC$4:$AG$17,4) -> 0.025 | AR36: =VLOOKUP(AR34,$AC$4:$AG$17,4) -> 0.025 | AS36: =VLOOKUP(AS34,$AC$4:$AG$17,4) -> 0.025 | ... AU36: =VLOOKUP(AU34,$AC$4:$AG$17,4) -> 0.025
B37: Cost of debt | K37: =+$AU$10 -> 0.062301838 | L37: =+$AU$20 -> 0.066930524 | M37: =+$AU$30 -> 0.06243134 | N37: =+$AU$30 -> 0.06243134 | O37: =+$AU$40 -> 0.063184948 | P37: =+$AU$50 -> 0.055328756 | Q37: =+$AU$10 -> 0.062301838 | R37: =+$AU$20 -> 0.066930524 | S37: =+$AU$30 -> 0.06243134 | T37: =+$AU$30 -> 0.06243134 | U37: =+$AU$50 -> 0.055328756 | AJ37: Yield on debt | AL37: =AL36+$C$64 -> 0.0572 | AM37: =AM36+$C$64 -> 0.0657 | AN37: =AN36+$C$64 -> 0.0657 | AO37: =AO36+$C$64 -> 0.0657 | AP37: =AP36+$C$64 -> 0.0657 | AQ37: =AQ36+$C$64 -> 0.0657 | AR37: =AR36+$C$64 -> 0.0657 | AS37: =AS36+$C$64 -> 0.0657 | ... AU37: =AU36+$C$64 -> 0.0657
B38: Tax Shield Discount Rate | K38: =IF(K3=2025,K37,(1+$C$63)*(((1+K37)/(1+$C$63))^(1/(K3-2024)))-1) -> 0.062301838 | L38: =IF(L3=2025,L37,(1+$C$63)*(((1+L37)/(1+$C$63))^(1/(L3-2024)))-1) -> 0.079676135 | M38: =IF(M3=2025,M37,(1+$C$63)*(((1+M37)/(1+$C$63))^(1/(M3-2024)))-1) -> 0.082432609 | N38: =IF(N3=2025,N37,(1+$C$63)*(((1+N37)/(1+$C$63))^(1/(N3-2024)))-1) -> 0.084959099 | O38: =IF(O3=2025,O37,(1+$C$63)*(((1+O37)/(1+$C$63))^(1/(O3-2024)))-1) -> 0.086631912 | P38: =IF(P3=2025,P37,(1+$C$63)*(((1+P37)/(1+$C$63))^(1/(P3-2024)))-1) -> 0.086276411 | Q38: =IF(Q3=2025,Q37,(1+$C$63)*(((1+Q37)/(1+$C$63))^(1/(Q3-2024)))-1) -> 0.08819716 | R38: =IF(R3=2025,R37,(1+$C$63)*(((1+R37)/(1+$C$63))^(1/(R3-2024)))-1) -> 0.089335165 | ... U38: =IF(U3=2025,U37,(1+$C$63)*(((1+U37)/(1+$C$63))^(1/(U3-2024)))-1) -> 0.089134442 | AJ38: Interest paid | AK38: =$C$64*$F$55 -> 2250.7835 | AL38: =$F$55*AL37 -> 3163.2633 | AM38: =$F$55*AM37 -> 3633.3287 | AN38: =$F$55*AN37 -> 3633.3287 | AO38: =$F$55*AO37 -> 3633.3287 | AP38: =$F$55*AP37 -> 3633.3287 | AQ38: =$F$55*AQ37 -> 3633.3287 | AR38: =$F$55*AR37 -> 3633.3287 | AS38: =$F$55*AS37 -> 3633.3287 | ... AU38: =$F$55*AU37 -> 3633.3287
B39: Present value of tax shields (beginning of year) | K39: =K36/(1+K38)^(K3-2024) -> 855.10396 | L39: =L36/(1+L38)^(L3-2024) -> 779.25545 | M39: =M36/(1+M38)^(M3-2024) -> 716.24936 | N39: =N36/(1+N38)^(N3-2024) -> 655.56142 | O39: =O36/(1+O38)^(O3-2024) -> 599.59027 | P39: =P36/(1+P38)^(P3-2024) -> 552.87221 | Q39: =Q36/(1+Q38)^(Q3-2024) -> 502.70561 | R39: =R36/(1+R38)^(R3-2024) -> 458.11516 | ... U39: =U36/(1+U38)^(U3-2024) -> 5210.9697 | AJ39: Prob of default | AL39: =VLOOKUP(AL34,$AC$5:$AG$17,5) -> 0.003 | AM39: =VLOOKUP(AM34,$AC$5:$AG$17,5) -> 0.004 | AN39: =VLOOKUP(AN34,$AC$5:$AG$17,5) -> 0.004 | AO39: =VLOOKUP(AO34,$AC$5:$AG$17,5) -> 0.004 | AP39: =VLOOKUP(AP34,$AC$5:$AG$17,5) -> 0.004 | AQ39: =VLOOKUP(AQ34,$AC$5:$AG$17,5) -> 0.004 | AR39: =VLOOKUP(AR34,$AC$5:$AG$17,5) -> 0.004 | AS39: =VLOOKUP(AS34,$AC$5:$AG$17,5) -> 0.004 | ... AU39: =VLOOKUP(AU34,$AC$5:$AG$17,5) -> 0.004
B40: Sum (PVTS) | K40: =SUM(K39:U39) -> 11136.895 | AJ40: Cost of debt | AL40: =(1-AL39+AL39*$C$68)*(1+AL37)-1 -> 0.055328756 | AM40: =(1-AM39+AM39*$C$68)*(1+AM37)-1 -> 0.063184948 | AN40: =(1-AN39+AN39*$C$68)*(1+AN37)-1 -> 0.063184948 | AO40: =(1-AO39+AO39*$C$68)*(1+AO37)-1 -> 0.063184948 | AP40: =(1-AP39+AP39*$C$68)*(1+AP37)-1 -> 0.063184948 | AQ40: =(1-AQ39+AQ39*$C$68)*(1+AQ37)-1 -> 0.063184948 | AR40: =(1-AR39+AR39*$C$68)*(1+AR37)-1 -> 0.063184948 | AS40: =(1-AS39+AS39*$C$68)*(1+AS37)-1 -> 0.063184948 | ... AU40: =(1-AU39+AU39*$C$68)*(1+AU37)-1 -> 0.063184948
B41: PVTS (every year) | K41: =K36/(1+K38)+L36/((1+L38)^2)+M36/((1+M38)^3)+N36/((1+N38)^4)+O36/((1+O38)^5)+P36/((1+P38)^6)+Q36/((1+Q38)^7)+R36/((1+R38)^8)+S36/((1+S38)^9)+T36/((1+T38)^10)+U36/((1+U38)^11) -> 11136.895 | L41: =L36/(1+L38)+M36/((1+M38)^2)+N36/((1+N38)^3)+O36/((1+O38)^4)+P36/((1+P38)^5)+Q36/((1+Q38)^6)+R36/((1+R38)^7)+S36/((1+S38)^8)+T36/((1+T38)^9)+U36/((1+U38)^10) -> 11180.054 | M41: =M36/(1+M38)+N36/((1+N38)^2)+O36/((1+O38)^3)+P36/((1+P38)^4)+Q36/((1+Q38)^5)+R36/((1+R38)^6)+S36/((1+S38)^7)+T36/((1+T38)^8)+U36/((1+U38)^9) -> 11248.506 | N41: =N36/(1+N38)+O36/((1+O38)^2)+P36/((1+P38)^3)+Q36/((1+Q38)^4)+R36/((1+R38)^5)+S36/((1+S38)^6)+T36/((1+T38)^7)+U36/((1+U38)^8) -> 11330.027 | O41: =O36/(1+O38)+P36/((1+P38)^2)+Q36/((1+Q38)^3)+R36/((1+R38)^4)+S36/((1+S38)^5)+T36/((1+T38)^6)+U36/((1+U38)^7) -> 11423.829 | P41: =P36/(1+P38)+Q36/((1+Q38)^2)+R36/((1+R38)^3)+S36/((1+S38)^4)+T36/((1+T38)^5)+U36/((1+U38)^6) -> 11529.122 | Q41: =Q36/((1+Q38)^1)+R36/((1+R38)^2)+S36/((1+S38)^3)+T36/((1+T38)^4)+U36/((1+U38)^5) -> 11645.678 | R41: =+R36/((1+R38)^1)+S36/((1+S38)^2)+T36/((1+T38)^3)+U36/((1+U38)^4) -> 11774.986 | S41: =+S36/((1+S38)^1)+T36/((1+T38)^2)+U36/((1+U38)^3) -> 11916.641 | T41: =+T36/((1+T38)^1)+U36/((1+U38)^2) -> 12070.782 | U41: =+U36/((1+U38)^1) -> 12238.649
B43: Costs of Financial distress | AJ43: Year 2029 | AK43: Iteration 0 | AL43: Iteration 1 | AM43: Iteration 2 | AN43: Iteration 3 | AO43: Iteration 4 | AP43: Iteration 5 | AQ43: Iteration 6 | AR43: Iteration 7 | AS43: Iteration 8 | AT43: Iteration 9 | AU43: Iteration 10
B44: Risk neutral prob of default | K44: =($AU$6)/((1+$AU$7)*(1-$C$68)) -> 0.13145283 | L44: =($AU$16)/((1+$AU$17)*(1-$C$68)) -> 0.092391129 | M44: =($AU$26)/((1+$AU$27)*(1-$C$68)) -> 0.10323658 | N44: =($AU$36)/((1+$AU$37)*(1-$C$68)) -> 0.039760609 | O44: =($AU$46)/((1+$AU$47)*(1-$C$68)) -> 0.026452991 | P44: =($AU$56)/((1+$AU$57)*(1-$C$68)) -> 0.039760609 | Q44: =($AU$66)/((1+$AU$67)*(1-$C$68)) -> 0.026452991 | R44: =($AU$76)/((1+$AU$77)*(1-$C$68)) -> 0.026452991 | S44: =($AU$86)/((1+$AU$87)*(1-$C$68)) -> 0.026452991 | T44: =($AU$96)/((1+$AU$97)*(1-$C$68)) -> 0.026452991 | U44: =($AU$106)/((1+$AU$107)*(1-$C$68)) -> 0.026452991 | AJ44: Trailing interest coverage ratio | AL44: =MAX(MIN($N$13/AK48,100000),-100000) -> 4.3301211 | AM44: =MAX(MIN($N$13/AL48,100000),-100000) -> 3.2218634 | AN44: =MAX(MIN($N$13/AM48,100000),-100000) -> 3.0810477 | AO44: =MAX(MIN($N$13/AN48,100000),-100000) -> 3.0810477 | AP44: =MAX(MIN($N$13/AO48,100000),-100000) -> 3.0810477 | AQ44: =MAX(MIN($N$13/AP48,100000),-100000) -> 3.0810477 | AR44: =MAX(MIN($N$13/AQ48,100000),-100000) -> 3.0810477 | AS44: =MAX(MIN($N$13/AR48,100000),-100000) -> 3.0810477 | ... AU44: =MAX(MIN($N$13/AT48,100000),-100000) -> 3.0810477
B45: PV of distress costs (beginning of year) | K45: =(K44*($C$67)*K27+(1-K44)*L45)/(1+$C$64) -> 43855.372 | L45: =(L44*($C$67)*L27+(1-L44)*M45)/(1+$C$64) -> 35030.58 | M45: =(M44*($C$67)*M27+(1-M44)*N45)/(1+$C$64) -> 27922.654 | N45: =(N44*($C$67)*N27+(1-N44)*O45)/(1+$C$64) -> 17874.355 | O45: =(O44*($C$67)*O27+(1-O44)*P45)/(1+$C$64) -> 13901.388 | P45: =(P44/($C$67+$C$64))*$C$67*P27 -> 11110.28 | Q45: =(Q44/($C$67+$C$64))*$C$67*Q27 -> 7685.2424 | R45: =(R44/($C$67+$C$64))*$C$67*R27 -> 7974.8297 | S45: =(S44/($C$67+$C$64))*$C$67*S27 -> 8266.1928 | T45: =(T44/($C$67+$C$64))*$C$67*T27 -> 8558.0309 | U45: =(U44/($C$67+$C$64))*$C$67*U27 -> 8853.6237 | AJ45: Credit rating | AL45: =VLOOKUP(AL44,$AC$5:$AG$17,3) -> A | AM45: =VLOOKUP(AM44,$AC$5:$AG$17,3) -> A- | AN45: =VLOOKUP(AN44,$AC$5:$AG$17,3) -> A- | AO45: =VLOOKUP(AO44,$AC$5:$AG$17,3) -> A- | AP45: =VLOOKUP(AP44,$AC$5:$AG$17,3) -> A- | AQ45: =VLOOKUP(AQ44,$AC$5:$AG$17,3) -> A- | AR45: =VLOOKUP(AR44,$AC$5:$AG$17,3) -> A- | AS45: =VLOOKUP(AS44,$AC$5:$AG$17,3) -> A- | ... AU45: =VLOOKUP(AU44,$AC$5:$AG$17,3) -> A-
AJ46: Credit spread | AL46: =VLOOKUP(AL44,$AC$4:$AG$17,4) -> 0.014 | AM46: =VLOOKUP(AM44,$AC$4:$AG$17,4) -> 0.0165 | AN46: =VLOOKUP(AN44,$AC$4:$AG$17,4) -> 0.0165 | AO46: =VLOOKUP(AO44,$AC$4:$AG$17,4) -> 0.0165 | AP46: =VLOOKUP(AP44,$AC$4:$AG$17,4) -> 0.0165 | AQ46: =VLOOKUP(AQ44,$AC$4:$AG$17,4) -> 0.0165 | AR46: =VLOOKUP(AR44,$AC$4:$AG$17,4) -> 0.0165 | AS46: =VLOOKUP(AS44,$AC$4:$AG$17,4) -> 0.0165 | ... AU46: =VLOOKUP(AU44,$AC$4:$AG$17,4) -> 0.0165
B47: FINAL CALCULATION - APV METHOD | AJ47: Yield on debt | AL47: =AL46+$C$64 -> 0.0547 | AM47: =AM46+$C$64 -> 0.0572 | AN47: =AN46+$C$64 -> 0.0572 | AO47: =AO46+$C$64 -> 0.0572 | AP47: =AP46+$C$64 -> 0.0572 | AQ47: =AQ46+$C$64 -> 0.0572 | AR47: =AR46+$C$64 -> 0.0572 | AS47: =AS46+$C$64 -> 0.0572 | ... AU47: =AU46+$C$64 -> 0.0572
B48: Value of the firm | C48: 2025 | D48: 2026 | E48: 2027 | F48: 2028 | G48: 2029 | H48: 2030 | I48: 2031 | J48: 2032 | K48: 2033 | L48: 2034 | M48: 2035 | AJ48: Interest paid | AK48: =$C$64*$G$55 -> 2388.9614 | AL48: =$G$55*AL47 -> 3210.7171 | AM48: =$G$55*AM47 -> 3357.4592 | AN48: =$G$55*AN47 -> 3357.4592 | AO48: =$G$55*AO47 -> 3357.4592 | AP48: =$G$55*AP47 -> 3357.4592 | AQ48: =$G$55*AQ47 -> 3357.4592 | AR48: =$G$55*AR47 -> 3357.4592 | AS48: =$G$55*AS47 -> 3357.4592 | ... AU48: =$G$55*AU47 -> 3357.4592
B49: Value of unlevered firm | C49: =+K29 -> 247920 | D49: =+L29 -> 257661.98 | E49: =+M29 -> 270326.82 | F49: =+N29 -> 282949.25 | G49: =+O29 -> 295547.85 | H49: =+P29 -> 307987.14 | I49: =+Q29 -> 320220.82 | J49: =+R29 -> 332301.39 | ... M49: =+U29 -> 369003.41 | AJ49: Prob of default | AL49: =VLOOKUP(AL44,$AC$5:$AG$17,5) -> 0.002 | AM49: =VLOOKUP(AM44,$AC$5:$AG$17,5) -> 0.003 | AN49: =VLOOKUP(AN44,$AC$5:$AG$17,5) -> 0.003 | AO49: =VLOOKUP(AO44,$AC$5:$AG$17,5) -> 0.003 | AP49: =VLOOKUP(AP44,$AC$5:$AG$17,5) -> 0.003 | AQ49: =VLOOKUP(AQ44,$AC$5:$AG$17,5) -> 0.003 | AR49: =VLOOKUP(AR44,$AC$5:$AG$17,5) -> 0.003 | AS49: =VLOOKUP(AS44,$AC$5:$AG$17,5) -> 0.003 | ... AU49: =VLOOKUP(AU44,$AC$5:$AG$17,5) -> 0.003
B50: PV of tax shields | C50: =K40 -> 11136.895 | D50: =L41 -> 11180.054 | E50: =M41 -> 11248.506 | F50: =N41 -> 11330.027 | G50: =O41 -> 11423.829 | H50: =P41 -> 11529.122 | I50: =Q41 -> 11645.678 | J50: =R41 -> 11774.986 | K50: =S41 -> 11916.641 | ... M50: =U41 -> 12238.649 | AJ50: Cost of debt | AL50: =(1-AL49+AL49*$C$68)*(1+AL47)-1 -> 0.053455454 | AM50: =(1-AM49+AM49*$C$68)*(1+AM47)-1 -> 0.055328756 | AN50: =(1-AN49+AN49*$C$68)*(1+AN47)-1 -> 0.055328756 | AO50: =(1-AO49+AO49*$C$68)*(1+AO47)-1 -> 0.055328756 | AP50: =(1-AP49+AP49*$C$68)*(1+AP47)-1 -> 0.055328756 | AQ50: =(1-AQ49+AQ49*$C$68)*(1+AQ47)-1 -> 0.055328756 | AR50: =(1-AR49+AR49*$C$68)*(1+AR47)-1 -> 0.055328756 | AS50: =(1-AS49+AS49*$C$68)*(1+AS47)-1 -> 0.055328756 | ... AU50: =(1-AU49+AU49*$C$68)*(1+AU47)-1 -> 0.055328756
B51: PV of bankruptcy costs | C51: =K45 -> 43855.372 | D51: =L45 -> 35030.58 | E51: =M45 -> 27922.654 | F51: =N45 -> 17874.355 | G51: =O45 -> 13901.388 | H51: =P45 -> 11110.28 | I51: =Q45 -> 7685.2424 | J51: =R45 -> 7974.8297 | ... M51: =U45 -> 8853.6237
B52: Value of levered firm | C52: =C49+C50-C51 -> 215201.52 | D52: =D49+D50-D51 -> 233811.46 | E52: =E49+E50-E51 -> 253652.67 | F52: =F49+F50-F51 -> 276404.92 | G52: =G49+G50-G51 -> 293070.29 | H52: =H49+H50-H51 -> 308405.99 | I52: =I49+I50-I51 -> 324181.26 | J52: =J49+J50-J51 -> 336101.55 | ... M52: =M49+M50-M51 -> 372388.44
AJ53: Year 2030 | AK53: Iteration 0 | AL53: Iteration 1 | AM53: Iteration 2 | AN53: Iteration 3 | AO53: Iteration 4 | AP53: Iteration 5 | AQ53: Iteration 6 | AR53: Iteration 7 | AS53: Iteration 8 | AT53: Iteration 9 | AU53: Iteration 10
B54: LEVERAGE RATIO | C54: =+C55/C52 -> 0.1997356 | D54: =+D55/D52 -> 0.19976707 | E54: =+E55/E52 -> 0.19987818 | F54: =+F55/F52 -> 0.20007533 | G54: =+G55/G52 -> 0.20028246 | H54: =+H55/H52 -> 0.19855135 | I54: =+I55/I52 -> 0.19794053 | J54: =+J55/J52 -> 0.19747863 | ... M54: =+M55/M52 -> 0.20234282 | AJ54: Trailing interest coverage ratio | AL54: =MAX(MIN($O$13/AK58,100000),-100000) -> 4.109005 | AM54: =MAX(MIN($O$13/AL58,100000),-100000) -> 2.9237151 | AN54: =MAX(MIN($O$13/AM58,100000),-100000) -> 2.5454566 | AO54: =MAX(MIN($O$13/AN58,100000),-100000) -> 2.5454566 | AP54: =MAX(MIN($O$13/AO58,100000),-100000) -> 2.5454566 | AQ54: =MAX(MIN($O$13/AP58,100000),-100000) -> 2.5454566 | AR54: =MAX(MIN($O$13/AQ58,100000),-100000) -> 2.5454566 | AS54: =MAX(MIN($O$13/AR58,100000),-100000) -> 2.5454566 | ... AU54: =MAX(MIN($O$13/AT58,100000),-100000) -> 2.5454566
B55: Debt | C55: 42983.406 | D55: 46707.83 | E55: 50699.634 | F55: 55301.806 | G55: 58696.84 | H55: 61234.425 | I55: 64168.61 | J55: 66372.874 | K55: 68571.044 | L55: 72620.981 | M55: 75350.127 | AJ55: Credit rating | AL55: =VLOOKUP(AL54,$AC$5:$AG$17,3) -> A- | AM55: =VLOOKUP(AM54,$AC$5:$AG$17,3) -> BBB | AN55: =VLOOKUP(AN54,$AC$5:$AG$17,3) -> BBB | AO55: =VLOOKUP(AO54,$AC$5:$AG$17,3) -> BBB | AP55: =VLOOKUP(AP54,$AC$5:$AG$17,3) -> BBB | AQ55: =VLOOKUP(AQ54,$AC$5:$AG$17,3) -> BBB | AR55: =VLOOKUP(AR54,$AC$5:$AG$17,3) -> BBB | AS55: =VLOOKUP(AS54,$AC$5:$AG$17,3) -> BBB | ... AU55: =VLOOKUP(AU54,$AC$5:$AG$17,3) -> BBB
AJ56: Credit spread | AL56: =VLOOKUP(AL54,$AC$4:$AG$17,4) -> 0.0165 | AM56: =VLOOKUP(AM54,$AC$4:$AG$17,4) -> 0.025 | AN56: =VLOOKUP(AN54,$AC$4:$AG$17,4) -> 0.025 | AO56: =VLOOKUP(AO54,$AC$4:$AG$17,4) -> 0.025 | AP56: =VLOOKUP(AP54,$AC$4:$AG$17,4) -> 0.025 | AQ56: =VLOOKUP(AQ54,$AC$4:$AG$17,4) -> 0.025 | AR56: =VLOOKUP(AR54,$AC$4:$AG$17,4) -> 0.025 | AS56: =VLOOKUP(AS54,$AC$4:$AG$17,4) -> 0.025 | ... AU56: =VLOOKUP(AU54,$AC$4:$AG$17,4) -> 0.025
B57: Calculations to minimize OLS | C57: =+(C54-0.2)^2 -> 6.9907035e-08 | D57: =+(D54-0.2)^2 -> 5.4255368e-08 | E57: =+(E54-0.2)^2 -> 1.484034e-08 | F57: =+(F54-0.2)^2 -> 5.67442e-09 | G57: =+(G54-0.2)^2 -> 7.9785446e-08 | H57: =+(H54-0.2)^2 -> 2.0985839e-06 | I57: =+(I54-0.2)^2 -> 4.2414166e-06 | J57: =+(J54-0.2)^2 -> 6.3572842e-06 | ... M57: =+(M54-0.2)^2 -> 5.4888104e-06 | N57: =+SUM(C57:M57) -> 3.0202052e-05 | AJ57: Yield on debt | AL57: =AL56+$C$64 -> 0.0572 | AM57: =AM56+$C$64 -> 0.0657 | AN57: =AN56+$C$64 -> 0.0657 | AO57: =AO56+$C$64 -> 0.0657 | AP57: =AP56+$C$64 -> 0.0657 | AQ57: =AQ56+$C$64 -> 0.0657 | AR57: =AR56+$C$64 -> 0.0657 | AS57: =AS56+$C$64 -> 0.0657 | ... AU57: =AU56+$C$64 -> 0.0657
AJ58: Interest paid | AK58: =$C$64*$H$55 -> 2492.2411 | AL58: =$H$55*AL57 -> 3502.6091 | AM58: =$H$55*AM57 -> 4023.1017 | AN58: =$H$55*AN57 -> 4023.1017 | AO58: =$H$55*AO57 -> 4023.1017 | AP58: =$H$55*AP57 -> 4023.1017 | AQ58: =$H$55*AQ57 -> 4023.1017 | AR58: =$H$55*AR57 -> 4023.1017 | AS58: =$H$55*AS57 -> 4023.1017 | ... AU58: =$H$55*AU57 -> 4023.1017
AJ59: Prob of default | AL59: =VLOOKUP(AL54,$AC$5:$AG$17,5) -> 0.003 | AM59: =VLOOKUP(AM54,$AC$5:$AG$17,5) -> 0.004 | AN59: =VLOOKUP(AN54,$AC$5:$AG$17,5) -> 0.004 | AO59: =VLOOKUP(AO54,$AC$5:$AG$17,5) -> 0.004 | AP59: =VLOOKUP(AP54,$AC$5:$AG$17,5) -> 0.004 | AQ59: =VLOOKUP(AQ54,$AC$5:$AG$17,5) -> 0.004 | AR59: =VLOOKUP(AR54,$AC$5:$AG$17,5) -> 0.004 | AS59: =VLOOKUP(AS54,$AC$5:$AG$17,5) -> 0.004 | ... AU59: =VLOOKUP(AU54,$AC$5:$AG$17,5) -> 0.004
B60: ASSUMPTIONS | AJ60: Cost of debt | AL60: =(1-AL59+AL59*$C$68)*(1+AL57)-1 -> 0.055328756 | AM60: =(1-AM59+AM59*$C$68)*(1+AM57)-1 -> 0.063184948 | AN60: =(1-AN59+AN59*$C$68)*(1+AN57)-1 -> 0.063184948 | AO60: =(1-AO59+AO59*$C$68)*(1+AO57)-1 -> 0.063184948 | AP60: =(1-AP59+AP59*$C$68)*(1+AP57)-1 -> 0.063184948 | AQ60: =(1-AQ59+AQ59*$C$68)*(1+AQ57)-1 -> 0.063184948 | AR60: =(1-AR59+AR59*$C$68)*(1+AR57)-1 -> 0.063184948 | AS60: =(1-AS59+AS59*$C$68)*(1+AS57)-1 -> 0.063184948 | ... AU60: =(1-AU59+AU59*$C$68)*(1+AU57)-1 -> 0.063184948
B62: Tax rate | C62: =-U19 -> 0.16484584 | D62: From the mean of the effective tax rate of historical years
B63: Unlevered cost of capital | C63: =+'Unlevered Cost of Capital'!D27 -> 0.092574006 | D63: From "Unlevered Cost of capital" | AJ63: Year 2031 | AK63: Iteration 0 | AL63: Iteration 1 | AM63: Iteration 2 | AN63: Iteration 3 | AO63: Iteration 4 | AP63: Iteration 5 | AQ63: Iteration 6 | AR63: Iteration 7 | AS63: Iteration 8 | AT63: Iteration 9 | AU63: Iteration 10
B64: Risk-Free Rate | C64: =+'Unlevered Cost of Capital'!D24 -> 0.0407 | AJ64: Trailing interest coverage ratio | AL64: =MAX(MIN($P$13/AK68,100000),-100000) -> 4.639657 | AM64: =MAX(MIN($P$13/AL68,100000),-100000) -> 3.4521763 | AN64: =MAX(MIN($P$13/AM68,100000),-100000) -> 3.3012944 | AO64: =MAX(MIN($P$13/AN68,100000),-100000) -> 3.3012944 | AP64: =MAX(MIN($P$13/AO68,100000),-100000) -> 3.3012944 | AQ64: =MAX(MIN($P$13/AP68,100000),-100000) -> 3.3012944 | AR64: =MAX(MIN($P$13/AQ68,100000),-100000) -> 3.3012944 | AS64: =MAX(MIN($P$13/AR68,100000),-100000) -> 3.3012944 | ... AU64: =MAX(MIN($P$13/AT68,100000),-100000) -> 3.3012944
B65: Market Risk Premium | C65: =+'Unlevered Cost of Capital'!D25 -> 0.042479688 | AJ65: Credit rating | AL65: =VLOOKUP(AL64,$AC$5:$AG$17,3) -> A | AM65: =VLOOKUP(AM64,$AC$5:$AG$17,3) -> A- | AN65: =VLOOKUP(AN64,$AC$5:$AG$17,3) -> A- | AO65: =VLOOKUP(AO64,$AC$5:$AG$17,3) -> A- | AP65: =VLOOKUP(AP64,$AC$5:$AG$17,3) -> A- | AQ65: =VLOOKUP(AQ64,$AC$5:$AG$17,3) -> A- | AR65: =VLOOKUP(AR64,$AC$5:$AG$17,3) -> A- | AS65: =VLOOKUP(AS64,$AC$5:$AG$17,3) -> A- | ... AU65: =VLOOKUP(AU64,$AC$5:$AG$17,3) -> A-
B66: Debt issued 2024 | AJ66: Credit spread | AL66: =VLOOKUP(AL64,$AC$4:$AG$17,4) -> 0.014 | AM66: =VLOOKUP(AM64,$AC$4:$AG$17,4) -> 0.0165 | AN66: =VLOOKUP(AN64,$AC$4:$AG$17,4) -> 0.0165 | AO66: =VLOOKUP(AO64,$AC$4:$AG$17,4) -> 0.0165 | AP66: =VLOOKUP(AP64,$AC$4:$AG$17,4) -> 0.0165 | AQ66: =VLOOKUP(AQ64,$AC$4:$AG$17,4) -> 0.0165 | AR66: =VLOOKUP(AR64,$AC$4:$AG$17,4) -> 0.0165 | AS66: =VLOOKUP(AS64,$AC$4:$AG$17,4) -> 0.0165 | ... AU66: =VLOOKUP(AU64,$AC$4:$AG$17,4) -> 0.0165
B67: Bakruptcy cost as % of firm value | C67: 0.474 | D67: From data coming from professor guidelines Appendix “Fraction of Unlevered firm value lost in bankruptcy“, line chosen “Other” | AJ67: Yield on debt | AL67: =AL66+$C$64 -> 0.0547 | AM67: =AM66+$C$64 -> 0.0572 | AN67: =AN66+$C$64 -> 0.0572 | AO67: =AO66+$C$64 -> 0.0572 | AP67: =AP66+$C$64 -> 0.0572 | AQ67: =AQ66+$C$64 -> 0.0572 | AR67: =AR66+$C$64 -> 0.0572 | AS67: =AS66+$C$64 -> 0.0572 | ... AU67: =AU66+$C$64 -> 0.0572
B68: Recovery in case of default | C68: 0.41 | D68: We assume is the same use in the exercise in class, as advised by the professor | AJ68: Interest paid | AK68: =$C$64*$I$55 -> 2611.6624 | AL68: =$I$55*AL67 -> 3510.023 | AM68: =$I$55*AM67 -> 3670.4445 | AN68: =$I$55*AN67 -> 3670.4445 | AO68: =$I$55*AO67 -> 3670.4445 | AP68: =$I$55*AP67 -> 3670.4445 | AQ68: =$I$55*AQ67 -> 3670.4445 | AR68: =$I$55*AR67 -> 3670.4445 | AS68: =$I$55*AS67 -> 3670.4445 | ... AU68: =$I$55*AU67 -> 3670.4445
B69: Long term growth rate | C69: 0.034292077 | AJ69: Prob of default | AL69: =VLOOKUP(AL64,$AC$5:$AG$17,5) -> 0.002 | AM69: =VLOOKUP(AM64,$AC$5:$AG$17,5) -> 0.003 | AN69: =VLOOKUP(AN64,$AC$5:$AG$17,5) -> 0.003 | AO69: =VLOOKUP(AO64,$AC$5:$AG$17,5) -> 0.003 | AP69: =VLOOKUP(AP64,$AC$5:$AG$17,5) -> 0.003 | AQ69: =VLOOKUP(AQ64,$AC$5:$AG$17,5) -> 0.003 | AR69: =VLOOKUP(AR64,$AC$5:$AG$17,5) -> 0.003 | AS69: =VLOOKUP(AS64,$AC$5:$AG$17,5) -> 0.003 | ... AU69: =VLOOKUP(AU64,$AC$5:$AG$17,5) -> 0.003
AJ70: Cost of debt | AL70: =(1-AL69+AL69*$C$68)*(1+AL67)-1 -> 0.053455454 | AM70: =(1-AM69+AM69*$C$68)*(1+AM67)-1 -> 0.055328756 | AN70: =(1-AN69+AN69*$C$68)*(1+AN67)-1 -> 0.055328756 | AO70: =(1-AO69+AO69*$C$68)*(1+AO67)-1 -> 0.055328756 | AP70: =(1-AP69+AP69*$C$68)*(1+AP67)-1 -> 0.055328756 | AQ70: =(1-AQ69+AQ69*$C$68)*(1+AQ67)-1 -> 0.055328756 | AR70: =(1-AR69+AR69*$C$68)*(1+AR67)-1 -> 0.055328756 | AS70: =(1-AS69+AS69*$C$68)*(1+AS67)-1 -> 0.055328756 | ... AU70: =(1-AU69+AU69*$C$68)*(1+AU67)-1 -> 0.055328756
AJ73: Year 2032 | AK73: Iteration 0 | AL73: Iteration 1 | AM73: Iteration 2 | AN73: Iteration 3 | AO73: Iteration 4 | AP73: Iteration 5 | AQ73: Iteration 6 | AR73: Iteration 7 | AS73: Iteration 8 | AT73: Iteration 9 | AU73: Iteration 10
B74: Is the transaction creating value for shareholders? | AJ74: Trailing interest coverage ratio | AL74: =MAX(MIN($Q$13/AK78,100000),-100000) -> 4.8270551 | AM74: =MAX(MIN($Q$13/AL78,100000),-100000) -> 3.5916114 | AN74: =MAX(MIN($Q$13/AM78,100000),-100000) -> 3.4346354 | AO74: =MAX(MIN($Q$13/AN78,100000),-100000) -> 3.4346354 | AP74: =MAX(MIN($Q$13/AO78,100000),-100000) -> 3.4346354 | AQ74: =MAX(MIN($Q$13/AP78,100000),-100000) -> 3.4346354 | AR74: =MAX(MIN($Q$13/AQ78,100000),-100000) -> 3.4346354 | AS74: =MAX(MIN($Q$13/AR78,100000),-100000) -> 3.4346354 | ... AU74: =MAX(MIN($Q$13/AT78,100000),-100000) -> 3.4346354
C75: 2025 | D75: 2026 | E75: 2027 | F75: 2028 | G75: 2029 | H75: 2030 | I75: 2031 | J75: 2032 | K75: 2033 | L75: 2034 | M75: 2035 | AJ75: Credit rating | AL75: =VLOOKUP(AL74,$AC$5:$AG$17,3) -> A | AM75: =VLOOKUP(AM74,$AC$5:$AG$17,3) -> A- | AN75: =VLOOKUP(AN74,$AC$5:$AG$17,3) -> A- | AO75: =VLOOKUP(AO74,$AC$5:$AG$17,3) -> A- | AP75: =VLOOKUP(AP74,$AC$5:$AG$17,3) -> A- | AQ75: =VLOOKUP(AQ74,$AC$5:$AG$17,3) -> A- | AR75: =VLOOKUP(AR74,$AC$5:$AG$17,3) -> A- | AS75: =VLOOKUP(AS74,$AC$5:$AG$17,3) -> A- | ... AU75: =VLOOKUP(AU74,$AC$5:$AG$17,3) -> A-
B76: Value of the Unlevered Firm | C76: {=C49:M49} -> 247920 | D76: 257661.98 | E76: 270326.82 | F76: 282949.25 | G76: 295547.85 | H76: 307987.14 | I76: 320220.82 | J76: 332301.39 | K76: 344462.72 | L76: 356651.74 | M76: 369003.41 | AJ76: Credit spread | AL76: =VLOOKUP(AL74,$AC$5:$AG$17,4) -> 0.014 | AM76: =VLOOKUP(AM74,$AC$5:$AG$17,4) -> 0.0165 | AN76: =VLOOKUP(AN74,$AC$5:$AG$17,4) -> 0.0165 | AO76: =VLOOKUP(AO74,$AC$5:$AG$17,4) -> 0.0165 | AP76: =VLOOKUP(AP74,$AC$5:$AG$17,4) -> 0.0165 | AQ76: =VLOOKUP(AQ74,$AC$5:$AG$17,4) -> 0.0165 | AR76: =VLOOKUP(AR74,$AC$5:$AG$17,4) -> 0.0165 | AS76: =VLOOKUP(AS74,$AC$5:$AG$17,4) -> 0.0165 | ... AU76: =VLOOKUP(AU74,$AC$5:$AG$17,4) -> 0.0165
B77: Value of the Levered Firm | C77: {=C52:M52} -> 215201.52 | D77: 233811.46 | E77: 253652.67 | F77: 276404.92 | G77: 293070.29 | H77: 308405.99 | I77: 324181.26 | J77: 336101.55 | K77: 348113.17 | L77: 360164.49 | M77: 372388.44 | AJ77: Yield on debt | AL77: =AL76+$C$64 -> 0.0547 | AM77: =AM76+$C$64 -> 0.0572 | AN77: =AN76+$C$64 -> 0.0572 | AO77: =AO76+$C$64 -> 0.0572 | AP77: =AP76+$C$64 -> 0.0572 | AQ77: =AQ76+$C$64 -> 0.0572 | AR77: =AR76+$C$64 -> 0.0572 | AS77: =AS76+$C$64 -> 0.0572 | ... AU77: =AU76+$C$64 -> 0.0572
AJ78: Interest paid | AK78: =+$J$55*$C$64 -> 2701.376 | AL78: =$J$55*AL77 -> 3630.5962 | AM78: =$J$55*AM77 -> 3796.5284 | AN78: =$J$55*AN77 -> 3796.5284 | AO78: =$J$55*AO77 -> 3796.5284 | AP78: =$J$55*AP77 -> 3796.5284 | AQ78: =$J$55*AQ77 -> 3796.5284 | AR78: =$J$55*AR77 -> 3796.5284 | AS78: =$J$55*AS77 -> 3796.5284 | ... AU78: =$J$55*AU77 -> 3796.5284
AJ79: Prob of default | AL79: =VLOOKUP(AL74,$AC$5:$AG$17,5) -> 0.002 | AM79: =VLOOKUP(AM74,$AC$5:$AG$17,5) -> 0.003 | AN79: =VLOOKUP(AN74,$AC$5:$AG$17,5) -> 0.003 | AO79: =VLOOKUP(AO74,$AC$5:$AG$17,5) -> 0.003 | AP79: =VLOOKUP(AP74,$AC$5:$AG$17,5) -> 0.003 | AQ79: =VLOOKUP(AQ74,$AC$5:$AG$17,5) -> 0.003 | AR79: =VLOOKUP(AR74,$AC$5:$AG$17,5) -> 0.003 | AS79: =VLOOKUP(AS74,$AC$5:$AG$17,5) -> 0.003 | ... AU79: =VLOOKUP(AU74,$AC$5:$AG$17,5) -> 0.003
AJ80: Cost of debt | AL80: =(1-AL79+AL79*$C$68)*(1+AL77)-1 -> 0.053455454 | AM80: =(1-AM79+AM79*$C$68)*(1+AM77)-1 -> 0.055328756 | AN80: =(1-AN79+AN79*$C$68)*(1+AN77)-1 -> 0.055328756 | AO80: =(1-AO79+AO79*$C$68)*(1+AO77)-1 -> 0.055328756 | AP80: =(1-AP79+AP79*$C$68)*(1+AP77)-1 -> 0.055328756 | AQ80: =(1-AQ79+AQ79*$C$68)*(1+AQ77)-1 -> 0.055328756 | AR80: =(1-AR79+AR79*$C$68)*(1+AR77)-1 -> 0.055328756 | AS80: =(1-AS79+AS79*$C$68)*(1+AS77)-1 -> 0.055328756 | ... AU80: =(1-AU79+AU79*$C$68)*(1+AU77)-1 -> 0.055328756
AJ83: Year 2033 | AK83: Iteration 0 | AL83: Iteration 1 | AM83: Iteration 2 | AN83: Iteration 3 | AO83: Iteration 4 | AP83: Iteration 5 | AQ83: Iteration 6 | AR83: Iteration 7 | AS83: Iteration 8 | AT83: Iteration 9 | AU83: Iteration 10
AJ84: Trailing interest coverage ratio | AL84: =MAX(MIN($R$13/AK88,100000),-100000) -> 4.9199815 | AM84: =MAX(MIN($R$13/AL88,100000),-100000) -> 3.660754 | AN84: =MAX(MIN($R$13/AM88,100000),-100000) -> 3.500756 | AO84: =MAX(MIN($R$13/AN88,100000),-100000) -> 3.500756 | AP84: =MAX(MIN($R$13/AO88,100000),-100000) -> 3.500756 | AQ84: =MAX(MIN($R$13/AP88,100000),-100000) -> 3.500756 | AR84: =MAX(MIN($R$13/AQ88,100000),-100000) -> 3.500756 | AS84: =MAX(MIN($R$13/AR88,100000),-100000) -> 3.500756 | ... AU84: =MAX(MIN($R$13/AT88,100000),-100000) -> 3.500756
AJ85: Credit rating | AL85: =VLOOKUP(AL84,$AC$5:$AG$17,3) -> A | AM85: =VLOOKUP(AM84,$AC$5:$AG$17,3) -> A- | AN85: =VLOOKUP(AN84,$AC$5:$AG$17,3) -> A- | AO85: =VLOOKUP(AO84,$AC$5:$AG$17,3) -> A- | AP85: =VLOOKUP(AP84,$AC$5:$AG$17,3) -> A- | AQ85: =VLOOKUP(AQ84,$AC$5:$AG$17,3) -> A- | AR85: =VLOOKUP(AR84,$AC$5:$AG$17,3) -> A- | AS85: =VLOOKUP(AS84,$AC$5:$AG$17,3) -> A- | ... AU85: =VLOOKUP(AU84,$AC$5:$AG$17,3) -> A-
AJ86: Credit spread | AL86: =VLOOKUP(AL84,$AC$5:$AG$17,4) -> 0.014 | AM86: =VLOOKUP(AM84,$AC$5:$AG$17,4) -> 0.0165 | AN86: =VLOOKUP(AN84,$AC$5:$AG$17,4) -> 0.0165 | AO86: =VLOOKUP(AO84,$AC$5:$AG$17,4) -> 0.0165 | AP86: =VLOOKUP(AP84,$AC$5:$AG$17,4) -> 0.0165 | AQ86: =VLOOKUP(AQ84,$AC$5:$AG$17,4) -> 0.0165 | AR86: =VLOOKUP(AR84,$AC$5:$AG$17,4) -> 0.0165 | AS86: =VLOOKUP(AS84,$AC$5:$AG$17,4) -> 0.0165 | ... AU86: =VLOOKUP(AU84,$AC$5:$AG$17,4) -> 0.0165
AJ87: Yield on debt | AL87: =AL86+$C$64 -> 0.0547 | AM87: =AM86+$C$64 -> 0.0572 | AN87: =AN86+$C$64 -> 0.0572 | AO87: =AO86+$C$64 -> 0.0572 | AP87: =AP86+$C$64 -> 0.0572 | AQ87: =AQ86+$C$64 -> 0.0572 | AR87: =AR86+$C$64 -> 0.0572 | AS87: =AS86+$C$64 -> 0.0572 | ... AU87: =AU86+$C$64 -> 0.0572
AJ88: Interest paid | AK88: =$C$64*$K$55 -> 2790.8415 | AL88: =$K$55*AL87 -> 3750.8361 | AM88: =$K$55*AM87 -> 3922.2637 | AN88: =$K$55*AN87 -> 3922.2637 | AO88: =$K$55*AO87 -> 3922.2637 | AP88: =$K$55*AP87 -> 3922.2637 | AQ88: =$K$55*AQ87 -> 3922.2637 | AR88: =$K$55*AR87 -> 3922.2637 | AS88: =$K$55*AS87 -> 3922.2637 | ... AU88: =$K$55*AU87 -> 3922.2637
AJ89: Prob of default | AL89: =VLOOKUP(AL84,$AC$5:$AG$17,5) -> 0.002 | AM89: =VLOOKUP(AM84,$AC$5:$AG$17,5) -> 0.003 | AN89: =VLOOKUP(AN84,$AC$5:$AG$17,5) -> 0.003 | AO89: =VLOOKUP(AO84,$AC$5:$AG$17,5) -> 0.003 | AP89: =VLOOKUP(AP84,$AC$5:$AG$17,5) -> 0.003 | AQ89: =VLOOKUP(AQ84,$AC$5:$AG$17,5) -> 0.003 | AR89: =VLOOKUP(AR84,$AC$5:$AG$17,5) -> 0.003 | AS89: =VLOOKUP(AS84,$AC$5:$AG$17,5) -> 0.003 | ... AU89: =VLOOKUP(AU84,$AC$5:$AG$17,5) -> 0.003
AJ90: Cost of debt | AL90: =(1-AL89+AL89*$C$68)*(1+AL87)-1 -> 0.053455454 | AM90: =(1-AM89+AM89*$C$68)*(1+AM87)-1 -> 0.055328756 | AN90: =(1-AN89+AN89*$C$68)*(1+AN87)-1 -> 0.055328756 | AO90: =(1-AO89+AO89*$C$68)*(1+AO87)-1 -> 0.055328756 | AP90: =(1-AP89+AP89*$C$68)*(1+AP87)-1 -> 0.055328756 | AQ90: =(1-AQ89+AQ89*$C$68)*(1+AQ87)-1 -> 0.055328756 | AR90: =(1-AR89+AR89*$C$68)*(1+AR87)-1 -> 0.055328756 | AS90: =(1-AS89+AS89*$C$68)*(1+AS87)-1 -> 0.055328756 | ... AU90: =(1-AU89+AU89*$C$68)*(1+AU87)-1 -> 0.055328756
AJ93: Year 2034 | AK93: Iteration 0 | AL93: Iteration 1 | AM93: Iteration 2 | AN93: Iteration 3 | AO93: Iteration 4 | AP93: Iteration 5 | AQ93: Iteration 6 | AR93: Iteration 7 | AS93: Iteration 8 | AT93: Iteration 9 | AU93: Iteration 10
AJ94: Trailing interest coverage ratio | AL94: =MAX(MIN($S$13/AK98,100000),-100000) -> 4.952084 | AM94: =MAX(MIN($S$13/AL98,100000),-100000) -> 3.6846402 | AN94: =MAX(MIN($S$13/AM98,100000),-100000) -> 3.5235982 | AO94: =MAX(MIN($S$13/AN98,100000),-100000) -> 3.5235982 | AP94: =MAX(MIN($S$13/AO98,100000),-100000) -> 3.5235982 | AQ94: =MAX(MIN($S$13/AP98,100000),-100000) -> 3.5235982 | AR94: =MAX(MIN($S$13/AQ98,100000),-100000) -> 3.5235982 | AS94: =MAX(MIN($S$13/AR98,100000),-100000) -> 3.5235982 | ... AU94: =MAX(MIN($S$13/AT98,100000),-100000) -> 3.5235982
AJ95: Credit rating | AL95: =VLOOKUP(AL94,$AC$5:$AG$17,3) -> A | AM95: =VLOOKUP(AM94,$AC$5:$AG$17,3) -> A- | AN95: =VLOOKUP(AN94,$AC$5:$AG$17,3) -> A- | AO95: =VLOOKUP(AO94,$AC$5:$AG$17,3) -> A- | AP95: =VLOOKUP(AP94,$AC$5:$AG$17,3) -> A- | AQ95: =VLOOKUP(AQ94,$AC$5:$AG$17,3) -> A- | AR95: =VLOOKUP(AR94,$AC$5:$AG$17,3) -> A- | AS95: =VLOOKUP(AS94,$AC$5:$AG$17,3) -> A- | ... AU95: =VLOOKUP(AU94,$AC$5:$AG$17,3) -> A-
AJ96: Credit spread | AL96: =VLOOKUP(AL94,$AC$4:$AG$17,4) -> 0.014 | AM96: =VLOOKUP(AM94,$AC$4:$AG$17,4) -> 0.0165 | AN96: =VLOOKUP(AN94,$AC$4:$AG$17,4) -> 0.0165 | AO96: =VLOOKUP(AO94,$AC$4:$AG$17,4) -> 0.0165 | AP96: =VLOOKUP(AP94,$AC$4:$AG$17,4) -> 0.0165 | AQ96: =VLOOKUP(AQ94,$AC$4:$AG$17,4) -> 0.0165 | AR96: =VLOOKUP(AR94,$AC$4:$AG$17,4) -> 0.0165 | AS96: =VLOOKUP(AS94,$AC$4:$AG$17,4) -> 0.0165 | ... AU96: =VLOOKUP(AU94,$AC$4:$AG$17,4) -> 0.0165
AJ97: Yield on debt | AL97: =AL96+$C$64 -> 0.0547 | AM97: =AM96+$C$64 -> 0.0572 | AN97: =AN96+$C$64 -> 0.0572 | AO97: =AO96+$C$64 -> 0.0572 | AP97: =AP96+$C$64 -> 0.0572 | AQ97: =AQ96+$C$64 -> 0.0572 | AR97: =AR96+$C$64 -> 0.0572 | AS97: =AS96+$C$64 -> 0.0572 | ... AU97: =AU96+$C$64 -> 0.0572
AJ98: Interest paid | AK98: =$C$64*$L$55 -> 2955.6739 | AL98: =$L$55*AL97 -> 3972.3677 | AM98: =$L$55*AM97 -> 4153.9201 | AN98: =$L$55*AN97 -> 4153.9201 | AO98: =$L$55*AO97 -> 4153.9201 | AP98: =$L$55*AP97 -> 4153.9201 | AQ98: =$L$55*AQ97 -> 4153.9201 | AR98: =$L$55*AR97 -> 4153.9201 | AS98: =$L$55*AS97 -> 4153.9201 | ... AU98: =$L$55*AU97 -> 4153.9201
AJ99: Prob of default | AL99: =VLOOKUP(AL94,$AC$5:$AG$17,5) -> 0.002 | AM99: =VLOOKUP(AM94,$AC$5:$AG$17,5) -> 0.003 | AN99: =VLOOKUP(AN94,$AC$5:$AG$17,5) -> 0.003 | AO99: =VLOOKUP(AO94,$AC$5:$AG$17,5) -> 0.003 | AP99: =VLOOKUP(AP94,$AC$5:$AG$17,5) -> 0.003 | AQ99: =VLOOKUP(AQ94,$AC$5:$AG$17,5) -> 0.003 | AR99: =VLOOKUP(AR94,$AC$5:$AG$17,5) -> 0.003 | AS99: =VLOOKUP(AS94,$AC$5:$AG$17,5) -> 0.003 | ... AU99: =VLOOKUP(AU94,$AC$5:$AG$17,5) -> 0.003
AJ100: Cost of debt | AL100: =(1-AL99+AL99*$C$68)*(1+AL97)-1 -> 0.053455454 | AM100: =(1-AM99+AM99*$C$68)*(1+AM97)-1 -> 0.055328756 | AN100: =(1-AN99+AN99*$C$68)*(1+AN97)-1 -> 0.055328756 | AO100: =(1-AO99+AO99*$C$68)*(1+AO97)-1 -> 0.055328756 | AP100: =(1-AP99+AP99*$C$68)*(1+AP97)-1 -> 0.055328756 | AQ100: =(1-AQ99+AQ99*$C$68)*(1+AQ97)-1 -> 0.055328756 | AR100: =(1-AR99+AR99*$C$68)*(1+AR97)-1 -> 0.055328756 | AS100: =(1-AS99+AS99*$C$68)*(1+AS97)-1 -> 0.055328756 | ... AU100: =(1-AU99+AU99*$C$68)*(1+AU97)-1 -> 0.055328756
AJ103: Year 2035 | AK103: Iteration 0 | AL103: Iteration 1 | AM103: Iteration 2 | AN103: Iteration 3 | AO103: Iteration 4 | AP103: Iteration 5 | AQ103: Iteration 6 | AR103: Iteration 7 | AS103: Iteration 8 | AT103: Iteration 9 | AU103: Iteration 10
AJ104: Trailing interest coverage ratio | AL104: =MAX(MIN($T$13/AK108,100000),-100000) -> 5.0036711 | AM104: =MAX(MIN($T$13/AL108,100000),-100000) -> 3.723024 | AN104: =MAX(MIN($T$13/AM108,100000),-100000) -> 3.5603045 | AO104: =MAX(MIN($T$13/AN108,100000),-100000) -> 3.5603045 | AP104: =MAX(MIN($T$13/AO108,100000),-100000) -> 3.5603045 | AQ104: =MAX(MIN($T$13/AP108,100000),-100000) -> 3.5603045 | AR104: =MAX(MIN($T$13/AQ108,100000),-100000) -> 3.5603045 | AS104: =MAX(MIN($T$13/AR108,100000),-100000) -> 3.5603045 | ... AU104: =MAX(MIN($T$13/AT108,100000),-100000) -> 3.5603045
AJ105: Credit rating | AL105: =VLOOKUP(AL104,$AC$5:$AG$17,3) -> A | AM105: =VLOOKUP(AM104,$AC$5:$AG$17,3) -> A- | AN105: =VLOOKUP(AN104,$AC$5:$AG$17,3) -> A- | AO105: =VLOOKUP(AO104,$AC$5:$AG$17,3) -> A- | AP105: =VLOOKUP(AP104,$AC$5:$AG$17,3) -> A- | AQ105: =VLOOKUP(AQ104,$AC$5:$AG$17,3) -> A- | AR105: =VLOOKUP(AR104,$AC$5:$AG$17,3) -> A- | AS105: =VLOOKUP(AS104,$AC$5:$AG$17,3) -> A- | ... AU105: =VLOOKUP(AU104,$AC$5:$AG$17,3) -> A-
AJ106: Credit spread | AL106: =VLOOKUP(AL104,$AC$4:$AG$17,4) -> 0.014 | AM106: =VLOOKUP(AM104,$AC$4:$AG$17,4) -> 0.0165 | AN106: =VLOOKUP(AN104,$AC$4:$AG$17,4) -> 0.0165 | AO106: =VLOOKUP(AO104,$AC$4:$AG$17,4) -> 0.0165 | AP106: =VLOOKUP(AP104,$AC$4:$AG$17,4) -> 0.0165 | AQ106: =VLOOKUP(AQ104,$AC$4:$AG$17,4) -> 0.0165 | AR106: =VLOOKUP(AR104,$AC$4:$AG$17,4) -> 0.0165 | AS106: =VLOOKUP(AS104,$AC$4:$AG$17,4) -> 0.0165 | ... AU106: =VLOOKUP(AU104,$AC$4:$AG$17,4) -> 0.0165
AJ107: Yield on debt | AL107: =AL106+$C$64 -> 0.0547 | AM107: =AM106+$C$64 -> 0.0572 | AN107: =AN106+$C$64 -> 0.0572 | AO107: =AO106+$C$64 -> 0.0572 | AP107: =AP106+$C$64 -> 0.0572 | AQ107: =AQ106+$C$64 -> 0.0572 | AR107: =AR106+$C$64 -> 0.0572 | AS107: =AS106+$C$64 -> 0.0572 | ... AU107: =AU106+$C$64 -> 0.0572
AJ108: Interest paid | AK108: =$C$64*$M$55 -> 3066.7502 | AL108: =$M$55*AL107 -> 4121.652 | AM108: =$M$55*AM107 -> 4310.0273 | AN108: =$M$55*AN107 -> 4310.0273 | AO108: =$M$55*AO107 -> 4310.0273 | AP108: =$M$55*AP107 -> 4310.0273 | AQ108: =$M$55*AQ107 -> 4310.0273 | AR108: =$M$55*AR107 -> 4310.0273 | AS108: =$M$55*AS107 -> 4310.0273 | ... AU108: =$M$55*AU107 -> 4310.0273
AJ109: Prob of default | AL109: =VLOOKUP(AL104,$AC$5:$AG$17,5) -> 0.002 | AM109: =VLOOKUP(AM104,$AC$5:$AG$17,5) -> 0.003 | AN109: =VLOOKUP(AN104,$AC$5:$AG$17,5) -> 0.003 | AO109: =VLOOKUP(AO104,$AC$5:$AG$17,5) -> 0.003 | AP109: =VLOOKUP(AP104,$AC$5:$AG$17,5) -> 0.003 | AQ109: =VLOOKUP(AQ104,$AC$5:$AG$17,5) -> 0.003 | AR109: =VLOOKUP(AR104,$AC$5:$AG$17,5) -> 0.003 | AS109: =VLOOKUP(AS104,$AC$5:$AG$17,5) -> 0.003 | ... AU109: =VLOOKUP(AU104,$AC$5:$AG$17,5) -> 0.003
AJ110: Cost of debt | AL110: =(1-AL109+AL109*$C$68)*(1+AL107)-1 -> 0.053455454 | AM110: =(1-AM109+AM109*$C$68)*(1+AM107)-1 -> 0.055328756 | AN110: =(1-AN109+AN109*$C$68)*(1+AN107)-1 -> 0.055328756 | AO110: =(1-AO109+AO109*$C$68)*(1+AO107)-1 -> 0.055328756 | AP110: =(1-AP109+AP109*$C$68)*(1+AP107)-1 -> 0.055328756 | AQ110: =(1-AQ109+AQ109*$C$68)*(1+AQ107)-1 -> 0.055328756 | AR110: =(1-AR109+AR109*$C$68)*(1+AR107)-1 -> 0.055328756 | AS110: =(1-AS109+AS109*$C$68)*(1+AS107)-1 -> 0.055328756 | ... AU110: =(1-AU109+AU109*$C$68)*(1+AU107)-1 -> 0.055328756

Sheet Bonds
C1: DEBT INCREASE/YEAR | D1: 2025 | E1: 2026 | F1: 2027 | G1: 2028 | H1: 2029 | I1: 2030 | J1: 2031 | K1: 2032 | L1: 2033 | M1: 2034 | N1: 2035
C2: Debt | D2: =+'Leverage finale'!C55 -> 42983.406 | E2: =+'Leverage finale'!D55 -> 46707.83 | F2: =+'Leverage finale'!E55 -> 50699.634 | G2: =+'Leverage finale'!F55 -> 55301.806 | H2: =+'Leverage finale'!G55 -> 58696.84 | I2: =+'Leverage finale'!H55 -> 61234.425 | J2: =+'Leverage finale'!I55 -> 64168.61 | K2: =+'Leverage finale'!J55 -> 66372.874 | ... N2: =+'Leverage finale'!M55 -> 75350.127
C3: Amount for bond issuance (in million) | D3: =+D2 -> 42983.406 | E3: =+E2-D2 -> 3724.4243 | F3: =+F2-E2 -> 3991.8045 | G3: =+G2-F2 -> 4602.1717 | H3: =+H2-G2 -> 3395.0333 | I3: =+I2-H2 -> 2537.5856 | J3: =+J2-I2 -> 2934.1851 | K3: =+K2-J2 -> 2204.2642 | L3: =+L2-K2 -> 2198.1695 | ... N3: =+N2-M2 -> 2729.1463
C6: TYPE 1 BOND Characteristics | D6: Values
C7: Coupon rate | D7: =+'Leverage finale'!AU10 -> 0.062301838
C8: Face value | D8: 1000
C12: TYPE 1 BOND (2025) | D12: 2025 | E12: 2026 | F12: 2027 | G12: 2028 | H12: 2029 | I12: 2030 | J12: 2031 | K12: 2032 | L12: 2033 | M12: 2034 | N12: 2035
C13: Cost of Debt | D13: =+D7 -> 0.062301838 | E13: =+'Leverage finale'!$AU$20 -> 0.066930524 | F13: =+'Leverage finale'!$AU$30 -> 0.06243134 | G13: =+'Leverage finale'!$AU$40 -> 0.063184948 | H13: =+'Leverage finale'!$AU$50 -> 0.055328756 | I13: =+'Leverage finale'!$AU$60 -> 0.063184948 | J13: =+'Leverage finale'!$AU$70 -> 0.055328756 | K13: =+'Leverage finale'!$AU$80 -> 0.055328756 | L13: =+'Leverage finale'!$AU$90 -> 0.055328756 | M13: =+'Leverage finale'!$AU$100 -> 0.055328756 | N13: =+'Leverage finale'!$AU$110 -> 0.055328756
C14: Annual coupon | D14: =$D$7*$D$8 -> 62.301838 | E14: =$D$7*$D$8 -> 62.301838 | F14: =$D$7*$D$8 -> 62.301838 | G14: =$D$7*$D$8 -> 62.301838 | H14: =$D$7*$D$8 -> 62.301838 | I14: =$D$7*$D$8 -> 62.301838 | J14: =$D$7*$D$8 -> 62.301838 | K14: =$D$7*$D$8 -> 62.301838 | ... N14: =$D$7*$D$8 -> 62.301838
C15: Bond Face Value | N15: =+D8 -> 1000
C16: Present Value of Cash Flows | D16: =D14/(1+D13) -> 58.647962 | E16: =E14/((1+E13)*(1+D13)) -> 54.968867 | F16: =F14/((1+F13)*(1+E13)*(1+D13)) -> 51.738748 | G16: =G14/((1+G13)*(1+F13)*(1+E13)*(1+D13)) -> 48.66392 | H16: =(H14)/((1+H13)*(1+G13)*(1+F13)*(1+E13)*(1+D13)) -> 46.112569 | I16: =(I14)/((1+D13)*(1+I13)*(1+H13)*(1+G13)*(1+F13)*(1+E13)) -> 43.372105 | J16: =(J14)/((1+J13)*(1+D13)*(1+I13)*(1+H13)*(1+G13)*(1+F13)*(1+E13)) -> 41.098193 | K16: =(K14)/((1+K13)*(1+J13)*(1+D13)*(1+I13)*(1+H13)*(1+G13)*(1+F13)*(1+E13)) -> 38.943498 | L16: =(L14)/((1+L13)*(1+K13)*(1+J13)*(1+D13)*(1+I13)*(1+H13)*(1+G13)*(1+F13)*(1+E13)) -> 36.901769 | M16: =(M14)/((1+M13)*(1+L13)*(1+K13)*(1+J13)*(1+D13)*(1+I13)*(1+H13)*(1+G13)*(1+F13)*(1+E13)) -> 34.967084 | N16: =(N14+N15)/((1+N13)*(1+M13)*(1+L13)*(1+K13)*(1+J13)*(1+D13)*(1+I13)*(1+H13)*(1+G13)*(1+F13)*(1+E13)) -> 564.96132
C17: Total PV of Type 1 Bond | D17: =SUM(D16:N16) -> 1020.376
C20: TYPE 2 BOND Characteristics | D20: Values
C21: Coupon rate | D21: =+'Leverage finale'!AU20 -> 0.066930524
C22: Face value | D22: 1000
C26: TYPE 2 BOND (2026) | D26: 2026 | E26: 2027 | F26: 2028 | G26: 2029 | H26: 2030 | I26: 2031 | J26: 2032 | K26: 2033 | L26: 2034 | M26: 2035 | N26: 2036
C27: Cost of Debt | D27: =+E13 -> 0.066930524 | E27: =+F13 -> 0.06243134 | F27: =+G13 -> 0.063184948 | G27: =+H13 -> 0.055328756 | H27: =+I13 -> 0.063184948 | I27: =+J13 -> 0.055328756 | J27: =+K13 -> 0.055328756 | K27: =+L13 -> 0.055328756 | ... M27: =+N13 -> 0.055328756 | N27: =+Tableau6[[#This Row],[2035]] -> 0.055328756
C28: Annual coupon | D28: =$D$22*$D$21 -> 66.930524 | E28: =$D$22*$D$21 -> 66.930524 | F28: =$D$22*$D$21 -> 66.930524 | G28: =$D$22*$D$21 -> 66.930524 | H28: =$D$22*$D$21 -> 66.930524 | I28: =$D$22*$D$21 -> 66.930524 | J28: =$D$22*$D$21 -> 66.930524 | K28: =$D$22*$D$21 -> 66.930524 | ... N28: =$D$22*$D$21 -> 66.930524
C29: Bond Face Value | N29: =+D22 -> 1000
C30: PV of each CF (all discounted to 2025) | D30: =D28/(1+D27) -> 62.731849 | E30: =E28/((1+E27)*(1+D27)) -> 59.045555 | F30: =F28/((1+F27)*(1+E27)*(1+D27)) -> 55.536485 | G30: =G28/((1+G27)*(1+F27)*(1+E27)*(1+D27)) -> 52.62482 | H30: =(H28)/((1+H27)*(1+G27)*(1+F27)*(1+E27)*(1+D27)) -> 49.497333 | I30: =(I28)/((1+D27)*(1+I27)*(1+H27)*(1+G27)*(1+F27)*(1+E27)) -> 46.902288 | J30: =(J28)/((1+J27)*(1+D27)*(1+I27)*(1+H27)*(1+G27)*(1+F27)*(1+E27)) -> 44.443296 | K30: =(K28)/((1+K27)*(1+J27)*(1+D27)*(1+I27)*(1+H27)*(1+G27)*(1+F27)*(1+E27)) -> 42.113223 | L30: =(L28)/((1+L27)*(1+K27)*(1+J27)*(1+D27)*(1+I27)*(1+H27)*(1+G27)*(1+F27)*(1+E27)) -> 39.905312 | M30: =(M28)/((1+M27)*(1+L27)*(1+K27)*(1+J27)*(1+D27)*(1+I27)*(1+H27)*(1+G27)*(1+F27)*(1+E27)) -> 37.813157 | N30: =(N28+N29)/((1+N27)*(1+M27)*(1+L27)*(1+K27)*(1+J27)*(1+D27)*(1+I27)*(1+H27)*(1+G27)*(1+F27)*(1+E27)) -> 571.17223
C31: PV Bond Type 2 | D31: =SUM(D30:N30) -> 1061.7855
C34: TYPE 3 BOND Characteristics | D34: Values
C35: Coupon rate | D35: =+'Leverage finale'!AU30 -> 0.06243134
C36: Face value | D36: 1000
C39: TYPE 3 BOND (2027) | D39: 2027 | E39: 2028 | F39: 2029 | G39: 2030 | H39: 2031 | I39: 2032 | J39: 2033 | K39: 2034 | L39: 2035 | M39: 2036 | N39: 2037
C40: Cost of Debt | D40: =+E27 -> 0.06243134 | E40: =+F27 -> 0.063184948 | F40: =+G27 -> 0.055328756 | G40: =+H27 -> 0.063184948 | H40: =+I27 -> 0.055328756 | I40: =+J27 -> 0.055328756 | J40: =+K27 -> 0.055328756 | K40: =+L27 -> 0.055328756 | L40: =+M27 -> 0.055328756 | M40: =+Tableau11[[#This Row],[2035]] -> 0.055328756 | N40: =+Tableau11[[#This Row],[2036]] -> 0.055328756
C41: Annual coupon | D41: =$D$35*$D$36 -> 62.43134 | E41: =$D$35*$D$36 -> 62.43134 | F41: =$D$35*$D$36 -> 62.43134 | G41: =$D$35*$D$36 -> 62.43134 | H41: =$D$35*$D$36 -> 62.43134 | I41: =$D$35*$D$36 -> 62.43134 | J41: =$D$35*$D$36 -> 62.43134 | K41: =$D$35*$D$36 -> 62.43134 | ... N41: =$D$35*$D$36 -> 62.43134
C42: Bond Face Value | N42: =+D36 -> 1000
C43: PV of each CF (all discounted to 2026) | D43: =D41/(1+D40) -> 58.762706 | E43: =E41/((1+E40)*(1+D40)) -> 55.270445 | F43: =F41/((1+F40)*(1+E40)*(1+D40)) -> 52.372727 | G43: =G41/((1+G40)*(1+F40)*(1+E40)*(1+D40)) -> 49.260223 | H43: =(H41)/((1+H40)*(1+G40)*(1+F40)*(1+E40)*(1+D40)) -> 46.677609 | I43: =(I41)/((1+D40)*(1+I40)*(1+H40)*(1+G40)*(1+F40)*(1+E40)) -> 44.230396 | J43: =(J41)/((1+J40)*(1+D40)*(1+I40)*(1+H40)*(1+G40)*(1+F40)*(1+E40)) -> 41.911486 | K43: =(K41)/((1+K40)*(1+J40)*(1+D40)*(1+I40)*(1+H40)*(1+G40)*(1+F40)*(1+E40)) -> 39.714151 | L43: =(L41)/((1+L40)*(1+K40)*(1+J40)*(1+D40)*(1+I40)*(1+H40)*(1+G40)*(1+F40)*(1+E40)) -> 37.632018 | M43: =(M41)/((1+M40)*(1+L40)*(1+K40)*(1+J40)*(1+D40)*(1+I40)*(1+H40)*(1+G40)*(1+F40)*(1+E40)) -> 35.659048 | N43: =(N41+N42)/((1+N40)*(1+M40)*(1+L40)*(1+K40)*(1+J40)*(1+D40)*(1+I40)*(1+H40)*(1+G40)*(1+F40)*(1+E40)) -> 575.01634
C44: PV Bond Type 3 | D44: =SUM(D43:N43) -> 1036.5071
C47: TYPE 4 BOND Characteristics | D47: Values
C48: Coupon rate | D48: =+'Leverage finale'!AU40 -> 0.063184948
C49: Face value | D49: 1000
C52: TYPE 4 BOND (2028) | D52: 2028 | E52: 2029 | F52: 2030 | G52: 2031 | H52: 2032 | I52: 2033 | J52: 2034 | K52: 2035 | L52: 2036 | M52: 2037 | N52: 2038
C53: Cost of Debt | D53: =+E40 -> 0.063184948 | E53: =+F40 -> 0.055328756 | F53: =+G40 -> 0.063184948 | G53: =+H40 -> 0.055328756 | H53: =+I40 -> 0.055328756 | I53: =+J40 -> 0.055328756 | J53: =+K40 -> 0.055328756 | K53: =+L40 -> 0.055328756 | L53: =+Tableau16[[#This Row],[2035]] -> 0.055328756 | M53: =+Tableau16[[#This Row],[2036]] -> 0.055328756 | N53: =+Tableau16[[#This Row],[2037]] -> 0.055328756
C54: Annual coupon | D54: =$D$48*$D$49 -> 63.184948 | E54: =$D$48*$D$49 -> 63.184948 | F54: =$D$48*$D$49 -> 63.184948 | G54: =$D$48*$D$49 -> 63.184948 | H54: =$D$48*$D$49 -> 63.184948 | I54: =$D$48*$D$49 -> 63.184948 | J54: =$D$48*$D$49 -> 63.184948 | K54: =$D$48*$D$49 -> 63.184948 | ... N54: =$D$48*$D$49 -> 63.184948
C55: Bond Face Value | N55: =+D49 -> 1000
C56: PV of each CF (all discounted to 2027) | D56: =D54/(1+D53) -> 59.429874 | E56: =E54/((1+E53)*(1+D53)) -> 56.314086 | F56: =F54/((1+F53)*(1+E53)*(1+D53)) -> 52.967347 | G56: =G54/((1+G53)*(1+F53)*(1+E53)*(1+D53)) -> 50.190376 | H56: =(H54)/((1+H53)*(1+G53)*(1+F53)*(1+E53)*(1+D53)) -> 47.558996 | I56: =(I54)/((1+D53)*(1+I53)*(1+H53)*(1+G53)*(1+F53)*(1+E53)) -> 45.065574 | J56: =(J54)/((1+J53)*(1+D53)*(1+I53)*(1+H53)*(1+G53)*(1+F53)*(1+E53)) -> 42.702877 | K56: =(K54)/((1+K53)*(1+J53)*(1+D53)*(1+I53)*(1+H53)*(1+G53)*(1+F53)*(1+E53)) -> 40.464051 | L56: =(L54)/((1+L53)*(1+K53)*(1+J53)*(1+D53)*(1+I53)*(1+H53)*(1+G53)*(1+F53)*(1+E53)) -> 38.342603 | M56: =(M54)/((1+M53)*(1+L53)*(1+K53)*(1+J53)*(1+D53)*(1+I53)*(1+H53)*(1+G53)*(1+F53)*(1+E53)) -> 36.332377 | N56: =(N54+N55)/((1+N53)*(1+M53)*(1+L53)*(1+K53)*(1+J53)*(1+D53)*(1+I53)*(1+H53)*(1+G53)*(1+F53)*(1+E53)) -> 579.29694
C57: PV Bond Type 4 | D57: =SUM(D56:N56) -> 1048.6651
C60: TYPE 5 BOND Characteristics | D60: Values
C61: Coupon rate | D61: =+'Leverage finale'!AU50 -> 0.055328756
C62: Face value | D62: 1000
C65: TYPE 5 BOND (2029) | D65: 2029 | E65: 2030 | F65: 2031 | G65: 2032 | H65: 2033 | I65: 2034 | J65: 2035 | K65: 2036 | L65: 2037 | M65: 2038 | N65: 2039
C66: Cost of Debt | D66: =+E53 -> 0.055328756 | E66: =+F53 -> 0.063184948 | F66: =+G53 -> 0.055328756 | G66: =+H53 -> 0.055328756 | H66: =+I53 -> 0.055328756 | I66: =+J53 -> 0.055328756 | J66: =+K53 -> 0.055328756 | K66: =+Tableau18[[#This Row],[2035]] -> 0.055328756 | L66: =+Tableau18[[#This Row],[2036]] -> 0.055328756 | M66: =+Tableau18[[#This Row],[2037]] -> 0.055328756 | N66: =+Tableau18[[#This Row],[2038]] -> 0.055328756
C67: Annual coupon | D67: =$D$61*$D$62 -> 55.328756 | E67: =$D$61*$D$62 -> 55.328756 | F67: =$D$61*$D$62 -> 55.328756 | G67: =$D$61*$D$62 -> 55.328756 | H67: =$D$61*$D$62 -> 55.328756 | I67: =$D$61*$D$62 -> 55.328756 | J67: =$D$61*$D$62 -> 55.328756 | K67: =$D$61*$D$62 -> 55.328756 | ... N67: =$D$61*$D$62 -> 55.328756
C68: Bond Face Value | N68: =+D62 -> 1000
C69: PV of each CF (all discounted to 2028) | D69: =D67/(1+D66) -> 52.427981 | E69: =E67/((1+E66)*(1+D66)) -> 49.312193 | F69: =F67/((1+F66)*(1+E66)*(1+D66)) -> 46.726854 | G69: =G67/((1+G66)*(1+F66)*(1+E66)*(1+D66)) -> 44.277059 | H69: =(H67)/((1+H66)*(1+G66)*(1+F66)*(1+E66)*(1+D66)) -> 41.955703 | I69: =(I67)/((1+D66)*(1+I66)*(1+H66)*(1+G66)*(1+F66)*(1+E66)) -> 39.75605 | J69: =(J67)/((1+J66)*(1+D66)*(1+I66)*(1+H66)*(1+G66)*(1+F66)*(1+E66)) -> 37.67172 | K69: =(K67)/((1+K66)*(1+J66)*(1+D66)*(1+I66)*(1+H66)*(1+G66)*(1+F66)*(1+E66)) -> 35.696668 | L69: =(L67)/((1+L66)*(1+K66)*(1+J66)*(1+D66)*(1+I66)*(1+H66)*(1+G66)*(1+F66)*(1+E66)) -> 33.825164 | M69: =(M67)/((1+M66)*(1+L66)*(1+K66)*(1+J66)*(1+D66)*(1+I66)*(1+H66)*(1+G66)*(1+F66)*(1+E66)) -> 32.051779 | N69: =(N67+N68)/((1+N66)*(1+M66)*(1+L66)*(1+K66)*(1+J66)*(1+D66)*(1+I66)*(1+H66)*(1+G66)*(1+F66)*(1+E66)) -> 579.29694
C70: PV Bond Type 5 | D70: =SUM(D69:N69) -> 992.99811
C74: TYPE 6 BOND Characteristics | D74: Values
C75: Coupon rate | D75: =+'Leverage finale'!AU60 -> 0.063184948
C76: Face value | D76: 1000
C79: TYPE 6 BOND (2030) | D79: 2030 | E79: 2031 | F79: 2032 | G79: 2033 | H79: 2034 | I79: 2035 | J79: 2036 | K79: 2037 | L79: 2038 | M79: 2039 | N79: 2040
C80: Cost of Debt | D80: =+E66 -> 0.063184948 | E80: =+F66 -> 0.055328756 | F80: =+G66 -> 0.055328756 | G80: =+H66 -> 0.055328756 | H80: =+I66 -> 0.055328756 | I80: =+'Leverage finale'!AU110 -> 0.055328756 | J80: =+Tableau1815[[#This Row],[2035]] -> 0.055328756 | K80: =+Tableau1815[[#This Row],[2036]] -> 0.055328756 | L80: =+Tableau1815[[#This Row],[2037]] -> 0.055328756 | M80: =+Tableau1815[[#This Row],[2038]] -> 0.055328756 | N80: =+Tableau1815[[#This Row],[2039]] -> 0.055328756
C81: Annual coupon | D81: =$D$75*$D$76 -> 63.184948 | E81: =$D$75*$D$76 -> 63.184948 | F81: =$D$75*$D$76 -> 63.184948 | G81: =$D$75*$D$76 -> 63.184948 | H81: =$D$75*$D$76 -> 63.184948 | I81: =$D$75*$D$76 -> 63.184948 | J81: =$D$75*$D$76 -> 63.184948 | K81: =$D$75*$D$76 -> 63.184948 | ... N81: =$D$75*$D$76 -> 63.184948
C82: Bond Face Value | N82: =+D76 -> 1000
C83: PV of each CF (all discounted to 2028) | D83: =D81/(1+D80) -> 59.429874 | E83: =E81/((1+E80)*(1+D80)) -> 56.314086 | F83: =F81/((1+F80)*(1+E80)*(1+D80)) -> 53.361652 | G83: =G81/((1+G80)*(1+F80)*(1+E80)*(1+D80)) -> 50.564009 | H83: =(H81)/((1+H80)*(1+G80)*(1+F80)*(1+E80)*(1+D80)) -> 47.91304 | I83: =(N81)/((1+D80)*(1+I80)*(1+H80)*(1+G80)*(1+F80)*(1+E80)) -> 45.401056 | J83: =(J81)/((1+J80)*(1+D80)*(1+I80)*(1+H80)*(1+G80)*(1+F80)*(1+E80)) -> 43.02077 | K83: =(K81)/((1+K80)*(1+J80)*(1+D80)*(1+I80)*(1+H80)*(1+G80)*(1+F80)*(1+E80)) -> 40.765278 | L83: =(L81)/((1+L80)*(1+K80)*(1+J80)*(1+D80)*(1+I80)*(1+H80)*(1+G80)*(1+F80)*(1+E80)) -> 38.628037 | M83: =(M81)/((1+M80)*(1+L80)*(1+K80)*(1+J80)*(1+D80)*(1+I80)*(1+H80)*(1+G80)*(1+F80)*(1+E80)) -> 36.602847 | N83: =(N81+N82)/((1+N80)*(1+M80)*(1+L80)*(1+K80)*(1+J80)*(1+D80)*(1+I80)*(1+H80)*(1+G80)*(1+F80)*(1+E80)) -> 583.6094
C84: PV Bond Type 5 | D84: =SUM(D83:N83) -> 1055.61
C88: TYPE 6 BOND Characteristics | D88: Values
C89: Coupon rate | D89: =+'Leverage finale'!AU70 -> 0.055328756
C90: Face value | D90: 1000
C93: TYPE 6 BOND (2031) | D93: 2031 | E93: 2032 | F93: 2033 | G93: 2034 | H93: 2035 | I93: 2036 | J93: 2037 | K93: 2038 | L93: 2039 | M93: 2040 | N93: 2041
C94: Cost of Debt | D94: =+E80 -> 0.055328756 | E94: =+F80 -> 0.055328756 | F94: =+G80 -> 0.055328756 | G94: =+H80 -> 0.055328756 | H94: =+I80 -> 0.055328756 | I94: =+Tableau181517[[#This Row],[2035]] -> 0.055328756 | J94: =+Tableau181517[[#This Row],[2036]] -> 0.055328756 | K94: =+Tableau181517[[#This Row],[2037]] -> 0.055328756 | L94: =+Tableau181517[[#This Row],[2038]] -> 0.055328756 | M94: =+Tableau181517[[#This Row],[2039]] -> 0.055328756 | N94: =+Tableau181517[[#This Row],[2040]] -> 0.055328756
C95: Annual coupon | D95: =$D$89*$D$90 -> 55.328756 | E95: =$D$89*$D$90 -> 55.328756 | F95: =$D$89*$D$90 -> 55.328756 | G95: =$D$89*$D$90 -> 55.328756 | H95: =$D$89*$D$90 -> 55.328756 | I95: =$D$89*$D$90 -> 55.328756 | J95: =$D$89*$D$90 -> 55.328756 | K95: =$D$89*$D$90 -> 55.328756 | ... N95: =$D$89*$D$90 -> 55.328756
C96: Bond Face Value | N96: =+D90 -> 1000
C97: PV of each CF (all discounted to 2028) | D97: =D95/(1+D94) -> 52.427981 | E97: =E95/((1+E94)*(1+D94)) -> 49.679288 | F97: =F95/((1+F94)*(1+E94)*(1+D94)) -> 47.074703 | G97: =G95/((1+G94)*(1+F94)*(1+E94)*(1+D94)) -> 44.606671 | H97: =(H95)/((1+H94)*(1+G94)*(1+F94)*(1+E94)*(1+D94)) -> 42.268034 | I97: =(I95)/((1+D94)*(1+I94)*(1+H94)*(1+G94)*(1+F94)*(1+E94)) -> 40.052006 | J97: =(J95)/((1+J94)*(1+D94)*(1+I94)*(1+H94)*(1+G94)*(1+F94)*(1+E94)) -> 37.95216 | K97: =(K95)/((1+K94)*(1+J94)*(1+D94)*(1+I94)*(1+H94)*(1+G94)*(1+F94)*(1+E94)) -> 35.962405 | L97: =(L95)/((1+L94)*(1+K94)*(1+J94)*(1+D94)*(1+I94)*(1+H94)*(1+G94)*(1+F94)*(1+E94)) -> 34.076969 | M97: =(M95)/((1+M94)*(1+L94)*(1+K94)*(1+J94)*(1+D94)*(1+I94)*(1+H94)*(1+G94)*(1+F94)*(1+E94)) -> 32.290382 | N97: =(N95+N96)/((1+N94)*(1+M94)*(1+L94)*(1+K94)*(1+J94)*(1+D94)*(1+I94)*(1+H94)*(1+G94)*(1+F94)*(1+E94)) -> 583.6094
C98: PV Bond Type 5 | D98: =SUM(D97:N97) -> 1000
C102: TYPE 6 BOND Characteristics | D102: Values
C103: Coupon rate | D103: =+'Leverage finale'!AU80 -> 0.055328756
C104: Face value | D104: 1000
C107: TYPE 6 BOND (2032) | D107: 2032 | E107: 2033 | F107: 2034 | G107: 2035 | H107: 2036 | I107: 2037 | J107: 2038 | K107: 2039 | L107: 2040 | M107: 2041 | N107: 2042
C108: Cost of Debt | D108: =+E94 -> 0.055328756 | E108: =+F94 -> 0.055328756 | F108: =+G94 -> 0.055328756 | G108: =+H94 -> 0.055328756 | H108: =+Tableau181519[[#This Row],[2035]] -> 0.055328756 | I108: =+Tableau181519[[#This Row],[2036]] -> 0.055328756 | J108: =+Tableau181519[[#This Row],[2037]] -> 0.055328756 | K108: =+Tableau181519[[#This Row],[2038]] -> 0.055328756 | L108: =+Tableau181519[[#This Row],[2039]] -> 0.055328756 | M108: =+Tableau181519[[#This Row],[2040]] -> 0.055328756 | N108: =+Tableau181519[[#This Row],[2041]] -> 0.055328756
C109: Annual coupon | D109: =$D$103*$D$104 -> 55.328756 | E109: =$D$103*$D$104 -> 55.328756 | F109: =$D$103*$D$104 -> 55.328756 | G109: =$D$103*$D$104 -> 55.328756 | H109: =$D$103*$D$104 -> 55.328756 | I109: =$D$103*$D$104 -> 55.328756 | J109: =$D$103*$D$104 -> 55.328756 | K109: =$D$103*$D$104 -> 55.328756 | ... N109: =$D$103*$D$104 -> 55.328756
C110: Bond Face Value | N110: =+D104 -> 1000
C111: PV of each CF (all discounted to 2028) | D111: =D109/(1+D108) -> 52.427981 | E111: =E109/((1+E108)*(1+D108)) -> 49.679288 | F111: =F109/((1+F108)*(1+E108)*(1+D108)) -> 47.074703 | G111: =G109/((1+G108)*(1+F108)*(1+E108)*(1+D108)) -> 44.606671 | H111: =(H109)/((1+H108)*(1+G108)*(1+F108)*(1+E108)*(1+D108)) -> 42.268034 | I111: =(I109)/((1+D108)*(1+I108)*(1+H108)*(1+G108)*(1+F108)*(1+E108)) -> 40.052006 | J111: =(J109)/((1+J108)*(1+D108)*(1+I108)*(1+H108)*(1+G108)*(1+F108)*(1+E108)) -> 37.95216 | K111: =(K109)/((1+K108)*(1+J108)*(1+D108)*(1+I108)*(1+H108)*(1+G108)*(1+F108)*(1+E108)) -> 35.962405 | L111: =(L109)/((1+L108)*(1+K108)*(1+J108)*(1+D108)*(1+I108)*(1+H108)*(1+G108)*(1+F108)*(1+E108)) -> 34.076969 | M111: =(M109)/((1+M108)*(1+L108)*(1+K108)*(1+J108)*(1+D108)*(1+I108)*(1+H108)*(1+G108)*(1+F108)*(1+E108)) -> 32.290382 | N111: =(N109+N110)/((1+N108)*(1+M108)*(1+L108)*(1+K108)*(1+J108)*(1+D108)*(1+I108)*(1+H108)*(1+G108)*(1+F108)*(1+E108)) -> 583.6094
C112: PV Bond Type 5 | D112: =SUM(D111:N111) -> 1000
C116: TYPE 6 BOND Characteristics | D116: Values
C117: Coupon rate | D117: =+'Leverage finale'!AU90 -> 0.055328756
C118: Face value | D118: 1000
C121: TYPE 6 BOND (2033) | D121: 2033 | E121: 2034 | F121: 2035 | G121: 2036 | H121: 2037 | I121: 2038 | J121: 2039 | K121: 2040 | L121: 2041 | M121: 2042 | N121: 2043
C122: Cost of Debt | D122: =+E108 -> 0.055328756 | E122: =+F108 -> 0.055328756 | F122: =+G108 -> 0.055328756 | G122: =+Tableau181521[[#This Row],[2035]] -> 0.055328756 | H122: =+Tableau181521[[#This Row],[2036]] -> 0.055328756 | I122: =+Tableau181521[[#This Row],[2037]] -> 0.055328756 | J122: =+Tableau181521[[#This Row],[2038]] -> 0.055328756 | K122: =+Tableau181521[[#This Row],[2039]] -> 0.055328756 | L122: =+Tableau181521[[#This Row],[2040]] -> 0.055328756 | M122: =+Tableau181521[[#This Row],[2041]] -> 0.055328756 | N122: =+Tableau181521[[#This Row],[2042]] -> 0.055328756
C123: Annual coupon | D123: =$D$117*$D$118 -> 55.328756 | E123: =$D$117*$D$118 -> 55.328756 | F123: =$D$117*$D$118 -> 55.328756 | G123: =$D$117*$D$118 -> 55.328756 | H123: =$D$117*$D$118 -> 55.328756 | I123: =$D$117*$D$118 -> 55.328756 | J123: =$D$117*$D$118 -> 55.328756 | K123: =$D$117*$D$118 -> 55.328756 | ... N123: =$D$117*$D$118 -> 55.328756
C124: Bond Face Value | N124: =+D118 -> 1000
C125: PV of each CF (all discounted to 2028) | D125: =D123/(1+D122) -> 52.427981 | E125: =E123/((1+E122)*(1+D122)) -> 49.679288 | F125: =F123/((1+F122)*(1+E122)*(1+D122)) -> 47.074703 | G125: =G123/((1+G122)*(1+F122)*(1+E122)*(1+D122)) -> 44.606671 | H125: =(H123)/((1+H122)*(1+G122)*(1+F122)*(1+E122)*(1+D122)) -> 42.268034 | I125: =(I123)/((1+D122)*(1+I122)*(1+H122)*(1+G122)*(1+F122)*(1+E122)) -> 40.052006 | J125: =(J123)/((1+J122)*(1+D122)*(1+I122)*(1+H122)*(1+G122)*(1+F122)*(1+E122)) -> 37.95216 | K125: =(K123)/((1+K122)*(1+J122)*(1+D122)*(1+I122)*(1+H122)*(1+G122)*(1+F122)*(1+E122)) -> 35.962405 | L125: =(L123)/((1+L122)*(1+K122)*(1+J122)*(1+D122)*(1+I122)*(1+H122)*(1+G122)*(1+F122)*(1+E122)) -> 34.076969 | M125: =(M123)/((1+M122)*(1+L122)*(1+K122)*(1+J122)*(1+D122)*(1+I122)*(1+H122)*(1+G122)*(1+F122)*(1+E122)) -> 32.290382 | N125: =(N123+N124)/((1+N122)*(1+M122)*(1+L122)*(1+K122)*(1+J122)*(1+D122)*(1+I122)*(1+H122)*(1+G122)*(1+F122)*(1+E122)) -> 583.6094
C126: PV Bond Type 5 | D126: =SUM(D125:N125) -> 1000
C130: TYPE 6 BOND Characteristics | D130: Values
C131: Coupon rate | D131: =+'Leverage finale'!AU100 -> 0.055328756
C132: Face value | D132: 1000
C135: TYPE 6 BOND (2034) | D135: 2034 | E135: 2035 | F135: 2036 | G135: 2037 | H135: 2038 | I135: 2039 | J135: 2040 | K135: 2041 | L135: 2042 | M135: 2043 | N135: 2044
C136: Cost of Debt | D136: =+H122 -> 0.055328756 | E136: =+I122 -> 0.055328756 | F136: =+Tableau181523[[#This Row],[2035]] -> 0.055328756 | G136: =+Tableau181523[[#This Row],[2036]] -> 0.055328756 | H136: =+Tableau181523[[#This Row],[2037]] -> 0.055328756 | I136: =+Tableau181523[[#This Row],[2038]] -> 0.055328756 | J136: =+Tableau181523[[#This Row],[2039]] -> 0.055328756 | K136: =+Tableau181523[[#This Row],[2040]] -> 0.055328756 | L136: =+Tableau181523[[#This Row],[2041]] -> 0.055328756 | M136: =+Tableau181523[[#This Row],[2042]] -> 0.055328756 | N136: =+Tableau181523[[#This Row],[2043]] -> 0.055328756
C137: Annual coupon | D137: =$D$131*$D$132 -> 55.328756 | E137: =$D$131*$D$132 -> 55.328756 | F137: =$D$131*$D$132 -> 55.328756 | G137: =$D$131*$D$132 -> 55.328756 | H137: =$D$131*$D$132 -> 55.328756 | I137: =$D$131*$D$132 -> 55.328756 | J137: =$D$131*$D$132 -> 55.328756 | K137: =$D$131*$D$132 -> 55.328756 | ... N137: =$D$131*$D$132 -> 55.328756
C138: Bond Face Value | N138: =+D132 -> 1000
C139: PV of each CF (all discounted to 2028) | D139: =D137/(1+D136) -> 52.427981 | E139: =E137/((1+E136)*(1+D136)) -> 49.679288 | F139: =F137/((1+F136)*(1+E136)*(1+D136)) -> 47.074703 | G139: =G137/((1+G136)*(1+F136)*(1+E136)*(1+D136)) -> 44.606671 | H139: =(H137)/((1+H136)*(1+G136)*(1+F136)*(1+E136)*(1+D136)) -> 42.268034 | I139: =(I137)/((1+D136)*(1+I136)*(1+H136)*(1+G136)*(1+F136)*(1+E136)) -> 40.052006 | J139: =(J137)/((1+J136)*(1+D136)*(1+I136)*(1+H136)*(1+G136)*(1+F136)*(1+E136)) -> 37.95216 | K139: =(K137)/((1+K136)*(1+J136)*(1+D136)*(1+I136)*(1+H136)*(1+G136)*(1+F136)*(1+E136)) -> 35.962405 | L139: =(L137)/((1+L136)*(1+K136)*(1+J136)*(1+D136)*(1+I136)*(1+H136)*(1+G136)*(1+F136)*(1+E136)) -> 34.076969 | M139: =(M137)/((1+M136)*(1+L136)*(1+K136)*(1+J136)*(1+D136)*(1+I136)*(1+H136)*(1+G136)*(1+F136)*(1+E136)) -> 32.290382 | N139: =(N137+N138)/((1+N136)*(1+M136)*(1+L136)*(1+K136)*(1+J136)*(1+D136)*(1+I136)*(1+H136)*(1+G136)*(1+F136)*(1+E136)) -> 583.6094
C140: PV Bond Type 5 | D140: =SUM(D139:N139) -> 1000
C144: TYPE 6 BOND Characteristics | D144: Values
C145: Coupon rate | D145: =+'Leverage finale'!AU110 -> 0.055328756
C146: Face value | D146: 1000
C149: TYPE 6 BOND (2035) | D149: 2035 | E149: 2036 | F149: 2037 | G149: 2038 | H149: 2039 | I149: 2040 | J149: 2041 | K149: 2042 | L149: 2043 | M149: 2044 | N149: 2045
C150: Cost of Debt | D150: =+E136 -> 0.055328756 | E150: =+F136 -> 0.055328756 | F150: =+G136 -> 0.055328756 | G150: =+H136 -> 0.055328756 | H150: =+I136 -> 0.055328756 | I150: =+J136 -> 0.055328756 | J150: =+K136 -> 0.055328756 | K150: =+L136 -> 0.055328756 | ... M150: =+N136 -> 0.055328756 | N150: =+N136 -> 0.055328756
C151: Annual coupon | D151: =$D$145*$D$146 -> 55.328756 | E151: =$D$145*$D$146 -> 55.328756 | F151: =$D$145*$D$146 -> 55.328756 | G151: =$D$145*$D$146 -> 55.328756 | H151: =$D$145*$D$146 -> 55.328756 | I151: =$D$145*$D$146 -> 55.328756 | J151: =$D$145*$D$146 -> 55.328756 | K151: =$D$145*$D$146 -> 55.328756 | ... N151: =$D$145*$D$146 -> 55.328756
C152: Bond Face Value | N152: =+D146 -> 1000
...

Sheet Unlevered Cost of Capital
C4: To evaluate Unlevered Cost of Capital we'll go through 3 steps: ru = rf + beta * risk premium
C11: ACTUAL LEVERAGE
C12: Financial item | D12: Numbers (Current) | E12: Source | G12: Comments
C13: Net Debt | D13: =8433-'Excess Cash'!I5 -> 4693.8 | G13: Total debt (10K) - Excess Cash
C14: Market Cap | D14: 247910 | E14: https://finance.yahoo.com/quote/CRM/key-statistics/
C15: D/(D+E) | D15: =D13/(D13+D14) -> 0.018581668
C22: rf + beta * risk premium
C23: Financial item | E23: Fonte | G23: Comments | I23: How to calculate risk premium (https://pages.stern.nyu.edu/~adamodar/New_Home_Page/datafile/histimpl.html):
C24: rf | D24: 0.0407 | E24: https://www.bloomberg.com/markets/rates-bonds | I24: Period | J24: ERP
C25: risk premium | D25: =J25 -> 0.042479688 | I25: 1960-2024 | J25: 0.042479688
C26: beta | D26: ='BETA Calculation chosen'!O18 -> 1.2211485 | F26: If we compare that with the Beta (Software (System & Application)) 1,24 found on https://pages.stern.nyu.edu/~adamodar/, the value from our analysis is reasonable
C27: Unlevered cost of capital | D27: =D24+D26*D25 -> 0.092574006

Sheet Excess Cash
A1: In Milions
B2: 2018 | C2: 2019 | D2: 2020 | E2: 2021 | F2: 2022 | G2: 2023 | H2: 2024 | I2: 2025
A3: Cash and cash equivalent | B3: =2543+1978 -> 4521 | C3: =2669+1673 -> 4342 | D3: =4145+3802 -> 7947 | E3: =6195+5771 -> 11966 | F3: =5464+5073 -> 10537 | G3: =7016+5492 -> 12508 | H3: =8472+5722 -> 14194 | I3: =8848+5184 -> 14032
A4: Total assets | B4: 21984 | C4: 30737 | D4: 55126 | E4: 66301 | F4: 95209 | G4: 98849 | H4: 99823 | I4: 102928
A5: Excess Cash | B5: =MAX(B3-0.1*B4,0) -> 2322.6 | C5: =MAX(C3-0.1*C4,0) -> 1268.3 | D5: =MAX(D3-0.1*D4,0) -> 2434.4 | E5: =MAX(E3-0.1*E4,0) -> 5335.9 | F5: =MAX(F3-0.1*F4,0) -> 1016.1 | G5: =MAX(G3-0.1*G4,0) -> 2623.1 | H5: =MAX(H3-0.1*H4,0) -> 4211.7 | I5: =MAX(I3-0.1*I4,0) -> 3739.2

Sheet Buyback
A2: In millions
A3: Market Cap (July 2025) | B3: ='Unlevered Cost of Capital'!D14 -> 247910 | D3: New Stock Price (S)= | E3: VL/N
A4: Number of stocks (N) | B4: 952
A5: Value per stocks | B5: =B3/B4 -> 260.40966 | E5: =B8/B4 -> 226.05202
D7: Number of stocks acquired (X)= | E7: (N*D)/VL
A8: Value of the Levered Firm (VL) | B8: ='Leverage finale'!C52 -> 215201.52
A9: Debt Issued (initial debt=0) (D) | B9: ='Leverage finale'!C55 -> 42983.406 | D9: million | E9: =B9/E5 -> 190.14829
D11: Gain/loss per stock | E11: =E5-B5 -> -34.357643
D12: % gain/loss per stock | E12: =E11/B5 -> -0.1319369

Sheet Montecarlo 
C2: Fiscal Year end January 31 2025
B3: Year | C3: 2018 | D3: 2019 | E3: 2020 | F3: 2021 | G3: 2022 | H3: 2023 | N3: 2024 | O3: 2025 | P3: 2026 | Q3: 2027 | R3: 2028 | S3: 2029 | T3: 2030 | AA3: Coverage ratio | AC3: Rating | AD3: Spread | AE3: Default probability | AH3: Year 2025 | AI3: Iteration 0 | AJ3: Iteration 1 | AK3: Iteration 2 | AL3: Iteration 3 | AM3: Iteration 4 | AN3: Iteration 5 | AO3: Iteration 6 | AP3: Iteration 7 | AQ3: Iteration 8 | AR3: Iteration 9 | AS3: Iteration 10
AA4: > | AB4: ≤ to | AH4: Trailing interest coverage ratio | AJ4: =MAX(MIN($N$14/AI8,100000),-100000) -> 2.7503076 | AK4: =MAX(MIN($N$14/AJ8,100000),-100000) -> 1.7037674 | AL4: =MAX(MIN($N$14/AK8,100000),-100000) -> 1.1115941 | AM4: =MAX(MIN($N$14/AL8,100000),-100000) -> 0.87314759 | AN4: =MAX(MIN($N$14/AM8,100000),-100000) -> 0.87314759 | AO4: =MAX(MIN($N$14/AN8,100000),-100000) -> 0.87314759 | AP4: =MAX(MIN($N$14/AO8,100000),-100000) -> 0.87314759 | AQ4: =MAX(MIN($N$14/AP8,100000),-100000) -> 0.87314759 | ... AS4: =MAX(MIN($N$14/AR8,100000),-100000) -> 0.87314759
C5: 0 | D5: =+(D6-C6)/C6 -> 0.2601518 | E5: =+(E6-D6)/D6 -> 0.28730613 | F5: =+(F6-E6)/E6 -> 0.24295239 | G5: =+(G6-F6)/F6 -> 0.24656503 | H5: =+(H6-G6)/G6 -> 0.18345161 | N5: =+(N6-H6)/H6 -> 0.1117951 | O5: =+(O6-N6)/N6 -> 0.087156095 | P5: =(P6-O6)/P6 -> 0.081283667 | Q5: =(Q6-P6)/Q6 -> 0.083336037 | R5: =(R6-Q6)/R6 -> 0.08872468 | S5: =(S6-R6)/S6 -> 0.089837138 | T5: =(T6-S6)/T6 -> 0.0843095 | AA5: -100000 | AB5: 0.199999 | AC5: D | AD5: 0.12 | AE5: 0.9 | AH5: Credit rating | AJ5: =VLOOKUP(AJ4,$AA$5:$AE$17,3) -> BBB | AK5: =VLOOKUP(AK4,$AA$5:$AE$17,3) -> B | AL5: =VLOOKUP(AL4,$AA$5:$AE$17,3) -> CCC | AM5: =VLOOKUP(AM4,$AA$5:$AE$17,3) -> CCC | AN5: =VLOOKUP(AN4,$AA$5:$AE$17,3) -> CCC | AO5: =VLOOKUP(AO4,$AA$5:$AE$17,3) -> CCC | AP5: =VLOOKUP(AP4,$AA$5:$AE$17,3) -> CCC | AQ5: =VLOOKUP(AQ4,$AA$5:$AE$17,3) -> CCC | ... AS5: =VLOOKUP(AS4,$AA$5:$AE$17,3) -> CCC
C6: 10540 | D6: 13282 | E6: 17098 | F6: 21252 | G6: 26492 | H6: 31352 | N6: 34857 | O6: 37895 | P6: 41247.77 | Q6: 44997.7 | R6: 49378.82 | S6: 54252.73 | T6: 59247.89 | AA6: 0.2 | AB6: 0.649999 | AC6: C | AD6: 0.105 | AE6: 0.3 | AH6: Credit spread | AJ6: =VLOOKUP(AJ4,$AA$4:$AE$17,4) -> 0.025 | AK6: =VLOOKUP(AK4,$AA$4:$AE$17,4) -> 0.06 | AL6: =VLOOKUP(AL4,$AA$4:$AE$17,4) -> 0.0875 | AM6: =VLOOKUP(AM4,$AA$4:$AE$17,4) -> 0.0875 | AN6: =VLOOKUP(AN4,$AA$4:$AE$17,4) -> 0.0875 | AO6: =VLOOKUP(AO4,$AA$4:$AE$17,4) -> 0.0875 | AP6: =VLOOKUP(AP4,$AA$4:$AE$17,4) -> 0.0875 | AQ6: =VLOOKUP(AQ4,$AA$4:$AE$17,4) -> 0.0875 | ... AS6: =VLOOKUP(AS4,$AA$4:$AE$17,4) -> 0.0875
C7: 2773 | D7: 3451 | E7: 4235 | F7: 5438 | G7: 7026 | H7: 8360 | N7: 8541 | O7: 8643 | P7: =P6-P9*P6 -> 8051.5647 | Q7: =Q6-Q9*Q6 -> 8671.0568 | R7: =R6-R9*R6 -> 9525.1744 | S7: =S6-S9*S6 -> 11083.833 | T7: =T6-T9*T6 -> 11523.715 | AA7: 0.65 | AB7: 0.799999 | AC7: CC | AD7: 0.095 | AE7: 0.2 | AH7: Yield on debt | AJ7: =AJ6+$AH$74 -> 0.0657 | AK7: =AK6+$AH$74 -> 0.1007 | AL7: =AL6+$AH$74 -> 0.1282 | AM7: =AM6+$AH$74 -> 0.1282 | AN7: =AN6+$AH$74 -> 0.1282 | AO7: =AO6+$AH$74 -> 0.1282 | AP7: =AP6+$AH$74 -> 0.1282 | AQ7: =AQ6+$AH$74 -> 0.1282 | ... AS7: =AS6+$AH$74 -> 0.1282
C8: =+C7/C6 -> 0.26309298 | D8: =+D7/D6 -> 0.25982533 | E8: =+E7/E6 -> 0.24768979 | F8: =+F7/F6 -> 0.2558818 | G8: =+G7/G6 -> 0.26521214 | H8: =+H7/H6 -> 0.26664966 | N8: =+N7/N6 -> 0.24502969 | O8: =+O7/O6 -> 0.22807758 | P8: =+P7/P6 -> 0.1952 | Q8: =+Q7/Q6 -> 0.1927 | R8: =+R7/R6 -> 0.1929 | S8: =+S7/S6 -> 0.2043 | T8: =+T7/T6 -> 0.1945 | AA8: 0.8 | AB8: 1.249999 | AC8: CCC | AD8: 0.0875 | AE8: 0.099 | AH8: Interest paid | AI8: =$AH$74*$C$54 -> 1821.978 | AJ8: =$C$54*AJ7 -> 2941.1291 | AK8: =$C$54*AK7 -> 4507.9406 | AL8: =$C$54*AL7 -> 5739.0068 | AM8: =$C$54*AM7 -> 5739.0068 | AN8: =$C$54*AN7 -> 5739.0068 | AO8: =$C$54*AO7 -> 5739.0068 | AP8: =$C$54*AP7 -> 5739.0068 | AQ8: =$C$54*AQ7 -> 5739.0068 | ... AS8: =$C$54*AS7 -> 5739.0068
C9: =+C10/C6 -> 0.73690702 | D9: =+D10/D6 -> 0.74017467 | E9: =+E10/E6 -> 0.75231021 | F9: =+F10/F6 -> 0.7441182 | G9: =+G10/G6 -> 0.73478786 | H9: =+H10/H6 -> 0.73335034 | N9: =+N10/N6 -> 0.75497031 | O9: 0.8054 | P9: 0.8048 | Q9: 0.8073 | R9: 0.8071 | S9: 0.7957 | T9: 0.8055 | AA9: 1.25 | AB9: 1.499999 | AC9: B- | AD9: 0.0675 | AE9: 0.07 | AH9: Prob of default | AJ9: =VLOOKUP(AJ4,$AA$5:$AE$17,5) -> 0.004 | AK9: =VLOOKUP(AK4,$AA$5:$AE$17,5) -> 0.052 | AL9: =VLOOKUP(AL4,$AA$5:$AE$17,5) -> 0.099 | AM9: =VLOOKUP(AM4,$AA$5:$AE$17,5) -> 0.099 | AN9: =VLOOKUP(AN4,$AA$5:$AE$17,5) -> 0.099 | AO9: =VLOOKUP(AO4,$AA$5:$AE$17,5) -> 0.099 | AP9: =VLOOKUP(AP4,$AA$5:$AE$17,5) -> 0.099 | AQ9: =VLOOKUP(AQ4,$AA$5:$AE$17,5) -> 0.099 | ... AS9: =VLOOKUP(AS4,$AA$5:$AE$17,5) -> 0.099
C10: =+C6-C7 -> 7767 | D10: =+D6-D7 -> 9831 | E10: =+E6-E7 -> 12863 | F10: =+F6-F7 -> 15814 | G10: =+G6-G7 -> 19466 | H10: =+H6-H7 -> 22992 | N10: =+N6-N7 -> 26316 | O10: =+O6-O7 -> 29252 | P10: =+P6-P7 -> 33196.205 | Q10: =+Q6-Q7 -> 36326.643 | R10: =+R6-R7 -> 39853.646 | S10: =+S6-S7 -> 43168.897 | T10: =+T6-T7 -> 47724.175 | AA10: 1.5 | AB10: 1.749999 | AC10: B | AD10: 0.06 | AE10: 0.052 | AH10: Cost of debt | AJ10: =(1-AJ9+AJ9*$AH$78)*(1+AJ7)-1 -> 0.063184948 | AK10: =(1-AK9+AK9*$AH$78)*(1+AK7)-1 -> 0.066930524 | AL10: =(1-AL9+AL9*$AH$78)*(1+AL7)-1 -> 0.062301838 | AM10: =(1-AM9+AM9*$AH$78)*(1+AM7)-1 -> 0.062301838 | AN10: =(1-AN9+AN9*$AH$78)*(1+AN7)-1 -> 0.062301838 | AO10: =(1-AO9+AO9*$AH$78)*(1+AO7)-1 -> 0.062301838 | AP10: =(1-AP9+AP9*$AH$78)*(1+AP7)-1 -> 0.062301838 | AQ10: =(1-AQ9+AQ9*$AH$78)*(1+AQ7)-1 -> 0.062301838 | ... AS10: =(1-AS9+AS9*$AH$78)*(1+AS7)-1 -> 0.062301838
C11: 7313 | D11: 9296 | E11: 12566 | F11: 15359 | G11: 18918 | H11: 21962 | N11: 21305 | O11: 22047 | P11: =+P6*P12 -> 26034.23 | Q11: =+Q6*Q12 -> 27361.156 | R11: =+R6*R12 -> 29973.199 | S11: =+S6*S12 -> 33387.653 | T11: =+T6*T12 -> 36150.526 | AA11: 1.75 | AB11: 1.999999 | AC11: B+ | AD11: 0.055 | AE11: 0.03
C12: =+C11/C6 -> 0.69383302 | D12: =+D11/D6 -> 0.69989459 | E12: =+E11/E6 -> 0.73493976 | F12: =+F11/F6 -> 0.72270845 | G12: =+G11/G6 -> 0.71410237 | H12: =+H11/H6 -> 0.70049758 | N12: =+N11/N6 -> 0.61121152 | O12: =+O11/O6 -> 0.58179179 | P12: =+AVERAGE(H12:O12) -> 0.63116696 | Q12: =+AVERAGE(N12:P12) -> 0.60805676 | R12: =+AVERAGE(O12:Q12) -> 0.60700517 | S12: =+AVERAGE(P12:R12) -> 0.61540963 | T12: =+AVERAGE(Q12:S12) -> 0.61015719 | AA12: 2.5 | AB12: 2.999999 | AC12: BBB | AD12: 0.025 | AE12: 0.004
O13: 12498 | P13: 14029.39 | Q13: 15720.75 | R13: 17726.86 | S13: 20720.8 | T13: 23559.75 | AA13: 3 | AB13: 4.249999 | AC13: A- | AD13: 0.0165 | AE13: 0.003 | AH13: Year 2026 | AI13: Iteration 0 | AJ13: Iteration 1 | AK13: Iteration 2 | AL13: Iteration 3 | AM13: Iteration 4 | AN13: Iteration 5 | AO13: Iteration 6 | AP13: Iteration 7 | AQ13: Iteration 8 | AR13: Iteration 9 | AS13: Iteration 10
C14: =+C10-C11 -> 454 | D14: =+D10-D11 -> 535 | E14: =+E10-E11 -> 297 | F14: =+F10-F11 -> 455 | G14: =+G10-G11 -> 548 | H14: =+H10-H11 -> 1030 | N14: =+N10-N11 -> 5011 | O14: =+O10-O11 -> 7205 | P14: =+P10-P11 -> 7161.9756 | Q14: =+Q10-Q11 -> 8965.4876 | R14: =+R10-R11 -> 9880.4465 | S14: =+S10-S11 -> 9781.2447 | T14: =+T10-T11 -> 11573.649 | AA14: 4.25 | AB14: 5.499999 | AC14: A | AD14: 0.014 | AE14: 0.002 | AH14: Trailing interest coverage ratio | AJ14: =MAX(MIN($O$14/AI18,100000),-100000) -> 3.5636789 | AK14: =MAX(MIN($O$14/AJ18,100000),-100000) -> 2.5356946 | AL14: =MAX(MIN($O$14/AK18,100000),-100000) -> 2.2076367 | AM14: =MAX(MIN($O$14/AL18,100000),-100000) -> 1.5155876 | AN14: =MAX(MIN($O$14/AM18,100000),-100000) -> 1.440335 | AO14: =MAX(MIN($O$14/AN18,100000),-100000) -> 1.3404966 | AP14: =MAX(MIN($O$14/AO18,100000),-100000) -> 1.3404966 | AQ14: =MAX(MIN($O$14/AP18,100000),-100000) -> 1.3404966 | ... AS14: =MAX(MIN($O$14/AR18,100000),-100000) -> 1.3404966
C15: =+C14/C6 -> 0.043074004 | D15: =+D14/D6 -> 0.040280078 | E15: =+E14/E6 -> 0.017370453 | F15: =+F14/F6 -> 0.02140975 | G15: =+G14/G6 -> 0.02068549 | H15: =+H14/H6 -> 0.032852769 | N15: =+N14/N6 -> 0.14375879 | O15: =+O13/O6 -> 0.32980604 | P15: =+P13/P6 -> 0.34012481 | Q15: =+Q13/Q6 -> 0.34936786 | R15: =+R13/R6 -> 0.35899724 | S15: =+S13/S6 -> 0.38193101 | T15: =+T13/T6 -> 0.39764707 | AA15: 5.5 | AB15: 6.499999 | AC15: A+ | AD15: 0.013 | AE15: 0.0015 | AH15: Credit rating | AJ15: =VLOOKUP(AJ14,$AA$5:$AE$17,3) -> A- | AK15: =VLOOKUP(AK14,$AA$5:$AE$17,3) -> BBB | AL15: =VLOOKUP(AL14,$AA$5:$AE$17,3) -> B+ | AM15: =VLOOKUP(AM14,$AA$5:$AE$17,3) -> B | AN15: =VLOOKUP(AN14,$AA$5:$AE$17,3) -> B- | AO15: =VLOOKUP(AO14,$AA$5:$AE$17,3) -> B- | AP15: =VLOOKUP(AP14,$AA$5:$AE$17,3) -> B- | AQ15: =VLOOKUP(AQ14,$AA$5:$AE$17,3) -> B- | ... AS15: =VLOOKUP(AS14,$AA$5:$AE$17,3) -> B-
O16: 12731 | P16: 14060.64 | Q16: 15762.05 | R16: 17811.23 | S16: 20224.55 | T16: 22452.55 | AA16: 6.5 | AB16: 8.499999 | AC16: AA | AD16: 0.0115 | AE16: 0.0005 | AH16: Credit spread | AJ16: =VLOOKUP(AJ14,$AA$5:$AE$17,4) -> 0.0165 | AK16: =VLOOKUP(AK14,$AA$4:$AE$17,4) -> 0.025 | AL16: =VLOOKUP(AL14,$AA$4:$AE$17,4) -> 0.055 | AM16: =VLOOKUP(AM14,$AA$4:$AE$17,4) -> 0.06 | AN16: =VLOOKUP(AN14,$AA$4:$AE$17,4) -> 0.0675 | AO16: =VLOOKUP(AO14,$AA$4:$AE$17,4) -> 0.0675 | AP16: =VLOOKUP(AP14,$AA$4:$AE$17,4) -> 0.0675 | AQ16: =VLOOKUP(AQ14,$AA$4:$AE$17,4) -> 0.0675 | AR16: =VLOOKUP(AR14,$AA$4:$AE$17,4) -> 0.0675 | AS16: =VLOOKUP(AS14,$AA$4:$AE$17,4) -> 0.0675
C17: 420 | D17: 983 | E17: 706 | F17: 2561 | G17: 1532 | H17: 660 | N17: 4950 | O17: 7438 | P17: 8887.15 | Q17: 10449.59 | R17: 12731.48 | S17: 13635.45 | T17: 15430.1 | AA17: 8.5 | AB17: 100000 | AC17: AAA | AD17: 0.0065 | AE17: 0.0001 | AH17: Yield on debt | AJ17: =AJ16+$AH$74 -> 0.0572 | AK17: =AK16+$AH$74 -> 0.0657 | AL17: =AL16+$AH$74 -> 0.0957 | AM17: =AM16+$AH$74 -> 0.1007 | AN17: =AN16+$AH$74 -> 0.1082 | AO17: =AO16+$AH$74 -> 0.1082 | AP17: =AP16+$AH$74 -> 0.1082 | AQ17: =AQ16+$AH$74 -> 0.1082 | ... AS17: =AS16+$AH$74 -> 0.1082
C18: =+C17/C6 -> 0.039848197 | D18: =+D17/D6 -> 0.074009938 | E18: =+E17/E6 -> 0.041291379 | F18: =+F17/F6 -> 0.12050631 | G18: =+G17/G6 -> 0.057828778 | H18: =+H17/H6 -> 0.021051289 | N18: =+N17/N6 -> 0.14200878 | O18: =+O17/O6 -> 0.19627919 | P18: =+P17/P6 -> 0.21545771 | Q18: =+Q17/Q6 -> 0.23222498 | R18: =+R17/R6 -> 0.25783281 | S18: =+S17/S6 -> 0.25133205 | T18: =+T17/T6 -> 0.2604329 | AH18: Interest paid | AI18: =+$D$54*$AH$74 -> 2021.7871 | AJ18: =$D$54*AJ17 -> 2841.4305 | AK18: =$D$54*AK17 -> 3263.6711 | AL18: =$D$54*AL17 -> 4753.9318 | AM18: =$D$54*AM17 -> 5002.3086 | AN18: =$D$54*AN17 -> 5374.8738 | AO18: =$D$54*AO17 -> 5374.8738 | AP18: =$D$54*AP17 -> 5374.8738 | AQ18: =$D$54*AQ17 -> 5374.8738 | ... AS18: =$D$54*AS17 -> 5374.8738
C19: -60 | D19: 127 | E19: -580 | F19: 1511 | G19: -88 | H19: -452 | N19: -814 | O19: -1241 | P19: =+P20-P17 -> -2018.65 | Q19: =+Q20-Q17 -> -2296.99 | R19: =+R20-R17 -> -3049.17 | S19: =+S20-S17 -> -2656.78 | T19: =+T20-T17 -> -2980.77 | AH19: Prob of default | AJ19: =VLOOKUP(AJ14,$AA$5:$AE$17,5) -> 0.003 | AK19: =VLOOKUP(AK14,$AA$5:$AE$17,5) -> 0.004 | AL19: =VLOOKUP(AL14,$AA$5:$AE$17,5) -> 0.03 | AM19: =VLOOKUP(AM14,$AA$5:$AE$17,5) -> 0.052 | AN19: =VLOOKUP(AN14,$AA$5:$AE$17,5) -> 0.07 | AO19: =VLOOKUP(AO14,$AA$5:$AE$17,5) -> 0.07 | AP19: =VLOOKUP(AP14,$AA$5:$AE$17,5) -> 0.07 | AQ19: =VLOOKUP(AQ14,$AA$5:$AE$17,5) -> 0.07 | ... AS19: =VLOOKUP(AS14,$AA$5:$AE$17,5) -> 0.07
C20: =+C17+C19 -> 360 | D20: =+D17+D19 -> 1110 | E20: =+E17+E19 -> 126 | F20: =+F17+F19 -> 4072 | G20: =+G17+G19 -> 1444 | H20: =+H17+H19 -> 208 | N20: =+N17+N19 -> 4136 | O20: =+O17+O19 -> 6197 | P20: 6868.5 | Q20: 8152.6 | R20: 9682.31 | S20: 10978.67 | T20: 12449.33 | AH20: Cost of debt | AJ20: =(1-AJ19+AJ19*$AH$78)*(1+AJ17)-1 -> 0.055328756 | AK20: =(1-AK19+AK19*$AH$78)*(1+AK17)-1 -> 0.063184948 | AL20: =(1-AL19+AL19*$AH$78)*(1+AL17)-1 -> 0.07630611 | AM20: =(1-AM19+AM19*$AH$78)*(1+AM17)-1 -> 0.066930524 | AN20: =(1-AN19+AN19*$AH$78)*(1+AN17)-1 -> 0.06243134 | AO20: =(1-AO19+AO19*$AH$78)*(1+AO17)-1 -> 0.06243134 | AP20: =(1-AP19+AP19*$AH$78)*(1+AP17)-1 -> 0.06243134 | AQ20: =(1-AQ19+AQ19*$AH$78)*(1+AQ17)-1 -> 0.06243134 | ... AS20: =(1-AS19+AS19*$AH$78)*(1+AS17)-1 -> 0.06243134
P21: =+O22*(1+P5) -> 14156.166 | Q21: =+P21*(1+Q5) -> 15335.885 | R21: =+Q21*(1+R5) -> 16696.556 | S21: =+R21*(1+S5) -> 18196.527 | T21: =+S21*(1+T5) -> 19730.667
C22: 2738 | D22: 3398 | E22: 4331 | F22: 4801 | G22: 6000 | H22: 7111 | N22: 10234 | O22: 13092 | P22: 14563.34 | Q22: 15855.26 | R22: 17566.88 | S22: 18236.25 | T22: 20608.25
C23: 417 | D23: 431 | E23: 342 | F23: 238 | G23: 802 | H23: 1188 | N23: 437 | O23: 77 | P23: =+AVERAGE(H23:O23)*(1+P5) -> 613.44827 | Q23: =+P23*(1+Q5) -> 664.57061 | R23: =+Q23*(1+R5) -> 723.53443 | S23: =+R23*(1+S5) -> 788.53469 | T23: =+S23*(1+T5) -> 855.01566 | AH23: Year 2027 | AI23: Iteration 0 | AJ23: Iteration 1 | AK23: Iteration 2 | AL23: Iteration 3 | AM23: Iteration 4 | AN23: Iteration 5 | AO23: Iteration 6 | AP23: Iteration 7 | AQ23: Iteration 8 | AR23: Iteration 9 | AS23: Iteration 10
D24: =+(D23-C23)/C23 -> 0.033573141 | E24: =+(E23-D23)/D23 -> -0.20649652 | F24: =+(F23-E23)/E23 -> -0.30409357 | G24: =+(G23-F23)/F23 -> 2.3697479 | H24: =+(H23-G23)/G23 -> 0.48129676 | N24: =+(N23-H23)/H23 -> -0.63215488 | O24: =+(O23-N23)/N23 -> -0.82379863 | P24: =+(P23-O23)/O23 -> 6.9668606 | Q24: =+(Q23-P23)/P23 -> 0.083336037 | R24: =+(R23-Q23)/Q23 -> 0.08872468 | S24: =+(S23-R23)/R23 -> 0.089837138 | T24: =+(T23-S23)/S23 -> 0.0843095 | AH24: Trailing interest coverage ratio | AJ24: =MAX(MIN($P$14/AI28,100000),-100000) -> 3.2041706 | AK24: =MAX(MIN($P$14/AJ28,100000),-100000) -> 2.2798907 | AL24: =MAX(MIN($P$14/AK28,100000),-100000) -> 1.3626933 | AM24: =MAX(MIN($P$14/AL28,100000),-100000) -> 1.2052657 | AN24: =MAX(MIN($P$14/AM28,100000),-100000) -> 1.0172367 | AO24: =MAX(MIN($P$14/AN28,100000),-100000) -> 1.0172367 | AP24: =MAX(MIN($P$14/AO28,100000),-100000) -> 1.0172367 | AQ24: =MAX(MIN($P$14/AP28,100000),-100000) -> 1.0172367 | ... AS24: =MAX(MIN($P$14/AR28,100000),-100000) -> 1.0172367
C25: =+C22-C23 -> 2321 | D25: =+D22-D23 -> 2967 | E25: =+E22-E23 -> 3989 | F25: =+F22-F23 -> 4563 | G25: =+G22-G23 -> 5198 | H25: =+H22-H23 -> 5923 | N25: =+N22-N23 -> 9797 | O25: =+O22-O23 -> 13015 | P25: =+P22-P23 -> 13949.892 | Q25: =+Q22-Q23 -> 15190.689 | R25: =+R22-R23 -> 16843.346 | S25: =+S22-S23 -> 17447.715 | T25: =+T22-T23 -> 19753.234 | AH25: Credit rating | AJ25: =VLOOKUP(AJ24,$AA$5:$AE$17,3) -> A- | AK25: =VLOOKUP(AK24,$AA$5:$AE$17,3) -> B+ | AL25: =VLOOKUP(AL24,$AA$5:$AE$17,3) -> B- | AM25: =VLOOKUP(AM24,$AA$5:$AE$17,3) -> CCC | AN25: =VLOOKUP(AN24,$AA$5:$AE$17,3) -> CCC | AO25: =VLOOKUP(AO24,$AA$5:$AE$17,3) -> CCC | AP25: =VLOOKUP(AP24,$AA$5:$AE$17,3) -> CCC | AQ25: =VLOOKUP(AQ24,$AA$5:$AE$17,3) -> CCC | ... AS25: =VLOOKUP(AS24,$AA$5:$AE$17,3) -> CCC
T26: =+T25*(1+AH79)/(AH73-AH79) -> 350548 | AH26: Credit spread | AJ26: =VLOOKUP(AJ24,$AA$5:$AE$17,4) -> 0.0165 | AK26: =VLOOKUP(AK24,$AA$5:$AE$17,4) -> 0.055 | AL26: =VLOOKUP(AL24,$AA$5:$AE$17,4) -> 0.0675 | AM26: =VLOOKUP(AM24,$AA$5:$AE$17,4) -> 0.0875 | AN26: =VLOOKUP(AN24,$AA$5:$AE$17,4) -> 0.0875 | AO26: =VLOOKUP(AO24,$AA$5:$AE$17,4) -> 0.0875 | AP26: =VLOOKUP(AP24,$AA$5:$AE$17,4) -> 0.0875 | AQ26: =VLOOKUP(AQ24,$AA$5:$AE$17,4) -> 0.0875 | ... AS26: =VLOOKUP(AS24,$AA$5:$AE$17,4) -> 0.0875
C27: =+C25 -> 2321 | D27: =+D25 -> 2967 | E27: =+E25 -> 3989 | F27: =+F25 -> 4563 | G27: =+G25 -> 5198 | H27: =+H25 -> 5923 | N27: =+N25 -> 9797 | O27: =+O25 -> 13015 | P27: =+P25 -> 13949.892 | Q27: =+Q25 -> 15190.689 | R27: =+R25 -> 16843.346 | S27: =+S25 -> 17447.715 | T27: =+T25+T26 -> 370301.23 | AH27: Yield on debt | AJ27: =AJ26+$AH$74 -> 0.0572 | AK27: =AK26+$AH$74 -> 0.0957 | AL27: =AL26+$AH$74 -> 0.1082 | AM27: =AM26+$AH$74 -> 0.1282 | AN27: =AN26+$AH$74 -> 0.1282 | AO27: =AO26+$AH$74 -> 0.1282 | AP27: =AP26+$AH$74 -> 0.1282 | AQ27: =AQ26+$AH$74 -> 0.1282 | ... AS27: =AS26+$AH$74 -> 0.1282
O28: =+NPV($AH$73,O27:T27) -> 275968.44 | P28: =+NPV($AH$73,P27:T27) -> 288500.95 | Q28: =+NPV($AH$73,Q27:T27) -> 301258.75 | R28: =+NPV($AH$73,R27:T27) -> 313956.79 | S28: =+NPV($AH$73,S27:T27) -> 326177.68 | T28: =+NPV($AH$73,T27) -> 338925.54 | AH28: Interest paid | AI28: =$AH$74*$E$54 -> 2235.2042 | AJ28: =$E$54*AJ27 -> 3141.368 | AK28: =$E$54*AK27 -> 5255.7503 | AL28: =$E$54*AL27 -> 5942.2381 | AM28: =$E$54*AM27 -> 7040.6185 | AN28: =$E$54*AN27 -> 7040.6185 | AO28: =$E$54*AO27 -> 7040.6185 | AP28: =$E$54*AP27 -> 7040.6185 | AQ28: =$E$54*AQ27 -> 7040.6185 | ... AS28: =$E$54*AS27 -> 7040.6185
AH29: Prob of default | AJ29: =VLOOKUP(AJ24,$AA$5:$AE$17,5) -> 0.003 | AK29: =VLOOKUP(AK24,$AA$5:$AE$17,5) -> 0.03 | AL29: =VLOOKUP(AL24,$AA$5:$AE$17,5) -> 0.07 | AM29: =VLOOKUP(AM24,$AA$5:$AE$17,5) -> 0.099 | AN29: =VLOOKUP(AN24,$AA$5:$AE$17,5) -> 0.099 | AO29: =VLOOKUP(AO24,$AA$5:$AE$17,5) -> 0.099 | AP29: =VLOOKUP(AP24,$AA$5:$AE$17,5) -> 0.099 | AQ29: =VLOOKUP(AQ24,$AA$5:$AE$17,5) -> 0.099 | ... AS29: =VLOOKUP(AS24,$AA$5:$AE$17,5) -> 0.099
G30: EXCESS CASH | H30: ='Excess Cash'!I5 -> 3739.2 | N30: Total Value | O30: =H30+O28 -> 279707.64 | AH30: Cost of debt | AJ30: =(1-AJ29+AJ29*$AH$78)*(1+AJ27)-1 -> 0.055328756 | AK30: =(1-AK29+AK29*$AH$78)*(1+AK27)-1 -> 0.07630611 | AL30: =(1-AL29+AL29*$AH$78)*(1+AL27)-1 -> 0.06243134 | AM30: =(1-AM29+AM29*$AH$78)*(1+AM27)-1 -> 0.062301838 | AN30: =(1-AN29+AN29*$AH$78)*(1+AN27)-1 -> 0.062301838 | AO30: =(1-AO29+AO29*$AH$78)*(1+AO27)-1 -> 0.062301838 | AP30: =(1-AP29+AP29*$AH$78)*(1+AP27)-1 -> 0.062301838 | AQ30: =(1-AQ29+AQ29*$AH$78)*(1+AQ27)-1 -> 0.062301838 | ... AS30: =(1-AS29+AS29*$AH$78)*(1+AS27)-1 -> 0.062301838
O32: =+AS8 -> 5739.0068 | P32: =+AS18 -> 5374.8738 | Q32: =+AS28 -> 7040.6185 | R32: =+AS38 -> 6653.3634 | S32: =+AS48 -> 7385.0756 | T32: =+AS58 -> 9763.2056
O33: =$AH$72*$O$32 -> 946.05143 | P33: =$AH$72*$O$32 -> 946.05143 | Q33: =$AH$72*$O$32 -> 946.05143 | R33: =$AH$72*$O$32 -> 946.05143 | S33: =$AH$72*$O$32 -> 946.05143 | T33: =$AH$72*$O$32 -> 946.05143 | AH33: Year 2028 | AI33: Iteration 0 | AJ33: Iteration 1 | AK33: Iteration 2 | AL33: Iteration 3 | AM33: Iteration 4 | AN33: Iteration 5 | AO33: Iteration 6 | AP33: Iteration 7 | AQ33: Iteration 8 | AR33: Iteration 9 | AS33: Iteration 10
T34: =AH72*H54 -> 12554.008 | AH34: Trailing interest coverage ratio | AJ34: =MAX(MIN($Q$14/AI38,100000),-100000) -> 3.5823294 | AK34: =MAX(MIN($Q$14/AJ38,100000),-100000) -> 2.5489652 | AL34: =MAX(MIN($Q$14/AK38,100000),-100000) -> 2.2191904 | AM34: =MAX(MIN($Q$14/AL38,100000),-100000) -> 1.5235194 | AN34: =MAX(MIN($Q$14/AM38,100000),-100000) -> 1.447873 | AO34: =MAX(MIN($Q$14/AN38,100000),-100000) -> 1.3475121 | AP34: =MAX(MIN($Q$14/AO38,100000),-100000) -> 1.3475121 | AQ34: =MAX(MIN($Q$14/AP38,100000),-100000) -> 1.3475121 | ... AS34: =MAX(MIN($Q$14/AR38,100000),-100000) -> 1.3475121
O35: =O33+O34 -> 946.05143 | P35: =P33+P34 -> 946.05143 | Q35: =Q33+Q34 -> 946.05143 | R35: =R33+R34 -> 946.05143 | S35: =S33+S34 -> 946.05143 | T35: =T33+T34 -> 13500.06 | AH35: Credit rating | AJ35: =VLOOKUP(AJ34,$AA$5:$AE$17,3) -> A- | AK35: =VLOOKUP(AK34,$AA$5:$AE$17,3) -> BBB | AL35: =VLOOKUP(AL34,$AA$5:$AE$17,3) -> B+ | AM35: =VLOOKUP(AM34,$AA$5:$AE$17,3) -> B | AN35: =VLOOKUP(AN34,$AA$5:$AE$17,3) -> B- | AO35: =VLOOKUP(AO34,$AA$5:$AE$17,3) -> B- | AP35: =VLOOKUP(AP34,$AA$5:$AE$17,3) -> B- | AQ35: =VLOOKUP(AQ34,$AA$5:$AE$17,3) -> B- | ... AS35: =VLOOKUP(AS34,$AA$5:$AE$17,3) -> B-
O36: =+$AS$10 -> 0.062301838 | P36: =+$AS$20 -> 0.06243134 | Q36: =+$AS$30 -> 0.062301838 | R36: =+$AS$30 -> 0.062301838 | S36: =+$AS$40 -> 0.06243134 | T36: =+$AS$50 -> 0.06243134 | AH36: Credit spread | AJ36: =VLOOKUP(AJ34,$AA$4:$AE$17,4) -> 0.0165 | AK36: =VLOOKUP(AK34,$AA$4:$AE$17,4) -> 0.025 | AL36: =VLOOKUP(AL34,$AA$4:$AE$17,4) -> 0.055 | AM36: =VLOOKUP(AM34,$AA$4:$AE$17,4) -> 0.06 | AN36: =VLOOKUP(AN34,$AA$4:$AE$17,4) -> 0.0675 | AO36: =VLOOKUP(AO34,$AA$4:$AE$17,4) -> 0.0675 | AP36: =VLOOKUP(AP34,$AA$4:$AE$17,4) -> 0.0675 | AQ36: =VLOOKUP(AQ34,$AA$4:$AE$17,4) -> 0.0675 | ... AS36: =VLOOKUP(AS34,$AA$4:$AE$17,4) -> 0.0675
O37: =IF(O3=2025,O36,(1+$AH$73)*(((1+O36)/(1+$AH$73))^(1/(O3-2024)))-1) -> 0.062301838 | P37: =IF(P3=2025,P36,(1+$AH$73)*(((1+P36)/(1+$AH$73))^(1/(P3-2024)))-1) -> 0.077397265 | Q37: =IF(Q3=2025,Q36,(1+$AH$73)*(((1+Q36)/(1+$AH$73))^(1/(Q3-2024)))-1) -> 0.082388627 | R37: =IF(R3=2025,R36,(1+$AH$73)*(((1+R36)/(1+$AH$73))^(1/(R3-2024)))-1) -> 0.084926035 | S37: =IF(S3=2025,S36,(1+$AH$73)*(((1+S36)/(1+$AH$73))^(1/(S3-2024)))-1) -> 0.086477822 | T37: =IF(T3=2025,T36,(1+$AH$73)*(((1+T36)/(1+$AH$73))^(1/(T3-2024)))-1) -> 0.087491486 | AH37: Yield on debt | AJ37: =AJ36+$AH$74 -> 0.0572 | AK37: =AK36+$AH$74 -> 0.0657 | AL37: =AL36+$AH$74 -> 0.0957 | AM37: =AM36+$AH$74 -> 0.1007 | AN37: =AN36+$AH$74 -> 0.1082 | AO37: =AO36+$AH$74 -> 0.1082 | AP37: =AP36+$AH$74 -> 0.1082 | AQ37: =AQ36+$AH$74 -> 0.1082 | ... AS37: =AS36+$AH$74 -> 0.1082
O38: =O35/(1+O37)^(O3-2024) -> 890.56744 | P38: =P35/(1+P37)^(P3-2024) -> 815.01013 | Q38: =Q35/(1+Q37)^(Q3-2024) -> 746.04511 | R38: =R35/(1+R37)^(R3-2024) -> 682.83256 | S38: =S35/(1+S37)^(S3-2024) -> 624.89985 | T38: =T35/(1+T37)^(T3-2024) -> 8161.6976 | AH38: Interest paid | AI38: =$AH$74*$F$54 -> 2502.6977 | AJ38: =$F$54*AJ37 -> 3517.3049 | AK38: =$F$54*AK37 -> 4039.9813 | AL38: =$F$54*AL37 -> 5884.7216 | AM38: =$F$54*AM37 -> 6192.1783 | AN38: =$F$54*AN37 -> 6653.3634 | AO38: =$F$54*AO37 -> 6653.3634 | AP38: =$F$54*AP37 -> 6653.3634 | AQ38: =$F$54*AQ37 -> 6653.3634 | ... AS38: =$F$54*AS37 -> 6653.3634
O39: =SUM(O38:T38) -> 11921.053 | AH39: Prob of default | AJ39: =VLOOKUP(AJ34,$AA$5:$AE$17,5) -> 0.003 | AK39: =VLOOKUP(AK34,$AA$5:$AE$17,5) -> 0.004 | AL39: =VLOOKUP(AL34,$AA$5:$AE$17,5) -> 0.03 | AM39: =VLOOKUP(AM34,$AA$5:$AE$17,5) -> 0.052 | AN39: =VLOOKUP(AN34,$AA$5:$AE$17,5) -> 0.07 | AO39: =VLOOKUP(AO34,$AA$5:$AE$17,5) -> 0.07 | AP39: =VLOOKUP(AP34,$AA$5:$AE$17,5) -> 0.07 | AQ39: =VLOOKUP(AQ34,$AA$5:$AE$17,5) -> 0.07 | ... AS39: =VLOOKUP(AS34,$AA$5:$AE$17,5) -> 0.07
O40: =O35/(1+O37)+P35/((1+P37)^2)+Q35/((1+Q37)^3)+R35/((1+R37)^4)+S35/((1+S37)^5)+T35/((1+T37)^6) -> 11921.053 | P40: =P35/((1+P37)^1)+Q35/((1+Q37)^2)+R35/((1+R37)^3)+S35/((1+S37)^4)+T35/((1+T37)^5) -> 11981.14 | Q40: =+Q35/((1+Q37)^1)+R35/((1+R37)^2)+S35/((1+S37)^3)+T35/((1+T37)^4) -> 12067.763 | R40: =+R35/((1+R37)^1)+S35/((1+S37)^2)+T35/((1+T37)^3) -> 12170.268 | S40: =+S35/((1+S37)^1)+T35/((1+T37)^2) -> 12285.962 | T40: =+T35/((1+T37)^1) -> 12413.945 | AH40: Cost of debt | AJ40: =(1-AJ39+AJ39*$AH$78)*(1+AJ37)-1 -> 0.055328756 | AK40: =(1-AK39+AK39*$AH$78)*(1+AK37)-1 -> 0.063184948 | AL40: =(1-AL39+AL39*$AH$78)*(1+AL37)-1 -> 0.07630611 | AM40: =(1-AM39+AM39*$AH$78)*(1+AM37)-1 -> 0.066930524 | AN40: =(1-AN39+AN39*$AH$78)*(1+AN37)-1 -> 0.06243134 | AO40: =(1-AO39+AO39*$AH$78)*(1+AO37)-1 -> 0.06243134 | AP40: =(1-AP39+AP39*$AH$78)*(1+AP37)-1 -> 0.06243134 | AQ40: =(1-AQ39+AQ39*$AH$78)*(1+AQ37)-1 -> 0.06243134 | ... AS40: =(1-AS39+AS39*$AH$78)*(1+AS37)-1 -> 0.06243134
O43: =($AS$6)/((1+$AS$7)*(1-$AH$78)) -> 0.13145283 | P43: =($AS$16)/((1+$AS$17)*(1-$AH$78)) -> 0.10323658 | Q43: =($AS$26)/((1+$AS$27)*(1-$AH$78)) -> 0.13145283 | R43: =($AS$36)/((1+$AS$37)*(1-$AH$78)) -> 0.10323658 | S43: =($AS$46)/((1+$AS$47)*(1-$AH$78)) -> 0.10323658 | T43: =($AS$56)/((1+$AS$57)*(1-$AH$78)) -> 0.13145283 | AH43: Year 2029 | AI43: Iteration 0 | AJ43: Iteration 1 | AK43: Iteration 2 | AL43: Iteration 3 | AM43: Iteration 4 | AN43: Iteration 5 | AO43: Iteration 6 | AP43: Iteration 7 | AQ43: Iteration 8 | AR43: Iteration 9 | AS43: Iteration 10
O44: =(O43*($AH$77)*O28+(1-O43)*P44)/(1+$AH$74) -> 75892.474 | P44: =(P43*($AH$77)*P28+(1-P43)*Q44)/(1+$AH$74) -> 71137.275 | Q44: =(Q43*($AH$77)*Q28+(1-Q43)*R44)/(1+$AH$74) -> 66812.512 | R44: =(R43*($AH$77)*R28+(1-R43)*S44)/(1+$AH$74) -> 58443.294 | S44: =(S43*($AH$77)*S28+(1-S43)*T44)/(1+$AH$74) -> 50692 | T44: =(T43/(AH77+AH74))*AH77*T28 -> 41029.707 | AH44: Trailing interest coverage ratio | AJ44: =MAX(MIN($R$14/AI48,100000),-100000) -> 3.5567593 | AK44: =MAX(MIN($R$14/AJ48,100000),-100000) -> 2.530771 | AL44: =MAX(MIN($R$14/AK48,100000),-100000) -> 2.2033501 | AM44: =MAX(MIN($R$14/AL48,100000),-100000) -> 1.5126448 | AN44: =MAX(MIN($R$14/AM48,100000),-100000) -> 1.4375383 | AO44: =MAX(MIN($R$14/AN48,100000),-100000) -> 1.3378937 | AP44: =MAX(MIN($R$14/AO48,100000),-100000) -> 1.3378937 | AQ44: =MAX(MIN($R$14/AP48,100000),-100000) -> 1.3378937 | ... AS44: =MAX(MIN($R$14/AR48,100000),-100000) -> 1.3378937
AH45: Credit rating | AJ45: =VLOOKUP(AJ44,$AA$5:$AE$17,3) -> A- | AK45: =VLOOKUP(AK44,$AA$5:$AE$17,3) -> BBB | AL45: =VLOOKUP(AL44,$AA$5:$AE$17,3) -> B+ | AM45: =VLOOKUP(AM44,$AA$5:$AE$17,3) -> B | AN45: =VLOOKUP(AN44,$AA$5:$AE$17,3) -> B- | AO45: =VLOOKUP(AO44,$AA$5:$AE$17,3) -> B- | AP45: =VLOOKUP(AP44,$AA$5:$AE$17,3) -> B- | AQ45: =VLOOKUP(AQ44,$AA$5:$AE$17,3) -> B- | ... AS45: =VLOOKUP(AS44,$AA$5:$AE$17,3) -> B-
AH46: Credit spread | AJ46: =VLOOKUP(AJ44,$AA$4:$AE$17,4) -> 0.0165 | AK46: =VLOOKUP(AK44,$AA$4:$AE$17,4) -> 0.025 | AL46: =VLOOKUP(AL44,$AA$4:$AE$17,4) -> 0.055 | AM46: =VLOOKUP(AM44,$AA$4:$AE$17,4) -> 0.06 | AN46: =VLOOKUP(AN44,$AA$4:$AE$17,4) -> 0.0675 | AO46: =VLOOKUP(AO44,$AA$4:$AE$17,4) -> 0.0675 | AP46: =VLOOKUP(AP44,$AA$4:$AE$17,4) -> 0.0675 | AQ46: =VLOOKUP(AQ44,$AA$4:$AE$17,4) -> 0.0675 | ... AS46: =VLOOKUP(AS44,$AA$4:$AE$17,4) -> 0.0675
C47: 2025 | D47: 2026 | E47: 2027 | F47: 2028 | G47: 2029 | H47: 2030 | AH47: Yield on debt | AJ47: =AJ46+$AH$74 -> 0.0572 | AK47: =AK46+$AH$74 -> 0.0657 | AL47: =AL46+$AH$74 -> 0.0957 | AM47: =AM46+$AH$74 -> 0.1007 | AN47: =AN46+$AH$74 -> 0.1082 | AO47: =AO46+$AH$74 -> 0.1082 | AP47: =AP46+$AH$74 -> 0.1082 | AQ47: =AQ46+$AH$74 -> 0.1082 | ... AS47: =AS46+$AH$74 -> 0.1082
C48: =+O28 -> 275968.44 | D48: =+P28 -> 288500.95 | E48: =+Q28 -> 301258.75 | F48: =+R28 -> 313956.79 | G48: =+S28 -> 326177.68 | H48: =+T28 -> 338925.54 | AH48: Interest paid | AI48: =$AH$74*$G$54 -> 2777.9351 | AJ48: =$G$54*AJ47 -> 3904.125 | AK48: =$G$54*AK47 -> 4484.2834 | AL48: =$G$54*AL47 -> 6531.9014 | AM48: =$G$54*AM47 -> 6873.1711 | AN48: =$G$54*AN47 -> 7385.0756 | AO48: =$G$54*AO47 -> 7385.0756 | AP48: =$G$54*AP47 -> 7385.0756 | AQ48: =$G$54*AQ47 -> 7385.0756 | ... AS48: =$G$54*AS47 -> 7385.0756
C49: =O39 -> 11921.053 | D49: =P40 -> 11981.14 | E49: =Q40 -> 12067.763 | F49: =R40 -> 12170.268 | G49: =S40 -> 12285.962 | H49: =T40 -> 12413.945 | AH49: Prob of default | AJ49: =VLOOKUP(AJ44,$AA$5:$AE$17,5) -> 0.003 | AK49: =VLOOKUP(AK44,$AA$5:$AE$17,5) -> 0.004 | AL49: =VLOOKUP(AL44,$AA$5:$AE$17,5) -> 0.03 | AM49: =VLOOKUP(AM44,$AA$5:$AE$17,5) -> 0.052 | AN49: =VLOOKUP(AN44,$AA$5:$AE$17,5) -> 0.07 | AO49: =VLOOKUP(AO44,$AA$5:$AE$17,5) -> 0.07 | AP49: =VLOOKUP(AP44,$AA$5:$AE$17,5) -> 0.07 | AQ49: =VLOOKUP(AQ44,$AA$5:$AE$17,5) -> 0.07 | ... AS49: =VLOOKUP(AS44,$AA$5:$AE$17,5) -> 0.07
C50: =O44 -> 75892.474 | D50: =P44 -> 71137.275 | E50: =Q44 -> 66812.512 | F50: =R44 -> 58443.294 | G50: =S44 -> 50692 | H50: =T44 -> 41029.707 | AH50: Cost of debt | AJ50: =(1-AJ49+AJ49*$AH$78)*(1+AJ47)-1 -> 0.055328756 | AK50: =(1-AK49+AK49*$AH$78)*(1+AK47)-1 -> 0.063184948 | AL50: =(1-AL49+AL49*$AH$78)*(1+AL47)-1 -> 0.07630611 | AM50: =(1-AM49+AM49*$AH$78)*(1+AM47)-1 -> 0.066930524 | AN50: =(1-AN49+AN49*$AH$78)*(1+AN47)-1 -> 0.06243134 | AO50: =(1-AO49+AO49*$AH$78)*(1+AO47)-1 -> 0.06243134 | AP50: =(1-AP49+AP49*$AH$78)*(1+AP47)-1 -> 0.06243134 | AQ50: =(1-AQ49+AQ49*$AH$78)*(1+AQ47)-1 -> 0.06243134 | ... AS50: =(1-AS49+AS49*$AH$78)*(1+AS47)-1 -> 0.06243134
C51: =C48+C49-C50 -> 211997.02 | D51: =D48+D49-D50 -> 229344.81 | E51: =E48+E49-E50 -> 246514 | F51: =F48+F49-F50 -> 267683.76 | G51: =G48+G49-G50 -> 287771.64 | H51: =H48+H49-H50 -> 310309.78
C53: =C54/C51 -> 0.21116355 | D53: =D54/D51 -> 0.21659683 | E53: =E54/E51 -> 0.22278257 | F53: =F54/F51 -> 0.22971638 | G53: =G54/G51 -> 0.23718089 | H53: =H54/H51 -> 0.24541943 | AH53: Year 2030 | AI53: Iteration 0 | AJ53: Iteration 1 | AK53: Iteration 2 | AL53: Iteration 3 | AM53: Iteration 4 | AN53: Iteration 5 | AO53: Iteration 6 | AP53: Iteration 7 | AQ53: Iteration 8 | AR53: Iteration 9 | AS53: Iteration 10
C54: 44766.044 | D54: 49675.359 | E54: 54919.021 | F54: 61491.344 | G54: 68253.934 | H54: 76156.05 | O54: =+(C53-0.25)^2 -> 0.0015082698 | P54: =+(D53-0.25)^2 -> 0.0011157721 | Q54: =+(E53-0.25)^2 -> 0.00074078868 | R54: =+(F53-0.25)^2 -> 0.00041142536 | S54: =+(G53-0.25)^2 -> 0.00016432961 | T54: =+(H53-0.25)^2 -> 2.0981582e-05 | Z54: =+SUM(O54:T54) -> 0.0039615671 | AH54: Trailing interest coverage ratio | AJ54: =MAX(MIN($S$14/AI58,100000),-100000) -> 3.1556971 | AK54: =MAX(MIN($S$14/AJ58,100000),-100000) -> 2.2453998 | AL54: =MAX(MIN($S$14/AK58,100000),-100000) -> 1.3420781 | AM54: =MAX(MIN($S$14/AL58,100000),-100000) -> 1.1870321 | AN54: =MAX(MIN($S$14/AM58,100000),-100000) -> 1.0018477 | AO54: =MAX(MIN($S$14/AN58,100000),-100000) -> 1.0018477 | AP54: =MAX(MIN($S$14/AO58,100000),-100000) -> 1.0018477 | AQ54: =MAX(MIN($S$14/AP58,100000),-100000) -> 1.0018477 | ... AS54: =MAX(MIN($S$14/AR58,100000),-100000) -> 1.0018477
AH55: Credit rating | AJ55: =VLOOKUP(AJ54,$AA$5:$AE$17,3) -> A- | AK55: =VLOOKUP(AK54,$AA$5:$AE$17,3) -> B+ | AL55: =VLOOKUP(AL54,$AA$5:$AE$17,3) -> B- | AM55: =VLOOKUP(AM54,$AA$5:$AE$17,3) -> CCC | AN55: =VLOOKUP(AN54,$AA$5:$AE$17,3) -> CCC | AO55: =VLOOKUP(AO54,$AA$5:$AE$17,3) -> CCC | AP55: =VLOOKUP(AP54,$AA$5:$AE$17,3) -> CCC | AQ55: =VLOOKUP(AQ54,$AA$5:$AE$17,3) -> CCC | ... AS55: =VLOOKUP(AS54,$AA$5:$AE$17,3) -> CCC
AH56: Credit spread | AJ56: =VLOOKUP(AJ54,$AA$4:$AE$17,4) -> 0.0165 | AK56: =VLOOKUP(AK54,$AA$4:$AE$17,4) -> 0.055 | AL56: =VLOOKUP(AL54,$AA$4:$AE$17,4) -> 0.0675 | AM56: =VLOOKUP(AM54,$AA$4:$AE$17,4) -> 0.0875 | AN56: =VLOOKUP(AN54,$AA$4:$AE$17,4) -> 0.0875 | AO56: =VLOOKUP(AO54,$AA$4:$AE$17,4) -> 0.0875 | AP56: =VLOOKUP(AP54,$AA$4:$AE$17,4) -> 0.0875 | AQ56: =VLOOKUP(AQ54,$AA$4:$AE$17,4) -> 0.0875 | ... AS56: =VLOOKUP(AS54,$AA$4:$AE$17,4) -> 0.0875
AH57: Yield on debt | AJ57: =AJ56+$AH$74 -> 0.0572 | AK57: =AK56+$AH$74 -> 0.0957 | AL57: =AL56+$AH$74 -> 0.1082 | AM57: =AM56+$AH$74 -> 0.1282 | AN57: =AN56+$AH$74 -> 0.1282 | AO57: =AO56+$AH$74 -> 0.1282 | AP57: =AP56+$AH$74 -> 0.1282 | AQ57: =AQ56+$AH$74 -> 0.1282 | ... AS57: =AS56+$AH$74 -> 0.1282
AH58: Interest paid | AI58: =$AH$74*$H$54 -> 3099.5512 | AJ58: =$H$54*AJ57 -> 4356.126 | AK58: =$H$54*AK57 -> 7288.134 | AL58: =$H$54*AL57 -> 8240.0846 | AM58: =$H$54*AM57 -> 9763.2056 | AN58: =$H$54*AN57 -> 9763.2056 | AO58: =$H$54*AO57 -> 9763.2056 | AP58: =$H$54*AP57 -> 9763.2056 | AQ58: =$H$54*AQ57 -> 9763.2056 | ... AS58: =$H$54*AS57 -> 9763.2056
AH59: Prob of default | AJ59: =VLOOKUP(AJ54,$AA$5:$AE$17,5) -> 0.003 | AK59: =VLOOKUP(AK54,$AA$5:$AE$17,5) -> 0.03 | AL59: =VLOOKUP(AL54,$AA$5:$AE$17,5) -> 0.07 | AM59: =VLOOKUP(AM54,$AA$5:$AE$17,5) -> 0.099 | AN59: =VLOOKUP(AN54,$AA$5:$AE$17,5) -> 0.099 | AO59: =VLOOKUP(AO54,$AA$5:$AE$17,5) -> 0.099 | AP59: =VLOOKUP(AP54,$AA$5:$AE$17,5) -> 0.099 | AQ59: =VLOOKUP(AQ54,$AA$5:$AE$17,5) -> 0.099 | ... AS59: =VLOOKUP(AS54,$AA$5:$AE$17,5) -> 0.099
AH60: Cost of debt | AJ60: =(1-AJ59+AJ59*$AH$78)*(1+AJ57)-1 -> 0.055328756 | AK60: =(1-AK59+AK59*$AH$78)*(1+AK57)-1 -> 0.07630611 | AL60: =(1-AL59+AL59*$AH$78)*(1+AL57)-1 -> 0.06243134 | AM60: =(1-AM59+AM59*$AH$78)*(1+AM57)-1 -> 0.062301838 | AN60: =(1-AN59+AN59*$AH$78)*(1+AN57)-1 -> 0.062301838 | AO60: =(1-AO59+AO59*$AH$78)*(1+AO57)-1 -> 0.062301838 | AP60: =(1-AP59+AP59*$AH$78)*(1+AP57)-1 -> 0.062301838 | AQ60: =(1-AQ59+AQ59*$AH$78)*(1+AQ57)-1 -> 0.062301838 | ... AS60: =(1-AS59+AS59*$AH$78)*(1+AS57)-1 -> 0.062301838
AG70: ASSUMPTIONS
AG72: Tax rate | AH72: ='Leverage finale'!C62 -> 0.16484584
B73: 2024 | C73: 2025 | D73: 2026 | E73: 2027 | F73: 2028 | G73: 2029 | H73: 2030 | I73: 2031 | J73: 2032 | K73: 2033 | L73: 2034 | M73: 2035 | AG73: Unlevered cost of capital | AH73: ='Leverage finale'!C63 -> 0.092574006
A74: FCF | B74: ='Leverage finale'!J26 -> 9797 | C74: ='Leverage finale'!K26 -> 13015 | D74: ='Leverage finale'!L26 -> 10986.1 | E74: ='Leverage finale'!M26 -> 12192.728 | F74: ='Leverage finale'!N26 -> 13376.522 | G74: ='Leverage finale'!O26 -> 14693.228 | H74: ='Leverage finale'!P26 -> 16041.137 | I74: ='Leverage finale'!Q26 -> 17317.134 | ... L74: ='Leverage finale'!T26 -> 20387.256 | M74: ='Leverage finale'!U24 -> 21181.467 | AG74: Risk-Free Rate | AH74: =+'Unlevered Cost of Capital'!D24 -> 0.0407
A75: % YOY increase in FCF | C75: =(C74-B74)/B74 -> 0.3284679 | D75: =(D74-C74)/C74 -> -0.15588938 | E75: =(E74-D74)/D74 -> 0.10983229 | F75: =(F74-E74)/E74 -> 0.09709016 | G75: =(G74-F74)/F74 -> 0.098434123 | H75: =(H74-G74)/G74 -> 0.091736752 | I75: =(I74-H74)/H74 -> 0.079545286 | J75: =(J74-I74)/I74 -> 0.059337265 | ... M75: =(M74-L74)/L74 -> 0.038956244 | AG75: Market Risk Premium | AH75: ='Leverage finale'!C65 -> 0.042479688
O76: NEW FCF VALUES (AVG OF MONTECARLO RESULTS) | Z76: NEW VALUE TV (AVG MONTECARLO RESULTS)
O77: =AVERAGE(O79:O1078) -> 13002.861 | P77: =AVERAGE(P79:P1078) -> 10993.76 | Q77: =AVERAGE(Q79:Q1078) -> 12187.667 | R77: =AVERAGE(R79:R1078) -> 13370.822 | S77: =AVERAGE(S79:S1078) -> 14683.806 | T77: =AVERAGE(T79:T1078) -> 16051.469 | U77: =AVERAGE(U79:U1078) -> 17322.107 | V77: =AVERAGE(V79:V1078) -> 18354.746 | ... Z77: =AVERAGE(Z79:Z1078) -> 376075.11 | AG77: Bakruptcy cost as % of firm value | AH77: ='Leverage finale'!C67 -> 0.474
C78: Growth rate 1 randomized | D78: Growth rate 2 randomized | E78: Growth rate 3 randomized | F78: Growth rate 4 randomized | G78: Growth rate 5 randomized | H78: Growth rate 6 randomized | I78: Growth rate 7 randomized | J78: Growth rate 8 randomized | K78: Growth rate 9 randomized | L78: Growth rate 10 randomized | M78: Growth rate 5 randomized | O78: FCF1 | P78: FCF2 | Q78: FCF3 | R78: FCF4 | S78: FCF5 | T78: FCF6 | U78: FCF7 | V78: FCF8 | W78: FCF9 | X78: FCF10 | Y78: FCF11 | Z78: TERMINAL VALUE | AA78: TOTAL FCF11 | AB78: VALUE UNLEVERED | AC78: STOCK PRICE | AD78: STOCK PRICE FIXED | AG78: Recovery in case of default | AH78: ='Leverage finale'!C68 -> 0.41
B79: 1 | C79: =C$75+_xlfn.NORM.INV(RAND(),0, $AH$80) -> 0.32878851 | D79: =D$75+_xlfn.NORM.INV(RAND(),0, $AH$80) -> -0.1697783 | E79: =E$75+_xlfn.NORM.INV(RAND(),0, $AH$80) -> 0.10633801 | F79: =F$75+_xlfn.NORM.INV(RAND(),0, $AH$80) -> 0.065040257 | G79: =G$75+_xlfn.NORM.INV(RAND(),0, $AH$80) -> 0.10231501 | H79: =H$75+_xlfn.NORM.INV(RAND(),0, $AH$80) -> 0.1102605 | I79: =I$75+_xlfn.NORM.INV(RAND(),0, $AH$80) -> 0.083550873 | J79: =J$75+_xlfn.NORM.INV(RAND(),0, $AH$80) -> 0.069218225 | ... M79: =M$75+_xlfn.NORM.INV(RAND(),0, $AH$80) -> 0.0082046358 | O79: =$B$74*(1+$C79) -> 13018.141 | P79: =$C$74*(1+$D79) -> 10805.335 | Q79: =$D$74*(1+$E79) -> 12154.34 | R79: =$E$74*(1+$F79) -> 12985.746 | S79: =$F$74*(1+$G79) -> 14745.141 | T79: =$G$74*(1+$H79) -> 16313.311 | U79: =$H$74*(1+$I79) -> 17381.388 | V79: =$I$74*(1+$J79) -> 18515.796 | W79: =$J$74*(1+$K79) -> 18887.838 | X79: =$K$74*(1+$L79) -> 20228.399 | Y79: =$L$74*(1+$M79) -> 20554.526 | Z79: =($Y79*(1+$AH$79))/($AH$73-$AH$79) -> 364768.01 | AA79: =SUM(Y79:Z79) -> 385322.53 | AB79: =NPV($AH$73,O79:X79,AA79) -> 239291.81 | AC79: =((AB79+$AH$82-$AH$83)-$AH$85)/($AH$87-($AH$87*$AH$85/(AB79+$AH$82-$AH$83))) -> 216.98879 | AD79: 223.23453 | AG79: Long term growth rate | AH79: ='Leverage finale'!C69 -> 0.034292077
B80: 2 | C80: =C$75+_xlfn.NORM.INV(RAND(),0, $AH$80) -> 0.35294393 | D80: =D$75+_xlfn.NORM.INV(RAND(),0, $AH$80) -> -0.15549119 | E80: =E$75+_xlfn.NORM.INV(RAND(),0, $AH$80) -> 0.11090674 | F80: =F$75+_xlfn.NORM.INV(RAND(),0, $AH$80) -> 0.047719373 | G80: =G$75+_xlfn.NORM.INV(RAND(),0, $AH$80) -> 0.097770172 | H80: =H$75+_xlfn.NORM.INV(RAND(),0, $AH$80) -> 0.09720787 | I80: =I$75+_xlfn.NORM.INV(RAND(),0, $AH$80) -> 0.083540263 | J80: =J$75+_xlfn.NORM.INV(RAND(),0, $AH$80) -> 0.058456311 | ... M80: =M$75+_xlfn.NORM.INV(RAND(),0, $AH$80) -> 0.072407715 | O80: =$B$74*(1+$C80) -> 13254.792 | P80: =$C$74*(1+$D80) -> 10991.282 | Q80: =$D$74*(1+$E80) -> 12204.532 | R80: =$E$74*(1+$F80) -> 12774.558 | S80: =$F$74*(1+$G80) -> 14684.347 | T80: =$G$74*(1+$H80) -> 16121.526 | U80: =$H$74*(1+$I80) -> 17381.218 | V80: =$I$74*(1+$J80) -> 18329.43 | W80: =$J$74*(1+$K80) -> 19530.498 | X80: =$K$74*(1+$L80) -> 20161.408 | Y80: =$L$74*(1+$M80) -> 21863.451 | Z80: =($Y80*(1+$AH$79))/($AH$73-$AH$79) -> 387996.65 | AA80: =SUM(Y80:Z80) -> 409860.1 | AB80: =NPV($AH$73,O80:X80,AA80) -> 248838.4 | AC80: =((AB80+$AH$82-$AH$83)-$AH$85)/($AH$87-($AH$87*$AH$85/(AB80+$AH$82-$AH$83))) -> 227.01672 | AD80: 222.9712 | AG80: Standard deviation | AH80: 0.02
B81: 3 | C81: =C$75+_xlfn.NORM.INV(RAND(),0, $AH$80) -> 0.29277104 | D81: =D$75+_xlfn.NORM.INV(RAND(),0, $AH$80) -> -0.16270765 | E81: =E$75+_xlfn.NORM.INV(RAND(),0, $AH$80) -> 0.13976894 | F81: =F$75+_xlfn.NORM.INV(RAND(),0, $AH$80) -> 0.095089259 | G81: =G$75+_xlfn.NORM.INV(RAND(),0, $AH$80) -> 0.090660807 | H81: =H$75+_xlfn.NORM.INV(RAND(),0, $AH$80) -> 0.098361522 | I81: =I$75+_xlfn.NORM.INV(RAND(),0, $AH$80) -> 0.066549178 | J81: =J$75+_xlfn.NORM.INV(RAND(),0, $AH$80) -> 0.054913139 | ... M81: =M$75+_xlfn.NORM.INV(RAND(),0, $AH$80) -> 0.04563735 | O81: =$B$74*(1+$C81) -> 12665.278 | P81: =$C$74*(1+$D81) -> 10897.36 | Q81: =$D$74*(1+$E81) -> 12521.615 | R81: =$E$74*(1+$F81) -> 13352.126 | S81: =$F$74*(1+$G81) -> 14589.248 | T81: =$G$74*(1+$H81) -> 16138.477 | U81: =$H$74*(1+$I81) -> 17108.662 | V81: =$I$74*(1+$J81) -> 18268.072 | W81: =$J$74*(1+$K81) -> 19583.269 | X81: =$K$74*(1+$L81) -> 19238.805 | Y81: =$L$74*(1+$M81) -> 21317.676 | Z81: =($Y81*(1+$AH$79))/($AH$73-$AH$79) -> 378311.15 | AA81: =SUM(Y81:Z81) -> 399628.82 | AB81: =NPV($AH$73,O81:X81,AA81) -> 244420.35 | AC81: =((AB81+$AH$82-$AH$83)-$AH$85)/($AH$87-($AH$87*$AH$85/(AB81+$AH$82-$AH$83))) -> 222.37592 | AD81: 218.23208
B82: 4 | C82: =C$75+_xlfn.NORM.INV(RAND(),0, $AH$80) -> 0.3430121 | D82: =D$75+_xlfn.NORM.INV(RAND(),0, $AH$80) -> -0.12214361 | E82: =E$75+_xlfn.NORM.INV(RAND(),0, $AH$80) -> 0.11060041 | F82: =F$75+_xlfn.NORM.INV(RAND(),0, $AH$80) -> 0.089654391 | G82: =G$75+_xlfn.NORM.INV(RAND(),0, $AH$80) -> 0.092563046 | H82: =H$75+_xlfn.NORM.INV(RAND(),0, $AH$80) -> 0.096740891 | I82: =I$75+_xlfn.NORM.INV(RAND(),0, $AH$80) -> 0.099406604 | J82: =J$75+_xlfn.NORM.INV(RAND(),0, $AH$80) -> 0.020735778 | ... M82: =M$75+_xlfn.NORM.INV(RAND(),0, $AH$80) -> 0.02865203 | O82: =$B$74*(1+$C82) -> 13157.49 | P82: =$C$74*(1+$D82) -> 11425.301 | Q82: =$D$74*(1+$E82) -> 12201.167 | R82: =$E$74*(1+$F82) -> 13285.86 | S82: =$F$74*(1+$G82) -> 14614.694 | T82: =$G$74*(1+$H82) -> 16114.664 | U82: =$H$74*(1+$I82) -> 17635.732 | V82: =$I$74*(1+$J82) -> 17676.219 | W82: =$J$74*(1+$K82) -> 19765.104 | X82: =$K$74*(1+$L82) -> 20228.715 | Y82: =$L$74*(1+$M82) -> 20971.392 | Z82: =($Y82*(1+$AH$79))/($AH$73-$AH$79) -> 372165.86 | AA82: =SUM(Y82:Z82) -> 393137.26 | AB82: =NPV($AH$73,O82:X82,AA82) -> 243054.49 | AC82: =((AB82+$AH$82-$AH$83)-$AH$85)/($AH$87-($AH$87*$AH$85/(AB82+$AH$82-$AH$83))) -> 220.94119 | AD82: 222.97348 | AG82: PV of tax shields | AH82: ='Leverage finale'!C50 -> 11136.895
B83: 5 | C83: =C$75+_xlfn.NORM.INV(RAND(),0, $AH$80) -> 0.31838655 | D83: =D$75+_xlfn.NORM.INV(RAND(),0, $AH$80) -> -0.15821758 | E83: =E$75+_xlfn.NORM.INV(RAND(),0, $AH$80) -> 0.099743916 | F83: =F$75+_xlfn.NORM.INV(RAND(),0, $AH$80) -> 0.10973074 | G83: =G$75+_xlfn.NORM.INV(RAND(),0, $AH$80) -> 0.10415595 | H83: =H$75+_xlfn.NORM.INV(RAND(),0, $AH$80) -> 0.055750259 | I83: =I$75+_xlfn.NORM.INV(RAND(),0, $AH$80) -> 0.074254602 | J83: =J$75+_xlfn.NORM.INV(RAND(),0, $AH$80) -> 0.055074728 | ... M83: =M$75+_xlfn.NORM.INV(RAND(),0, $AH$80) -> 0.042479125 | O83: =$B$74*(1+$C83) -> 12916.233 | P83: =$C$74*(1+$D83) -> 10955.798 | Q83: =$D$74*(1+$E83) -> 12081.896 | R83: =$E$74*(1+$F83) -> 13530.645 | S83: =$F$74*(1+$G83) -> 14769.766 | T83: =$G$74*(1+$H83) -> 15512.38 | U83: =$H$74*(1+$I83) -> 17232.266 | V83: =$I$74*(1+$J83) -> 18270.871 | W83: =$J$74*(1+$K83) -> 19498.766 | X83: =$K$74*(1+$L83) -> 20446.519 | Y83: =$L$74*(1+$M83) -> 21253.289 | Z83: =($Y83*(1+$AH$79))/($AH$73-$AH$79) -> 377168.5 | AA83: =SUM(Y83:Z83) -> 398421.79 | AB83: =NPV($AH$73,O83:X83,AA83) -> 244307.27 | AC83: =((AB83+$AH$82-$AH$83)-$AH$85)/($AH$87-($AH$87*$AH$85/(AB83+$AH$82-$AH$83))) -> 222.25714 | AD83: 216.45473 | AG83: PV of bankruptcy costs | AH83: ='Leverage finale'!C51 -> 43855.372
B84: 6 | C84: =C$75+_xlfn.NORM.INV(RAND(),0, $AH$80) -> 0.30287539 | D84: =D$75+_xlfn.NORM.INV(RAND(),0, $AH$80) -> -0.12149084 | E84: =E$75+_xlfn.NORM.INV(RAND(),0, $AH$80) -> 0.072525746 | F84: =F$75+_xlfn.NORM.INV(RAND(),0, $AH$80) -> 0.10626564 | G84: =G$75+_xlfn.NORM.INV(RAND(),0, $AH$80) -> 0.10806739 | H84: =H$75+_xlfn.NORM.INV(RAND(),0, $AH$80) -> 0.11476964 | I84: =I$75+_xlfn.NORM.INV(RAND(),0, $AH$80) -> 0.096764242 | J84: =J$75+_xlfn.NORM.INV(RAND(),0, $AH$80) -> 0.07888215 | ... M84: =M$75+_xlfn.NORM.INV(RAND(),0, $AH$80) -> -0.0012970732 | O84: =$B$74*(1+$C84) -> 12764.27 | P84: =$C$74*(1+$D84) -> 11433.797 | Q84: =$D$74*(1+$E84) -> 11782.875 | R84: =$E$74*(1+$F84) -> 13488.396 | S84: =$F$74*(1+$G84) -> 14822.088 | T84: =$G$74*(1+$H84) -> 16379.565 | U84: =$H$74*(1+$I84) -> 17593.346 | V84: =$I$74*(1+$J84) -> 18683.147 | W84: =$J$74*(1+$K84) -> 18549.417 | X84: =$K$74*(1+$L84) -> 20407.817 | Y84: =$L$74*(1+$M84) -> 20360.812 | Z84: =($Y84*(1+$AH$79))/($AH$73-$AH$79) -> 361330.29 | AA84: =SUM(Y84:Z84) -> 381691.1 | AB84: =NPV($AH$73,O84:X84,AA84) -> 238488.91 | AC84: =((AB84+$AH$82-$AH$83)-$AH$85)/($AH$87-($AH$87*$AH$85/(AB84+$AH$82-$AH$83))) -> 216.14542 | AD84: 221.28925
B85: 7 | C85: =C$75+_xlfn.NORM.INV(RAND(),0, $AH$80) -> 0.31710808 | D85: =D$75+_xlfn.NORM.INV(RAND(),0, $AH$80) -> -0.15204312 | E85: =E$75+_xlfn.NORM.INV(RAND(),0, $AH$80) -> 0.16632268 | F85: =F$75+_xlfn.NORM.INV(RAND(),0, $AH$80) -> 0.11551966 | G85: =G$75+_xlfn.NORM.INV(RAND(),0, $AH$80) -> 0.11239702 | H85: =H$75+_xlfn.NORM.INV(RAND(),0, $AH$80) -> 0.097749337 | I85: =I$75+_xlfn.NORM.INV(RAND(),0, $AH$80) -> 0.087451361 | J85: =J$75+_xlfn.NORM.INV(RAND(),0, $AH$80) -> 0.089722049 | ... M85: =M$75+_xlfn.NORM.INV(RAND(),0, $AH$80) -> 0.030750517 | O85: =$B$74*(1+$C85) -> 12903.708 | P85: =$C$74*(1+$D85) -> 11036.159 | Q85: =$D$74*(1+$E85) -> 12813.337 | R85: =$E$74*(1+$F85) -> 13601.228 | S85: =$F$74*(1+$G85) -> 14880.003 | T85: =$G$74*(1+$H85) -> 16129.482 | U85: =$H$74*(1+$I85) -> 17443.957 | V85: =$I$74*(1+$J85) -> 18870.863 | W85: =$J$74*(1+$K85) -> 19295.205 | X85: =$K$74*(1+$L85) -> 19866.713 | Y85: =$L$74*(1+$M85) -> 21014.175 | Z85: =($Y85*(1+$AH$79))/($AH$73-$AH$79) -> 372925.1 | AA85: =SUM(Y85:Z85) -> 393939.27 | AB85: =NPV($AH$73,O85:X85,AA85) -> 243792.88 | AC85: =((AB85+$AH$82-$AH$83)-$AH$85)/($AH$87-($AH$87*$AH$85/(AB85+$AH$82-$AH$83))) -> 221.71681 | AD85: 224.56489 | AG85: Debt issued | AH85: ='Leverage finale'!C55 -> 42983.406
B86: 8 | C86: =C$75+_xlfn.NORM.INV(RAND(),0, $AH$80) -> 0.34470685 | D86: =D$75+_xlfn.NORM.INV(RAND(),0, $AH$80) -> -0.11942801 | E86: =E$75+_xlfn.NORM.INV(RAND(),0, $AH$80) -> 0.095406522 | F86: =F$75+_xlfn.NORM.INV(RAND(),0, $AH$80) -> 0.1123802 | G86: =G$75+_xlfn.NORM.INV(RAND(),0, $AH$80) -> 0.11137098 | H86: =H$75+_xlfn.NORM.INV(RAND(),0, $AH$80) -> 0.089297686 | I86: =I$75+_xlfn.NORM.INV(RAND(),0, $AH$80) -> 0.1066908 | J86: =J$75+_xlfn.NORM.INV(RAND(),0, $AH$80) -> 0.058365738 | ... M86: =M$75+_xlfn.NORM.INV(RAND(),0, $AH$80) -> 0.038169566 | O86: =$B$74*(1+$C86) -> 13174.093 | P86: =$C$74*(1+$D86) -> 11460.644 | Q86: =$D$74*(1+$E86) -> 12034.245 | R86: =$E$74*(1+$F86) -> 13562.949 | S86: =$F$74*(1+$G86) -> 14866.279 | T86: =$G$74*(1+$H86) -> 16005.3 | U86: =$H$74*(1+$I86) -> 17752.579 | V86: =$I$74*(1+$J86) -> 18327.862 | W86: =$J$74*(1+$K86) -> 19553.927 | X86: =$K$74*(1+$L86) -> 20309.225 | Y86: =$L$74*(1+$M86) -> 21165.429 | Z86: =($Y86*(1+$AH$79))/($AH$73-$AH$79) -> 375609.31 | AA86: =SUM(Y86:Z86) -> 396774.73 | AB86: =NPV($AH$73,O86:X86,AA86) -> 244958.43 | AC86: =((AB86+$AH$82-$AH$83)-$AH$85)/($AH$87-($AH$87*$AH$85/(AB86+$AH$82-$AH$83))) -> 222.94112 | AD86: 219.98183
B87: 9 | C87: =C$75+_xlfn.NORM.INV(RAND(),0, $AH$80) -> 0.29350411 | D87: =D$75+_xlfn.NORM.INV(RAND(),0, $AH$80) -> -0.17749303 | E87: =E$75+_xlfn.NORM.INV(RAND(),0, $AH$80) -> 0.13061222 | F87: =F$75+_xlfn.NORM.INV(RAND(),0, $AH$80) -> 0.067948194 | G87: =G$75+_xlfn.NORM.INV(RAND(),0, $AH$80) -> 0.086385505 | H87: =H$75+_xlfn.NORM.INV(RAND(),0, $AH$80) -> 0.090441816 | I87: =I$75+_xlfn.NORM.INV(RAND(),0, $AH$80) -> 0.092057339 | J87: =J$75+_xlfn.NORM.INV(RAND(),0, $AH$80) -> 0.07171367 | ... M87: =M$75+_xlfn.NORM.INV(RAND(),0, $AH$80) -> 0.031183429 | O87: =$B$74*(1+$C87) -> 12672.46 | P87: =$C$74*(1+$D87) -> 10704.928 | Q87: =$D$74*(1+$E87) -> 12421.019 | R87: =$E$74*(1+$F87) -> 13021.202 | S87: =$F$74*(1+$G87) -> 14532.06 | T87: =$G$74*(1+$H87) -> 16022.111 | U87: =$H$74*(1+$I87) -> 17517.842 | V87: =$I$74*(1+$J87) -> 18559.01 | W87: =$J$74*(1+$K87) -> 19732.542 | X87: =$K$74*(1+$L87) -> 19768.035 | Y87: =$L$74*(1+$M87) -> 21023 | Z87: =($Y87*(1+$AH$79))/($AH$73-$AH$79) -> 373081.72 | AA87: =SUM(Y87:Z87) -> 394104.72 | AB87: =NPV($AH$73,O87:X87,AA87) -> 242414.35 | AC87: =((AB87+$AH$82-$AH$83)-$AH$85)/($AH$87-($AH$87*$AH$85/(AB87+$AH$82-$AH$83))) -> 220.26878 | AD87: 228.44224 | AG87: Initial Number of stocks (N) | AH87: 952
B88: 10 | C88: =C$75+_xlfn.NORM.INV(RAND(),0, $AH$80) -> 0.29747235 | D88: =D$75+_xlfn.NORM.INV(RAND(),0, $AH$80) -> -0.1836728 | E88: =E$75+_xlfn.NORM.INV(RAND(),0, $AH$80) -> 0.12975916 | F88: =F$75+_xlfn.NORM.INV(RAND(),0, $AH$80) -> 0.077009694 | G88: =G$75+_xlfn.NORM.INV(RAND(),0, $AH$80) -> 0.07913856 | H88: =H$75+_xlfn.NORM.INV(RAND(),0, $AH$80) -> 0.092801102 | I88: =I$75+_xlfn.NORM.INV(RAND(),0, $AH$80) -> 0.09342032 | J88: =J$75+_xlfn.NORM.INV(RAND(),0, $AH$80) -> 0.073196944 | ... M88: =M$75+_xlfn.NORM.INV(RAND(),0, $AH$80) -> 0.012641326 | O88: =$B$74*(1+$C88) -> 12711.337 | P88: =$C$74*(1+$D88) -> 10624.498 | Q88: =$D$74*(1+$E88) -> 12411.647 | R88: =$E$74*(1+$F88) -> 13131.686 | S88: =$F$74*(1+$G88) -> 14435.121 | T88: =$G$74*(1+$H88) -> 16056.776 | U88: =$H$74*(1+$I88) -> 17539.706 | V88: =$I$74*(1+$J88) -> 18584.696 | W88: =$J$74*(1+$K88) -> 20245.089 | X88: =$K$74*(1+$L88) -> 20780.355 | Y88: =$L$74*(1+$M88) -> 20644.978 | Z88: =($Y88*(1+$AH$79))/($AH$73-$AH$79) -> 366373.2 | AA88: =SUM(Y88:Z88) -> 387018.18 | AB88: =NPV($AH$73,O88:X88,AA88) -> 240408.18 | AC88: =((AB88+$AH$82-$AH$83)-$AH$85)/($AH$87-($AH$87*$AH$85/(AB88+$AH$82-$AH$83))) -> 218.16146 | AD88: 226.02084
B89: 11 | C89: =C$75+_xlfn.NORM.INV(RAND(),0, $AH$80) -> 0.33743665 | D89: =D$75+_xlfn.NORM.INV(RAND(),0, $AH$80) -> -0.11800743 | E89: =E$75+_xlfn.NORM.INV(RAND(),0, $AH$80) -> 0.065227922 | F89: =F$75+_xlfn.NORM.INV(RAND(),0, $AH$80) -> 0.10911191 | G89: =G$75+_xlfn.NORM.INV(RAND(),0, $AH$80) -> 0.11335593 | H89: =H$75+_xlfn.NORM.INV(RAND(),0, $AH$80) -> 0.081915031 | I89: =I$75+_xlfn.NORM.INV(RAND(),0, $AH$80) -> 0.057205745 | J89: =J$75+_xlfn.NORM.INV(RAND(),0, $AH$80) -> 0.075999551 | ... M89: =M$75+_xlfn.NORM.INV(RAND(),0, $AH$80) -> 0.04512598 | O89: =$B$74*(1+$C89) -> 13102.867 | P89: =$C$74*(1+$D89) -> 11479.133 | Q89: =$D$74*(1+$E89) -> 11702.7 | R89: =$E$74*(1+$F89) -> 13523.1 | S89: =$F$74*(1+$G89) -> 14892.83 | T89: =$G$74*(1+$H89) -> 15896.825 | U89: =$H$74*(1+$I89) -> 16958.783 | V89: =$I$74*(1+$J89) -> 18633.229 | W89: =$J$74*(1+$K89) -> 19292.003 | X89: =$K$74*(1+$L89) -> 20186.263 | Y89: =$L$74*(1+$M89) -> 21307.251 | Z89: =($Y89*(1+$AH$79))/($AH$73-$AH$79) -> 378126.13 | AA89: =SUM(Y89:Z89) -> 399433.38 | AB89: =NPV($AH$73,O89:X89,AA89) -> 245138.23 | AC89: =((AB89+$AH$82-$AH$83)-$AH$85)/($AH$87-($AH$87*$AH$85/(AB89+$AH$82-$AH$83))) -> 223.12999 | AD89: 225.62127
B90: 12 | C90: =C$75+_xlfn.NORM.INV(RAND(),0, $AH$80) -> 0.31716657 | D90: =D$75+_xlfn.NORM.INV(RAND(),0, $AH$80) -> -0.14177693 | E90: =E$75+_xlfn.NORM.INV(RAND(),0, $AH$80) -> 0.12292245 | F90: =F$75+_xlfn.NORM.INV(RAND(),0, $AH$80) -> 0.10278388 | G90: =G$75+_xlfn.NORM.INV(RAND(),0, $AH$80) -> 0.11381676 | H90: =H$75+_xlfn.NORM.INV(RAND(),0, $AH$80) -> 0.072882316 | I90: =I$75+_xlfn.NORM.INV(RAND(),0, $AH$80) -> 0.060336704 | J90: =J$75+_xlfn.NORM.INV(RAND(),0, $AH$80) -> 0.030116531 | ... M90: =M$75+_xlfn.NORM.INV(RAND(),0, $AH$80) -> 0.051114328 | O90: =$B$74*(1+$C90) -> 12904.281 | P90: =$C$74*(1+$D90) -> 11169.773 | Q90: =$D$74*(1+$E90) -> 12336.538 | R90: =$E$74*(1+$F90) -> 13445.944 | S90: =$F$74*(1+$G90) -> 14898.995 | T90: =$G$74*(1+$H90) -> 15764.105 | U90: =$H$74*(1+$I90) -> 17009.007 | V90: =$I$74*(1+$J90) -> 17838.666 | W90: =$J$74*(1+$K90) -> 19247.408 | X90: =$K$74*(1+$L90) -> 20914.571 | Y90: =$L$74*(1+$M90) -> 21429.337 | Z90: =($Y90*(1+$AH$79))/($AH$73-$AH$79) -> 380292.71 | AA90: =SUM(Y90:Z90) -> 401722.05 | AB90: =NPV($AH$73,O90:X90,AA90) -> 245835.4 | AC90: =((AB90+$AH$82-$AH$83)-$AH$85)/($AH$87-($AH$87*$AH$85/(AB90+$AH$82-$AH$83))) -> 223.86231 | AD90: 219.82839 | AG90: STOCK PRICE - MONTECARLO RESULTS | AJ90: For Comparison
B91: 13 | C91: =C$75+_xlfn.NORM.INV(RAND(),0, $AH$80) -> 0.32087762 | D91: =D$75+_xlfn.NORM.INV(RAND(),0, $AH$80) -> -0.15017527 | E91: =E$75+_xlfn.NORM.INV(RAND(),0, $AH$80) -> 0.11227076 | F91: =F$75+_xlfn.NORM.INV(RAND(),0, $AH$80) -> 0.12879264 | G91: =G$75+_xlfn.NORM.INV(RAND(),0, $AH$80) -> 0.082998711 | H91: =H$75+_xlfn.NORM.INV(RAND(),0, $AH$80) -> 0.083817179 | I91: =I$75+_xlfn.NORM.INV(RAND(),0, $AH$80) -> 0.097686427 | J91: =J$75+_xlfn.NORM.INV(RAND(),0, $AH$80) -> 0.027991366 | ... M91: =M$75+_xlfn.NORM.INV(RAND(),0, $AH$80) -> 0.032196233 | O91: =$B$74*(1+$C91) -> 12940.638 | P91: =$C$74*(1+$D91) -> 11060.469 | Q91: =$D$74*(1+$E91) -> 12219.517 | R91: =$E$74*(1+$F91) -> 13763.062 | S91: =$F$74*(1+$G91) -> 14486.756 | T91: =$G$74*(1+$H91) -> 15924.773 | U91: =$H$74*(1+$I91) -> 17608.139 | V91: =$I$74*(1+$J91) -> 17801.865 | W91: =$J$74*(1+$K91) -> 19399.401 | X91: =$K$74*(1+$L91) -> 19823.458 | Y91: =$L$74*(1+$M91) -> 21043.649 | Z91: =($Y91*(1+$AH$79))/($AH$73-$AH$79) -> 373448.16 | AA91: =SUM(Y91:Z91) -> 394491.8 | AB91: =NPV($AH$73,O91:X91,AA91) -> 242932.01 | AC91: =((AB91+$AH$82-$AH$83)-$AH$85)/($AH$87-($AH$87*$AH$85/(AB91+$AH$82-$AH$83))) -> 220.81254 | AD91: 218.27472 | AG91: Mean | AH91: =AVERAGE(AD79:AD1078) -> 222.22368 | AJ91: Value per stock (Pre Debt issued) | AK91: =Buyback!B5 -> 260.40966
B92: 14 | C92: =C$75+_xlfn.NORM.INV(RAND(),0, $AH$80) -> 0.35479178 | D92: =D$75+_xlfn.NORM.INV(RAND(),0, $AH$80) -> -0.16502149 | E92: =E$75+_xlfn.NORM.INV(RAND(),0, $AH$80) -> 0.11725801 | F92: =F$75+_xlfn.NORM.INV(RAND(),0, $AH$80) -> 0.13079326 | G92: =G$75+_xlfn.NORM.INV(RAND(),0, $AH$80) -> 0.10490659 | H92: =H$75+_xlfn.NORM.INV(RAND(),0, $AH$80) -> 0.11557122 | I92: =I$75+_xlfn.NORM.INV(RAND(),0, $AH$80) -> 0.0654593 | J92: =J$75+_xlfn.NORM.INV(RAND(),0, $AH$80) -> 0.072404973 | ... M92: =M$75+_xlfn.NORM.INV(RAND(),0, $AH$80) -> 0.059190704 | O92: =$B$74*(1+$C92) -> 13272.895 | P92: =$C$74*(1+$D92) -> 10867.245 | Q92: =$D$74*(1+$E92) -> 12274.308 | R92: =$E$74*(1+$F92) -> 13787.455 | S92: =$F$74*(1+$G92) -> 14779.807 | T92: =$G$74*(1+$H92) -> 16391.343 | U92: =$H$74*(1+$I92) -> 17091.179 | V92: =$I$74*(1+$J92) -> 18570.981 | W92: =$J$74*(1+$K92) -> 19440.206 | X92: =$K$74*(1+$L92) -> 20229.578 | Y92: =$L$74*(1+$M92) -> 21593.992 | Z92: =($Y92*(1+$AH$79))/($AH$73-$AH$79) -> 383214.74 | AA92: =SUM(Y92:Z92) -> 404808.74 | AB92: =NPV($AH$73,O92:X92,AA92) -> 247778.21 | AC92: =((AB92+$AH$82-$AH$83)-$AH$85)/($AH$87-($AH$87*$AH$85/(AB92+$AH$82-$AH$83))) -> 225.90308 | AD92: 222.381 | AG92: Median | AH92: =MEDIAN(AD79:AD1078) -> 222.30714 | AJ92: Value per stock (in case of Buyback) | AK92: =Buyback!E5 -> 226.05202
B93: 15 | C93: =C$75+_xlfn.NORM.INV(RAND(),0, $AH$80) -> 0.32404871 | D93: =D$75+_xlfn.NORM.INV(RAND(),0, $AH$80) -> -0.17612832 | E93: =E$75+_xlfn.NORM.INV(RAND(),0, $AH$80) -> 0.11436624 | F93: =F$75+_xlfn.NORM.INV(RAND(),0, $AH$80) -> 0.096926055 | G93: =G$75+_xlfn.NORM.INV(RAND(),0, $AH$80) -> 0.13076103 | H93: =H$75+_xlfn.NORM.INV(RAND(),0, $AH$80) -> 0.092750823 | I93: =I$75+_xlfn.NORM.INV(RAND(),0, $AH$80) -> 0.08889338 | J93: =J$75+_xlfn.NORM.INV(RAND(),0, $AH$80) -> 0.1016782 | ... M93: =M$75+_xlfn.NORM.INV(RAND(),0, $AH$80) -> 0.045010614 | O93: =$B$74*(1+$C93) -> 12971.705 | P93: =$C$74*(1+$D93) -> 10722.69 | Q93: =$D$74*(1+$E93) -> 12242.539 | R93: =$E$74*(1+$F93) -> 13374.521 | S93: =$F$74*(1+$G93) -> 15125.65 | T93: =$G$74*(1+$H93) -> 16056.037 | U93: =$H$74*(1+$I93) -> 17467.088 | V93: =$I$74*(1+$J93) -> 19077.909 | W93: =$J$74*(1+$K93) -> 19252.234 | X93: =$K$74*(1+$L93) -> 20333.901 | Y93: =$L$74*(1+$M93) -> 21304.899 | Z93: =($Y93*(1+$AH$79))/($AH$73-$AH$79) -> 378084.39 | AA93: =SUM(Y93:Z93) -> 399389.29 | AB93: =NPV($AH$73,O93:X93,AA93) -> 245456.12 | AC93: =((AB93+$AH$82-$AH$83)-$AH$85)/($AH$87-($AH$87*$AH$85/(AB93+$AH$82-$AH$83))) -> 223.46392 | AD93: 222.3081 | AG93: 1st Quartile (Q1) | AH93: =_xlfn.QUARTILE.INC(AD79:AD1078, 1) -> 220.21492
B94: 16 | C94: =C$75+_xlfn.NORM.INV(RAND(),0, $AH$80) -> 0.32108055 | D94: =D$75+_xlfn.NORM.INV(RAND(),0, $AH$80) -> -0.14043658 | E94: =E$75+_xlfn.NORM.INV(RAND(),0, $AH$80) -> 0.08435176 | F94: =F$75+_xlfn.NORM.INV(RAND(),0, $AH$80) -> 0.11325097 | G94: =G$75+_xlfn.NORM.INV(RAND(),0, $AH$80) -> 0.11265625 | H94: =H$75+_xlfn.NORM.INV(RAND(),0, $AH$80) -> 0.065211982 | I94: =I$75+_xlfn.NORM.INV(RAND(),0, $AH$80) -> 0.073149925 | J94: =J$75+_xlfn.NORM.INV(RAND(),0, $AH$80) -> 0.026957411 | ... M94: =M$75+_xlfn.NORM.INV(RAND(),0, $AH$80) -> 0.042132304 | O94: =$B$74*(1+$C94) -> 12942.626 | P94: =$C$74*(1+$D94) -> 11187.218 | Q94: =$D$74*(1+$E94) -> 11912.797 | R94: =$E$74*(1+$F94) -> 13573.566 | S94: =$F$74*(1+$G94) -> 14883.471 | T94: =$G$74*(1+$H94) -> 15651.403 | U94: =$H$74*(1+$I94) -> 17214.545 | V94: =$I$74*(1+$J94) -> 17783.959 | W94: =$J$74*(1+$K94) -> 19872.408 | X94: =$K$74*(1+$L94) -> 20664.6 | Y94: =$L$74*(1+$M94) -> 21246.218 | Z94: =($Y94*(1+$AH$79))/($AH$73-$AH$79) -> 377043.02 | AA94: =SUM(Y94:Z94) -> 398289.24 | AB94: =NPV($AH$73,O94:X94,AA94) -> 244539.53 | AC94: =((AB94+$AH$82-$AH$83)-$AH$85)/($AH$87-($AH$87*$AH$85/(AB94+$AH$82-$AH$83))) -> 222.50111 | AD94: 226.71762 | AG94: 3rd Quartile (Q3) | AH94: =_xlfn.QUARTILE.INC(AD79:AD1079, 3) -> 224.25287
B95: 17 | C95: =C$75+_xlfn.NORM.INV(RAND(),0, $AH$80) -> 0.32021586 | D95: =D$75+_xlfn.NORM.INV(RAND(),0, $AH$80) -> -0.18610332 | E95: =E$75+_xlfn.NORM.INV(RAND(),0, $AH$80) -> 0.11852167 | F95: =F$75+_xlfn.NORM.INV(RAND(),0, $AH$80) -> 0.11441828 | G95: =G$75+_xlfn.NORM.INV(RAND(),0, $AH$80) -> 0.14364836 | H95: =H$75+_xlfn.NORM.INV(RAND(),0, $AH$80) -> 0.050230854 | I95: =I$75+_xlfn.NORM.INV(RAND(),0, $AH$80) -> 0.047901409 | J95: =J$75+_xlfn.NORM.INV(RAND(),0, $AH$80) -> 0.045087572 | ... M95: =M$75+_xlfn.NORM.INV(RAND(),0, $AH$80) -> 0.072694125 | O95: =$B$74*(1+$C95) -> 12934.155 | P95: =$C$74*(1+$D95) -> 10592.865 | Q95: =$D$74*(1+$E95) -> 12288.191 | R95: =$E$74*(1+$F95) -> 13587.799 | S95: =$F$74*(1+$G95) -> 15298.038 | T95: =$G$74*(1+$H95) -> 15431.282 | U95: =$H$74*(1+$I95) -> 16809.531 | V95: =$I$74*(1+$J95) -> 18097.922 | W95: =$J$74*(1+$K95) -> 19762.15 | X95: =$K$74*(1+$L95) -> 21068.25 | Y95: =$L$74*(1+$M95) -> 21869.29 | Z95: =($Y95*(1+$AH$79))/($AH$73-$AH$79) -> 388100.28 | AA95: =SUM(Y95:Z95) -> 409969.57 | AB95: =NPV($AH$73,O95:X95,AA95) -> 248932.67 | AC95: =((AB95+$AH$82-$AH$83)-$AH$85)/($AH$87-($AH$87*$AH$85/(AB95+$AH$82-$AH$83))) -> 227.11575 | AD95: 220.19627 | AG95: Standard Deviation | AH95: =_xlfn.STDEV.S(AD79:AD1078, 1) -> 7.6683166
B96: 18 | C96: =C$75+_xlfn.NORM.INV(RAND(),0, $AH$80) -> 0.33391953 | D96: =D$75+_xlfn.NORM.INV(RAND(),0, $AH$80) -> -0.18207971 | E96: =E$75+_xlfn.NORM.INV(RAND(),0, $AH$80) -> 0.089146362 | F96: =F$75+_xlfn.NORM.INV(RAND(),0, $AH$80) -> 0.12554083 | G96: =G$75+_xlfn.NORM.INV(RAND(),0, $AH$80) -> 0.11443699 | H96: =H$75+_xlfn.NORM.INV(RAND(),0, $AH$80) -> 0.059601149 | I96: =I$75+_xlfn.NORM.INV(RAND(),0, $AH$80) -> 0.079062524 | J96: =J$75+_xlfn.NORM.INV(RAND(),0, $AH$80) -> 0.058605657 | ... M96: =M$75+_xlfn.NORM.INV(RAND(),0, $AH$80) -> 0.05479541 | O96: =$B$74*(1+$C96) -> 13068.41 | P96: =$C$74*(1+$D96) -> 10645.233 | Q96: =$D$74*(1+$E96) -> 11965.471 | R96: =$E$74*(1+$F96) -> 13723.413 | S96: =$F$74*(1+$G96) -> 14907.291 | T96: =$G$74*(1+$H96) -> 15568.962 | U96: =$H$74*(1+$I96) -> 17309.39 | V96: =$I$74*(1+$J96) -> 18332.016 | W96: =$J$74*(1+$K96) -> 18945.4 | X96: =$K$74*(1+$L96) -> 20330.419 | Y96: =$L$74*(1+$M96) -> 21504.384 | Z96: =($Y96*(1+$AH$79))/($AH$73-$AH$79) -> 381624.53 | AA96: =SUM(Y96:Z96) -> 403128.91 | AB96: =NPV($AH$73,O96:X96,AA96) -> 245905.72 | AC96: =((AB96+$AH$82-$AH$83)-$AH$85)/($AH$87-($AH$87*$AH$85/(AB96+$AH$82-$AH$83))) -> 223.93618 | AD96: 216.76425 | AG96: 5th Percentile | AH96: =_xlfn.PERCENTILE.INC(AD79:AD1078, 0.05) -> 216.89495
B97: 19 | C97: =C$75+_xlfn.NORM.INV(RAND(),0, $AH$80) -> 0.3551832 | D97: =D$75+_xlfn.NORM.INV(RAND(),0, $AH$80) -> -0.1624702 | E97: =E$75+_xlfn.NORM.INV(RAND(),0, $AH$80) -> 0.12087887 | F97: =F$75+_xlfn.NORM.INV(RAND(),0, $AH$80) -> 0.052643476 | G97: =G$75+_xlfn.NORM.INV(RAND(),0, $AH$80) -> 0.10752538 | H97: =H$75+_xlfn.NORM.INV(RAND(),0, $AH$80) -> 0.090802639 | I97: =I$75+_xlfn.NORM.INV(RAND(),0, $AH$80) -> 0.081906229 | J97: =J$75+_xlfn.NORM.INV(RAND(),0, $AH$80) -> 0.074203635 | ... M97: =M$75+_xlfn.NORM.INV(RAND(),0, $AH$80) -> 0.045657791 | O97: =$B$74*(1+$C97) -> 13276.73 | P97: =$C$74*(1+$D97) -> 10900.45 | Q97: =$D$74*(1+$E97) -> 12314.087 | R97: =$E$74*(1+$F97) -> 12834.596 | S97: =$F$74*(1+$G97) -> 14814.838 | T97: =$G$74*(1+$H97) -> 16027.412 | U97: =$H$74*(1+$I97) -> 17355.006 | V97: =$I$74*(1+$J97) -> 18602.129 | W97: =$J$74*(1+$K97) -> 19387.703 | X97: =$K$74*(1+$L97) -> 20566.086 | Y97: =$L$74*(1+$M97) -> 21318.093 | Z97: =($Y97*(1+$AH$79))/($AH$73-$AH$79) -> 378318.54 | AA97: =SUM(Y97:Z97) -> 399636.63 | AB97: =NPV($AH$73,O97:X97,AA97) -> 245299.33 | AC97: =((AB97+$AH$82-$AH$83)-$AH$85)/($AH$87-($AH$87*$AH$85/(AB97+$AH$82-$AH$83))) -> 223.29922 | AD97: 225.02428 | AG97: 95th Percentile | AH97: =_xlfn.PERCENTILE.INC(AD79:AD1078, 0.95) -> 227.3578
B98: 20 | C98: =C$75+_xlfn.NORM.INV(RAND(),0, $AH$80) -> 0.33526697 | D98: =D$75+_xlfn.NORM.INV(RAND(),0, $AH$80) -> -0.17488118 | E98: =E$75+_xlfn.NORM.INV(RAND(),0, $AH$80) -> 0.11776652 | F98: =F$75+_xlfn.NORM.INV(RAND(),0, $AH$80) -> 0.094723143 | G98: =G$75+_xlfn.NORM.INV(RAND(),0, $AH$80) -> 0.087395773 | H98: =H$75+_xlfn.NORM.INV(RAND(),0, $AH$80) -> 0.083215185 | I98: =I$75+_xlfn.NORM.INV(RAND(),0, $AH$80) -> 0.080063529 | J98: =J$75+_xlfn.NORM.INV(RAND(),0, $AH$80) -> 0.075879543 | ... M98: =M$75+_xlfn.NORM.INV(RAND(),0, $AH$80) -> 0.037795335 | O98: =$B$74*(1+$C98) -> 13081.611 | P98: =$C$74*(1+$D98) -> 10738.921 | Q98: =$D$74*(1+$E98) -> 12279.894 | R98: =$E$74*(1+$F98) -> 13347.662 | S98: =$F$74*(1+$G98) -> 14545.574 | T98: =$G$74*(1+$H98) -> 15915.928 | U98: =$H$74*(1+$I98) -> 17325.447 | V98: =$I$74*(1+$J98) -> 18631.151 | W98: =$J$74*(1+$K98) -> 18933.035 | X98: =$K$74*(1+$L98) -> 20842.718 | Y98: =$L$74*(1+$M98) -> 21157.799 | Z98: =($Y98*(1+$AH$79))/($AH$73-$AH$79) -> 375473.91 | AA98: =SUM(Y98:Z98) -> 396631.71 | AB98: =NPV($AH$73,O98:X98,AA98) -> 243853.67 | AC98: =((AB98+$AH$82-$AH$83)-$AH$85)/($AH$87-($AH$87*$AH$85/(AB98+$AH$82-$AH$83))) -> 221.78066 | AD98: 224.438
B99: 21 | C99: =C$75+_xlfn.NORM.INV(RAND(),0, $AH$80) -> 0.33786721 | D99: =D$75+_xlfn.NORM.INV(RAND(),0, $AH$80) -> -0.13346491 | E99: =E$75+_xlfn.NORM.INV(RAND(),0, $AH$80) -> 0.12454462 | F99: =F$75+_xlfn.NORM.INV(RAND(),0, $AH$80) -> 0.092008455 | G99: =G$75+_xlfn.NORM.INV(RAND(),0, $AH$80) -> 0.099378813 | H99: =H$75+_xlfn.NORM.INV(RAND(),0, $AH$80) -> 0.075199676 | I99: =I$75+_xlfn.NORM.INV(RAND(),0, $AH$80) -> 0.088370601 | J99: =J$75+_xlfn.NORM.INV(RAND(),0, $AH$80) -> 0.061917976 | ... M99: =M$75+_xlfn.NORM.INV(RAND(),0, $AH$80) -> 0.045012261 | O99: =$B$74*(1+$C99) -> 13107.085 | P99: =$C$74*(1+$D99) -> 11277.954 | Q99: =$D$74*(1+$E99) -> 12354.359 | R99: =$E$74*(1+$F99) -> 13314.562 | S99: =$F$74*(1+$G99) -> 14705.865 | T99: =$G$74*(1+$H99) -> 15798.154 | U99: =$H$74*(1+$I99) -> 17458.702 | V99: =$I$74*(1+$J99) -> 18389.376 | W99: =$J$74*(1+$K99) -> 19338.944 | X99: =$K$74*(1+$L99) -> 20211.651 | Y99: =$L$74*(1+$M99) -> 21304.932 | Z99: =($Y99*(1+$AH$79))/($AH$73-$AH$79) -> 378084.99 | AA99: =SUM(Y99:Z99) -> 399389.92 | AB99: =NPV($AH$73,O99:X99,AA99) -> 245312.89 | AC99: =((AB99+$AH$82-$AH$83)-$AH$85)/($AH$87-($AH$87*$AH$85/(AB99+$AH$82-$AH$83))) -> 223.31346 | AD99: 223.0973
B100: 22 | C100: =C$75+_xlfn.NORM.INV(RAND(),0, $AH$80) -> 0.30579888 | D100: =D$75+_xlfn.NORM.INV(RAND(),0, $AH$80) -> -0.13886854 | E100: =E$75+_xlfn.NORM.INV(RAND(),0, $AH$80) -> 0.10344583 | F100: =F$75+_xlfn.NORM.INV(RAND(),0, $AH$80) -> 0.06830331 | G100: =G$75+_xlfn.NORM.INV(RAND(),0, $AH$80) -> 0.093187027 | H100: =H$75+_xlfn.NORM.INV(RAND(),0, $AH$80) -> 0.08061697 | I100: =I$75+_xlfn.NORM.INV(RAND(),0, $AH$80) -> 0.076790236 | J100: =J$75+_xlfn.NORM.INV(RAND(),0, $AH$80) -> 0.083555487 | ... M100: =M$75+_xlfn.NORM.INV(RAND(),0, $AH$80) -> 0.025896255 | O100: =$B$74*(1+$C100) -> 12792.912 | P100: =$C$74*(1+$D100) -> 11207.626 | Q100: =$D$74*(1+$E100) -> 12122.566 | R100: =$E$74*(1+$F100) -> 13025.532 | S100: =$F$74*(1+$G100) -> 14623.04 | T100: =$G$74*(1+$H100) -> 15877.752 | U100: =$H$74*(1+$I100) -> 17272.94 | V100: =$I$74*(1+$J100) -> 18764.076 | W100: =$J$74*(1+$K100) -> 18833.526 | X100: =$K$74*(1+$L100) -> 20096.626 | Y100: =$L$74*(1+$M100) -> 20915.209 | Z100: =($Y100*(1+$AH$79))/($AH$73-$AH$79) -> 371168.83 | AA100: =SUM(Y100:Z100) -> 392084.04 | AB100: =NPV($AH$73,O100:X100,AA100) -> 241630.01 | AC100: =((AB100+$AH$82-$AH$83)-$AH$85)/($AH$87-($AH$87*$AH$85/(AB100+$AH$82-$AH$83))) -> 219.44489 | AD100: 223.55508
B101: 23 | C101: =C$75+_xlfn.NORM.INV(RAND(),0, $AH$80) -> 0.30670765 | D101: =D$75+_xlfn.NORM.INV(RAND(),0, $AH$80) -> -0.14595869 | E101: =E$75+_xlfn.NORM.INV(RAND(),0, $AH$80) -> 0.12237776 | F101: =F$75+_xlfn.NORM.INV(RAND(),0, $AH$80) -> 0.059667413 | G101: =G$75+_xlfn.NORM.INV(RAND(),0, $AH$80) -> 0.067517215 | H101: =H$75+_xlfn.NORM.INV(RAND(),0, $AH$80) -> 0.093952588 | I101: =I$75+_xlfn.NORM.INV(RAND(),0, $AH$80) -> 0.11419617 | J101: =J$75+_xlfn.NORM.INV(RAND(),0, $AH$80) -> 0.080782036 | ... M101: =M$75+_xlfn.NORM.INV(RAND(),0, $AH$80) -> 0.0076699231 | O101: =$B$74*(1+$C101) -> 12801.815 | P101: =$C$74*(1+$D101) -> 11115.348 | Q101: =$D$74*(1+$E101) -> 12330.554 | R101: =$E$74*(1+$F101) -> 12920.237 | S101: =$F$74*(1+$G101) -> 14279.668 | T101: =$G$74*(1+$H101) -> 16073.695 | U101: =$H$74*(1+$I101) -> 17872.974 | V101: =$I$74*(1+$J101) -> 18716.048 | W101: =$J$74*(1+$K101) -> 19429.192 | X101: =$K$74*(1+$L101) -> 20752.828 | Y101: =$L$74*(1+$M101) -> 20543.625 | Z101: =($Y101*(1+$AH$79))/($AH$73-$AH$79) -> 364574.55 | AA101: =SUM(Y101:Z101) -> 385118.17 | AB101: =NPV($AH$73,O101:X101,AA101) -> 239749.15 | AC101: =((AB101+$AH$82-$AH$83)-$AH$85)/($AH$87-($AH$87*$AH$85/(AB101+$AH$82-$AH$83))) -> 217.46919 | AD101: 227.44452
B102: 24 | C102: =C$75+_xlfn.NORM.INV(RAND(),0, $AH$80) -> 0.3218535 | D102: =D$75+_xlfn.NORM.INV(RAND(),0, $AH$80) -> -0.14813379 | E102: =E$75+_xlfn.NORM.INV(RAND(),0, $AH$80) -> 0.1259018 | F102: =F$75+_xlfn.NORM.INV(RAND(),0, $AH$80) -> 0.071997255 | G102: =G$75+_xlfn.NORM.INV(RAND(),0, $AH$80) -> 0.086411838 | H102: =H$75+_xlfn.NORM.INV(RAND(),0, $AH$80) -> 0.10034618 | I102: =I$75+_xlfn.NORM.INV(RAND(),0, $AH$80) -> 0.11146173 | J102: =J$75+_xlfn.NORM.INV(RAND(),0, $AH$80) -> 0.031824207 | ... M102: =M$75+_xlfn.NORM.INV(RAND(),0, $AH$80) -> 0.059017658 | O102: =$B$74*(1+$C102) -> 12950.199 | P102: =$C$74*(1+$D102) -> 11087.039 | Q102: =$D$74*(1+$E102) -> 12369.269 | R102: =$E$74*(1+$F102) -> 13070.571 | S102: =$F$74*(1+$G102) -> 14532.412 | T102: =$G$74*(1+$H102) -> 16167.638 | U102: =$H$74*(1+$I102) -> 17829.11 | V102: =$I$74*(1+$J102) -> 17868.238 | W102: =$J$74*(1+$K102) -> 18943.041 | X102: =$K$74*(1+$L102) -> 20925.932 | Y102: =$L$74*(1+$M102) -> 21590.464 | Z102: =($Y102*(1+$AH$79))/($AH$73-$AH$79) -> 383152.14 | AA102: =SUM(Y102:Z102) -> 404742.6 | AB102: =NPV($AH$73,O102:X102,AA102) -> 247035.47 | AC102: =((AB102+$AH$82-$AH$83)-$AH$85)/($AH$87-($AH$87*$AH$85/(AB102+$AH$82-$AH$83))) -> 225.12289 | AD102: 223.36653
B103: 25 | C103: =C$75+_xlfn.NORM.INV(RAND(),0, $AH$80) -> 0.30711742 | D103: =D$75+_xlfn.NORM.INV(RAND(),0, $AH$80) -> -0.16146963 | E103: =E$75+_xlfn.NORM.INV(RAND(),0, $AH$80) -> 0.14184363 | F103: =F$75+_xlfn.NORM.INV(RAND(),0, $AH$80) -> 0.080175795 | G103: =G$75+_xlfn.NORM.INV(RAND(),0, $AH$80) -> 0.097632826 | H103: =H$75+_xlfn.NORM.INV(RAND(),0, $AH$80) -> 0.09209471 | I103: =I$75+_xlfn.NORM.INV(RAND(),0, $AH$80) -> 0.061365382 | J103: =J$75+_xlfn.NORM.INV(RAND(),0, $AH$80) -> 0.091840402 | ... M103: =M$75+_xlfn.NORM.INV(RAND(),0, $AH$80) -> 0.028912316 | O103: =$B$74*(1+$C103) -> 12805.829 | P103: =$C$74*(1+$D103) -> 10913.473 | Q103: =$D$74*(1+$E103) -> 12544.408 | R103: =$E$74*(1+$F103) -> 13170.29 | S103: =$F$74*(1+$G103) -> 14682.51 | T103: =$G$74*(1+$H103) -> 16046.397 | U103: =$H$74*(1+$I103) -> 17025.508 | V103: =$I$74*(1+$J103) -> 18907.547 | W103: =$J$74*(1+$K103) -> 19088.809 | X103: =$K$74*(1+$L103) -> 20553.227 | Y103: =$L$74*(1+$M103) -> 20976.699 | Z103: =($Y103*(1+$AH$79))/($AH$73-$AH$79) -> 372260.04 | AA103: =SUM(Y103:Z103) -> 393236.73 | AB103: =NPV($AH$73,O103:X103,AA103) -> 242634.02 | AC103: =((AB103+$AH$82-$AH$83)-$AH$85)/($AH$87-($AH$87*$AH$85/(AB103+$AH$82-$AH$83))) -> 220.49952 | AD103: 219.54689
B104: 26 | C104: =C$75+_xlfn.NORM.INV(RAND(),0, $AH$80) -> 0.31677807 | D104: =D$75+_xlfn.NORM.INV(RAND(),0, $AH$80) -> -0.14449559 | E104: =E$75+_xlfn.NORM.INV(RAND(),0, $AH$80) -> 0.12446818 | F104: =F$75+_xlfn.NORM.INV(RAND(),0, $AH$80) -> 0.11461366 | G104: =G$75+_xlfn.NORM.INV(RAND(),0, $AH$80) -> 0.12030149 | H104: =H$75+_xlfn.NORM.INV(RAND(),0, $AH$80) -> 0.095238619 | I104: =I$75+_xlfn.NORM.INV(RAND(),0, $AH$80) -> 0.10071899 | J104: =J$75+_xlfn.NORM.INV(RAND(),0, $AH$80) -> 0.06539028 | ... M104: =M$75+_xlfn.NORM.INV(RAND(),0, $AH$80) -> 0.066960808 | O104: =$B$74*(1+$C104) -> 12900.475 | P104: =$C$74*(1+$D104) -> 11134.39 | Q104: =$D$74*(1+$E104) -> 12353.52 | R104: =$E$74*(1+$F104) -> 13590.181 | S104: =$F$74*(1+$G104) -> 14985.738 | T104: =$G$74*(1+$H104) -> 16092.591 | U104: =$H$74*(1+$I104) -> 17656.785 | V104: =$I$74*(1+$J104) -> 18449.507 | W104: =$J$74*(1+$K104) -> 19119.743 | X104: =$K$74*(1+$L104) -> 20591.723 | Y104: =$L$74*(1+$M104) -> 21752.403 | Z104: =($Y104*(1+$AH$79))/($AH$73-$AH$79) -> 386025.96 | AA104: =SUM(Y104:Z104) -> 407778.37 | AB104: =NPV($AH$73,O104:X104,AA104) -> 248910.89 | AC104: =((AB104+$AH$82-$AH$83)-$AH$85)/($AH$87-($AH$87*$AH$85/(AB104+$AH$82-$AH$83))) -> 227.09288 | AD104: 219.30803
B105: 27 | C105: =C$75+_xlfn.NORM.INV(RAND(),0, $AH$80) -> 0.34012242 | D105: =D$75+_xlfn.NORM.INV(RAND(),0, $AH$80) -> -0.17704104 | E105: =E$75+_xlfn.NORM.INV(RAND(),0, $AH$80) -> 0.095170157 | F105: =F$75+_xlfn.NORM.INV(RAND(),0, $AH$80) -> 0.097478257 | G105: =G$75+_xlfn.NORM.INV(RAND(),0, $AH$80) -> 0.081485383 | H105: =H$75+_xlfn.NORM.INV(RAND(),0, $AH$80) -> 0.13510268 | I105: =I$75+_xlfn.NORM.INV(RAND(),0, $AH$80) -> 0.093601521 | J105: =J$75+_xlfn.NORM.INV(RAND(),0, $AH$80) -> 0.060527762 | ... M105: =M$75+_xlfn.NORM.INV(RAND(),0, $AH$80) -> 0.029759479 | O105: =$B$74*(1+$C105) -> 13129.179 | P105: =$C$74*(1+$D105) -> 10710.811 | Q105: =$D$74*(1+$E105) -> 12031.649 | R105: =$E$74*(1+$F105) -> 13381.254 | S105: =$F$74*(1+$G105) -> 14466.513 | T105: =$G$74*(1+$H105) -> 16678.323 | U105: =$H$74*(1+$I105) -> 17542.612 | V105: =$I$74*(1+$J105) -> 18365.302 | W105: =$J$74*(1+$K105) -> 19380.879 | X105: =$K$74*(1+$L105) -> 20131.263 | Y105: =$L$74*(1+$M105) -> 20993.97 | Z105: =($Y105*(1+$AH$79))/($AH$73-$AH$79) -> 372566.54 | AA105: =SUM(Y105:Z105) -> 393560.51 | AB105: =NPV($AH$73,O105:X105,AA105) -> 242838.88 | AC105: =((AB105+$AH$82-$AH$83)-$AH$85)/($AH$87-($AH$87*$AH$85/(AB105+$AH$82-$AH$83))) -> 220.71471 | AD105: 225.3112
B106: 28 | C106: =C$75+_xlfn.NORM.INV(RAND(),0, $AH$80) -> 0.33702273 | D106: =D$75+_xlfn.NORM.INV(RAND(),0, $AH$80) -> -0.17422383 | E106: =E$75+_xlfn.NORM.INV(RAND(),0, $AH$80) -> 0.11476619 | F106: =F$75+_xlfn.NORM.INV(RAND(),0, $AH$80) -> 0.1158771 | G106: =G$75+_xlfn.NORM.INV(RAND(),0, $AH$80) -> 0.092161778 | H106: =H$75+_xlfn.NORM.INV(RAND(),0, $AH$80) -> 0.068823763 | I106: =I$75+_xlfn.NORM.INV(RAND(),0, $AH$80) -> 0.083471482 | J106: =J$75+_xlfn.NORM.INV(RAND(),0, $AH$80) -> 0.074405682 | ... M106: =M$75+_xlfn.NORM.INV(RAND(),0, $AH$80) -> 0.052551623 | O106: =$B$74*(1+$C106) -> 13098.812 | P106: =$C$74*(1+$D106) -> 10747.477 | Q106: =$D$74*(1+$E106) -> 12246.932 | R106: =$E$74*(1+$F106) -> 13605.586 | S106: =$F$74*(1+$G106) -> 14609.326 | T106: =$G$74*(1+$H106) -> 15704.472 | U106: =$H$74*(1+$I106) -> 17380.115 | V106: =$I$74*(1+$J106) -> 18605.627 | W106: =$J$74*(1+$K106) -> 19282.179 | X106: =$K$74*(1+$L106) -> 20370.474 | Y106: =$L$74*(1+$M106) -> 21458.639 | Z106: =($Y106*(1+$AH$79))/($AH$73-$AH$79) -> 380812.73 | AA106: =SUM(Y106:Z106) -> 402271.37 | AB106: =NPV($AH$73,O106:X106,AA106) -> 246057.92 | AC106: =((AB106+$AH$82-$AH$83)-$AH$85)/($AH$87-($AH$87*$AH$85/(AB106+$AH$82-$AH$83))) -> 224.09605 | AD106: 223.81437
B107: 29 | C107: =C$75+_xlfn.NORM.INV(RAND(),0, $AH$80) -> 0.31622516 | D107: =D$75+_xlfn.NORM.INV(RAND(),0, $AH$80) -> -0.14288691 | E107: =E$75+_xlfn.NORM.INV(RAND(),0, $AH$80) -> 0.1308594 | F107: =F$75+_xlfn.NORM.INV(RAND(),0, $AH$80) -> 0.10990228 | G107: =G$75+_xlfn.NORM.INV(RAND(),0, $AH$80) -> 0.10686313 | H107: =H$75+_xlfn.NORM.INV(RAND(),0, $AH$80) -> 0.072199004 | I107: =I$75+_xlfn.NORM.INV(RAND(),0, $AH$80) -> 0.086300474 | J107: =J$75+_xlfn.NORM.INV(RAND(),0, $AH$80) -> 0.078891167 | ... M107: =M$75+_xlfn.NORM.INV(RAND(),0, $AH$80) -> 0.0075253835 | O107: =$B$74*(1+$C107) -> 12895.058 | P107: =$C$74*(1+$D107) -> 11155.327 | Q107: =$D$74*(1+$E107) -> 12423.734 | R107: =$E$74*(1+$F107) -> 13532.737 | S107: =$F$74*(1+$G107) -> 14805.979 | T107: =$G$74*(1+$H107) -> 15754.065 | U107: =$H$74*(1+$I107) -> 17425.495 | V107: =$I$74*(1+$J107) -> 18683.303 | W107: =$J$74*(1+$K107) -> 19289.388 | X107: =$K$74*(1+$L107) -> 20725.084 | Y107: =$L$74*(1+$M107) -> 20540.678 | Z107: =($Y107*(1+$AH$79))/($AH$73-$AH$79) -> 364522.25 | AA107: =SUM(Y107:Z107) -> 385062.93 | AB107: =NPV($AH$73,O107:X107,AA107) -> 240167.18 | AC107: =((AB107+$AH$82-$AH$83)-$AH$85)/($AH$87-($AH$87*$AH$85/(AB107+$AH$82-$AH$83))) -> 217.90831 | AD107: 224.32429
B108: 30 | C108: =C$75+_xlfn.NORM.INV(RAND(),0, $AH$80) -> 0.33102164 | D108: =D$75+_xlfn.NORM.INV(RAND(),0, $AH$80) -> -0.1567446 | E108: =E$75+_xlfn.NORM.INV(RAND(),0, $AH$80) -> 0.14089349 | F108: =F$75+_xlfn.NORM.INV(RAND(),0, $AH$80) -> 0.11370535 | G108: =G$75+_xlfn.NORM.INV(RAND(),0, $AH$80) -> 0.12377907 | H108: =H$75+_xlfn.NORM.INV(RAND(),0, $AH$80) -> 0.079656235 | I108: =I$75+_xlfn.NORM.INV(RAND(),0, $AH$80) -> 0.068155827 | J108: =J$75+_xlfn.NORM.INV(RAND(),0, $AH$80) -> 0.026407185 | ... M108: =M$75+_xlfn.NORM.INV(RAND(),0, $AH$80) -> 0.026738732 | O108: =$B$74*(1+$C108) -> 13040.019 | P108: =$C$74*(1+$D108) -> 10974.969 | Q108: =$D$74*(1+$E108) -> 12533.97 | R108: =$E$74*(1+$F108) -> 13579.107 | S108: =$F$74*(1+$G108) -> 15032.256 | T108: =$G$74*(1+$H108) -> 15863.636 | U108: =$H$74*(1+$I108) -> 17134.434 | V108: =$I$74*(1+$J108) -> 17774.431 | W108: =$J$74*(1+$K108) -> 19259.247 | X108: =$K$74*(1+$L108) -> 20271.35 | Y108: =$L$74*(1+$M108) -> 20932.385 | Z108: =($Y108*(1+$AH$79))/($AH$73-$AH$79) -> 371473.63 | AA108: =SUM(Y108:Z108) -> 392406.02 | AB108: =NPV($AH$73,O108:X108,AA108) -> 242443.4 | AC108: =((AB108+$AH$82-$AH$83)-$AH$85)/($AH$87-($AH$87*$AH$85/(AB108+$AH$82-$AH$83))) -> 220.29929 | AD108: 225.81016
B109: 31 | C109: =C$75+_xlfn.NORM.INV(RAND(),0, $AH$80) -> 0.32641341 | D109: =D$75+_xlfn.NORM.INV(RAND(),0, $AH$80) -> -0.14716908 | E109: =E$75+_xlfn.NORM.INV(RAND(),0, $AH$80) -> 0.13531128 | F109: =F$75+_xlfn.NORM.INV(RAND(),0, $AH$80) -> 0.073885026 | G109: =G$75+_xlfn.NORM.INV(RAND(),0, $AH$80) -> 0.072433143 | H109: =H$75+_xlfn.NORM.INV(RAND(),0, $AH$80) -> 0.08694486 | I109: =I$75+_xlfn.NORM.INV(RAND(),0, $AH$80) -> 0.062863729 | J109: =J$75+_xlfn.NORM.INV(RAND(),0, $AH$80) -> 0.056472738 | ... M109: =M$75+_xlfn.NORM.INV(RAND(),0, $AH$80) -> 0.010100531 | O109: =$B$74*(1+$C109) -> 12994.872 | P109: =$C$74*(1+$D109) -> 11099.594 | Q109: =$D$74*(1+$E109) -> 12472.643 | R109: =$E$74*(1+$F109) -> 13093.588 | S109: =$F$74*(1+$G109) -> 14345.426 | T109: =$G$74*(1+$H109) -> 15970.729 | U109: =$H$74*(1+$I109) -> 17049.543 | V109: =$I$74*(1+$J109) -> 18295.08 | W109: =$J$74*(1+$K109) -> 18791.024 | X109: =$K$74*(1+$L109) -> 20155.146 | Y109: =$L$74*(1+$M109) -> 20593.178 | Z109: =($Y109*(1+$AH$79))/($AH$73-$AH$79) -> 365453.94 | AA109: =SUM(Y109:Z109) -> 386047.12 | AB109: =NPV($AH$73,O109:X109,AA109) -> 239291.1 | AC109: =((AB109+$AH$82-$AH$83)-$AH$85)/($AH$87-($AH$87*$AH$85/(AB109+$AH$82-$AH$83))) -> 216.98805 | AD109: 225.73022
... B1078: 1000 | C1078: =C$75+_xlfn.NORM.INV(RAND(),0, $AH$80) -> 0.32196904 | D1078: =D$75+_xlfn.NORM.INV(RAND(),0, $AH$80) -> -0.17633641 | E1078: =E$75+_xlfn.NORM.INV(RAND(),0, $AH$80) -> 0.13199626 | F1078: =F$75+_xlfn.NORM.INV(RAND(),0, $AH$80) -> 0.1054072 | G1078: =G$75+_xlfn.NORM.INV(RAND(),0, $AH$80) -> 0.074933701 | H1078: =H$75+_xlfn.NORM.INV(RAND(),0, $AH$80) -> 0.10460026 | I1078: =I$75+_xlfn.NORM.INV(RAND(),0, $AH$80) -> 0.04801136 | J1078: =J$75+_xlfn.NORM.INV(RAND(),0, $AH$80) -> 0.069507249 | ... M1078: =M$75+_xlfn.NORM.INV(RAND(),0, $AH$80) -> 0.00020724892 | O1078: =$B$74*(1+$C1078) -> 12951.331 | P1078: =$C$74*(1+$D1078) -> 10719.982 | Q1078: =$D$74*(1+$E1078) -> 12436.224 | R1078: =$E$74*(1+$F1078) -> 13477.929 | S1078: =$F$74*(1+$G1078) -> 14378.874 | T1078: =$G$74*(1+$H1078) -> 16230.144 | U1078: =$H$74*(1+$I1078) -> 16811.294 | V1078: =$I$74*(1+$J1078) -> 18520.801 | W1078: =$J$74*(1+$K1078) -> 19487.412 | X1078: =$K$74*(1+$L1078) -> 20740.611 | Y1078: =$L$74*(1+$M1078) -> 20391.481 | Z1078: =($Y1078*(1+$AH$79))/($AH$73-$AH$79) -> 361874.56 | AA1078: =SUM(Y1078:Z1078) -> 382266.04 | AB1078: =NPV($AH$73,O1078:X1078,AA1078) -> 238459.67 | AC1078: =((AB1078+$AH$82-$AH$83)-$AH$85)/($AH$87-($AH$87*$AH$85/(AB1078+$AH$82-$AH$83))) -> 216.1147 | AD1078: 218.06518

Sheet BETA Calculation chosen
A1: Price | D1: Price | E1: Adj Close | F1: Return | G1: Return-rf | I1: Price | J1: Adj Close | K1: Return | L1: Return-rf | N1: SUMMARY OUTPUT CORRECT
A2: Ticker | B2: Risk free | D2: Ticker | E2: CRM | I2: Ticker | J2: ^GSPC
A3: Date | D3: Date | E3: SALESFORCE DAILY | I3: Date | J3: SP500 DAILY | N3: Regression Statistics
A4: 44147 | B4: 0.88 | D4: 44147 | E4: 246.82362 | I4: 44147 | J4: 3537.01 | N4: Multiple R | O4: 0.6055308
A5: 44148 | B5: 0.89 | D5: 44148 | E5: 246.91267 | F5: =+(E5-E4)/E4*100 -> 0.036078513 | G5: =+F5-B5 -> -0.85392149 | I5: 44148 | J5: 3585.1499 | K5: =+(J5-J4)/J4*100 -> 1.3610335 | L5: =+K5-B5 -> 0.47103354 | N5: R Square | O5: 0.36666755
A6: 44151 | B6: 0.91 | D6: 44151 | E6: 247.28873 | F6: =+(E6-E5)/E5*100 -> 0.15230197 | G6: =+F6-B6 -> -0.75769803 | I6: 44151 | J6: 3626.9099 | K6: =+(J6-J5)/J5*100 -> 1.1648051 | L6: =+K6-B6 -> 0.25480512 | N6: Adjusted R Square | O6: 0.36542083
A7: 44152 | B7: 0.87 | D7: 44152 | E7: 253.50339 | F7: =+(E7-E6)/E6*100 -> 2.5131193 | G7: =+F7-B7 -> 1.6431193 | I7: 44152 | J7: 3609.53 | K7: =+(J7-J6)/J6*100 -> -0.47919257 | L7: =+K7-B7 -> -1.3491926 | N7: Standard Error | O7: 1.7968457
A8: 44153 | B8: 0.88 | D8: 44153 | E8: 254.48305 | F8: =+(E8-E7)/E7*100 -> 0.3864485 | G8: =+F8-B8 -> -0.4935515 | I8: 44153 | J8: 3567.79 | K8: =+(J8-J7)/J7*100 -> -1.156383 | L8: =+K8-B8 -> -2.036383 | N8: Observations | O8: 510
A9: 44154 | B9: 0.86 | D9: 44154 | E9: 261.89508 | F9: =+(E9-E8)/E8*100 -> 2.9125842 | G9: =+F9-B9 -> 2.0525842 | I9: 44154 | J9: 3581.8701 | K9: =+(J9-J8)/J8*100 -> 0.39464425 | L9: =+K9-B9 -> -0.46535575
A10: 44155 | B10: 0.83 | D10: 44155 | E10: 255.35394 | F10: =+(E10-E9)/E9*100 -> -2.4976176 | G10: =+F10-B10 -> -3.3276176 | I10: 44155 | J10: 3557.54 | K10: =+(J10-J9)/J9*100 -> -0.67925629 | L10: =+K10-B10 -> -1.5092563 | N10: ANOVA
A11: 44158 | B11: 0.86 | D11: 44158 | E11: 254.95807 | F11: =+(E11-E10)/E10*100 -> -0.15502953 | G11: =+F11-B11 -> -1.0150295 | I11: 44158 | J11: 3577.5901 | K11: =+(J11-J10)/J10*100 -> 0.56359306 | L11: =+K11-B11 -> -0.29640694 | O11: df | P11: SS | Q11: MS | R11: F | S11: Significance F
A12: 44159 | B12: 0.88 | D12: 44159 | E12: 258.12473 | F12: =+(E12-E11)/E11*100 -> 1.2420303 | G12: =+F12-B12 -> 0.36203031 | I12: 44159 | J12: 3635.4099 | K12: =+(J12-J11)/J11*100 -> 1.6161668 | L12: =+K12-B12 -> 0.73616683 | N12: Regression | O12: 1 | P12: 949.56786 | Q12: 949.56786 | R12: 294.10638 | S12: 2.3969662e-52
A13: 44160 | B13: 0.88 | D13: 44160 | E13: 244.2507 | F13: =+(E13-E12)/E12*100 -> -5.3749301 | G13: =+F13-B13 -> -6.2549301 | I13: 44160 | J13: 3629.6499 | K13: =+(J13-J12)/J12*100 -> -0.15844182 | L13: =+K13-B13 -> -1.0384418 | N13: Residual | O13: 508 | P13: 1640.1564 | Q13: 3.2286544
A14: 44162 | B14: 0.84 | D14: 44162 | E14: 245.05228 | F14: =+(E14-E13)/E13*100 -> 0.32817703 | G14: =+F14-B14 -> -0.51182297 | I14: 44162 | J14: 3638.3501 | K14: =+(J14-J13)/J13*100 -> 0.23969792 | L14: =+K14-B14 -> -0.60030208 | N14: Total | O14: 509 | P14: 2589.7243
A15: 44165 | B15: 0.84 | D15: 44165 | E15: 243.24132 | F15: =+(E15-E14)/E14*100 -> -0.7390092 | G15: =+F15-B15 -> -1.5790092 | I15: 44165 | J15: 3621.6299 | K15: =+(J15-J14)/J14*100 -> -0.45955486 | L15: =+K15-B15 -> -1.2995549
A16: 44166 | B16: 0.92 | D16: 44166 | E16: 238.83765 | F16: =+(E16-E15)/E15*100 -> -1.8104125 | G16: =+F16-B16 -> -2.7304125 | I16: 44166 | J16: 3662.45 | K16: =+(J16-J15)/J15*100 -> 1.1271187 | L16: =+K16-B16 -> 0.20711872 | O16: Coefficients | P16: Standard Error | Q16: t Stat | R16: P-value | S16: Lower 95% | T16: Upper 95% | U16: Lower 95,0% | V16: Upper 95,0%
A17: 44167 | B17: 0.95 | D17: 44167 | E17: 218.48177 | F17: =+(E17-E16)/E16*100 -> -8.5228945 | G17: =+F17-B17 -> -9.4728945 | I17: 44167 | J17: 3669.01 | K17: =+(J17-J16)/J16*100 -> 0.17911668 | L17: =+K17-B17 -> -0.77088332 | N17: Intercept | O17: 0.87466201 | P17: 0.30373695 | Q17: 2.8796694 | R17: 0.004148923 | S17: 0.2779268 | T17: 1.4713972 | U17: 0.2779268 | V17: 1.4713972
A18: 44168 | B18: 0.92 | D18: 44168 | E18: 218.66978 | F18: =+(E18-E17)/E17*100 -> 0.086056975 | G18: =+F18-B18 -> -0.83394302 | I18: 44168 | J18: 3666.72 | K18: =+(J18-J17)/J17*100 -> -0.062415721 | L18: =+K18-B18 -> -0.98241572 | N18: X Variable 1 | O18: 1.2211485 | P18: 0.071205945 | Q18: 17.14953 | R18: 2.3969662e-52 | S18: 1.0812541 | T18: 1.3610429 | U18: 1.0812541 | V18: 1.3610429
A19: 44169 | B19: 0.97 | D19: 44169 | E19: 223.50888 | F19: =+(E19-E18)/E18*100 -> 2.2129697 | G19: =+F19-B19 -> 1.2429697 | I19: 44169 | J19: 3699.1201 | K19: =+(J19-J18)/J18*100 -> 0.88362751 | L19: =+K19-B19 -> -0.086372487
A20: 44172 | B20: 0.94 | D20: 44172 | E20: 225.32973 | F20: =+(E20-E19)/E19*100 -> 0.81466408 | G20: =+F20-B20 -> -0.12533592 | I20: 44172 | J20: 3691.96 | K20: =+(J20-J19)/J19*100 -> -0.19356377 | L20: =+K20-B20 -> -1.1335638
A21: 44173 | B21: 0.92 | D21: 44173 | E21: 225.48807 | F21: =+(E21-E20)/E20*100 -> 0.070270557 | G21: =+F21-B21 -> -0.84972944 | I21: 44173 | J21: 3702.25 | K21: =+(J21-J20)/J20*100 -> 0.27871481 | L21: =+K21-B21 -> -0.64128519
A22: 44174 | B22: 0.95 | D22: 44174 | E22: 218.27394 | F22: =+(E22-E21)/E21*100 -> -3.1993385 | G22: =+F22-B22 -> -4.1493385 | I22: 44174 | J22: 3672.8201 | K22: =+(J22-J21)/J21*100 -> -0.79492016 | L22: =+K22-B22 -> -1.7449202
A23: 44175 | B23: 0.92 | D23: 44175 | E23: 220.59949 | F23: =+(E23-E22)/E22*100 -> 1.0654255 | G23: =+F23-B23 -> 0.14542552 | I23: 44175 | J23: 3668.1001 | K23: =+(J23-J22)/J22*100 -> -0.12851081 | L23: =+K23-B23 -> -1.0485108
A24: 44176 | B24: 0.9 | D24: 44176 | E24: 220.10468 | F24: =+(E24-E23)/E23*100 -> -0.22430334 | G24: =+F24-B24 -> -1.1243033 | I24: 44176 | J24: 3663.46 | K24: =+(J24-J23)/J23*100 -> -0.12649973 | L24: =+K24-B24 -> -1.0264997 | N24: SUMMARY OUTPUT WITH COVID
A25: 44179 | B25: 0.9 | D25: 44179 | E25: 218.96664 | F25: =+(E25-E24)/E24*100 -> -0.51704081 | G25: =+F25-B25 -> -1.4170408 | I25: 44179 | J25: 3647.49 | K25: =+(J25-J24)/J24*100 -> -0.4359259 | L25: =+K25-B25 -> -1.3359259
A26: 44180 | B26: 0.92 | D26: 44180 | E26: 217.85832 | F26: =+(E26-E25)/E25*100 -> -0.50616026 | G26: =+F26-B26 -> -1.4261603 | I26: 44180 | J26: 3694.6201 | K26: =+(J26-J25)/J25*100 -> 1.2921249 | L26: =+K26-B26 -> 0.37212492 | N26: Regression Statistics
A27: 44181 | B27: 0.92 | D27: 44181 | E27: 221.29219 | F27: =+(E27-E26)/E26*100 -> 1.5761934 | G27: =+F27-B27 -> 0.65619336 | I27: 44181 | J27: 3701.1699 | K27: =+(J27-J26)/J26*100 -> 0.17727952 | L27: =+K27-B27 -> -0.74272048 | N27: Multiple R | O27: 0.72154189
A28: 44182 | B28: 0.94 | D28: 44182 | E28: 223.56825 | F28: =+(E28-E27)/E27*100 -> 1.0285325 | G28: =+F28-B28 -> 0.08853246 | I28: 44182 | J28: 3722.48 | K28: =+(J28-J27)/J27*100 -> 0.57576548 | L28: =+K28-B28 -> -0.36423452 | N28: R Square | O28: 0.5206227
A29: 44183 | B29: 0.95 | D29: 44183 | E29: 225.06252 | F29: =+(E29-E28)/E28*100 -> 0.66836981 | G29: =+F29-B29 -> -0.28163019 | I29: 44183 | J29: 3709.4099 | K29: =+(J29-J28)/J28*100 -> -0.35111185 | L29: =+K29-B29 -> -1.3011119 | N29: Adjusted R Square | O29: 0.52024012
A30: 44186 | B30: 0.95 | D30: 44186 | E30: 224.11253 | F30: =+(E30-E29)/E29*100 -> -0.42209681 | G30: =+F30-B30 -> -1.3720968 | I30: 44186 | J30: 3694.9199 | K30: =+(J30-J29)/J29*100 -> -0.39062791 | L30: =+K30-B30 -> -1.3406279 | N30: Standard Error | O30: 1.7671951
A31: 44187 | B31: 0.93 | D31: 44187 | E31: 228.76361 | F31: =+(E31-E30)/E30*100 -> 2.0753312 | G31: =+F31-B31 -> 1.1453312 | I31: 44187 | J31: 3687.26 | K31: =+(J31-J30)/J30*100 -> -0.20730929 | L31: =+K31-B31 -> -1.1373093 | N31: Observations | O31: 1255
A32: 44188 | B32: 0.96 | D32: 44188 | E32: 225.06252 | F32: =+(E32-E31)/E31*100 -> -1.617869 | G32: =+F32-B32 -> -2.577869 | I32: 44188 | J32: 3690.01 | K32: =+(J32-J31)/J31*100 -> 0.074581125 | L32: =+K32-B32 -> -0.88541887
A33: 44189 | B33: 0.94 | D33: 44189 | E33: 223.42972 | F33: =+(E33-E32)/E32*100 -> -0.72548609 | G33: =+F33-B33 -> -1.6654861 | I33: 44189 | J33: 3703.0601 | K33: =+(J33-J32)/J32*100 -> 0.3536589 | L33: =+K33-B33 -> -0.5863411 | N33: ANOVA
A34: 44193 | B34: 0.94 | D34: 44193 | E34: 222.30157 | F34: =+(E34-E33)/E33*100 -> -0.50492089 | G34: =+F34-B34 -> -1.4449209 | I34: 44193 | J34: 3735.3601 | K34: =+(J34-J33)/J33*100 -> 0.8722529 | L34: =+K34-B34 -> -0.067747098 | O34: df | P34: SS | Q34: MS | R34: F | S34: Significance F
A35: 44194 | B35: 0.94 | D35: 44194 | E35: 220.14429 | F35: =+(E35-E34)/E34*100 -> -0.97043289 | G35: =+F35-B35 -> -1.9104329 | I35: 44194 | J35: 3727.04 | K35: =+(J35-J34)/J34*100 -> -0.22273805 | L35: =+K35-B35 -> -1.1627381 | N35: Regression | O35: 1 | P35: 4249.7728 | Q35: 4249.7728 | R35: 1360.8075 | S35: 2.7461914e-202
A36: 44195 | B36: 0.93 | D36: 44195 | E36: 220.08487 | F36: =+(E36-E35)/E35*100 -> -0.026990355 | G36: =+F36-B36 -> -0.95699036 | I36: 44195 | J36: 3732.04 | K36: =+(J36-J35)/J35*100 -> 0.13415472 | L36: =+K36-B36 -> -0.79584528 | N36: Residual | O36: 1253 | P36: 3913.0922 | Q36: 3.1229786
A37: 44196 | B37: 0.93 | D37: 44196 | E37: 220.21355 | F37: =+(E37-E36)/E36*100 -> 0.058467158 | G37: =+F37-B37 -> -0.87153284 | I37: 44196 | J37: 3756.0701 | K37: =+(J37-J36)/J36*100 -> 0.64388455 | L37: =+K37-B37 -> -0.28611545 | N37: Total | O37: 1254 | P37: 8162.865
A38: 44200 | B38: 0.93 | D38: 44200 | E38: 218.01665 | F38: =+(E38-E37)/E37*100 -> -0.99762228 | G38: =+F38-B38 -> -1.9276223 | I38: 44200 | J38: 3700.6499 | K38: =+(J38-J37)/J37*100 -> -1.4754828 | L38: =+K38-B38 -> -2.4054828
A39: 44201 | B39: 0.96 | D39: 44201 | E39: 219.21407 | F39: =+(E39-E38)/E38*100 -> 0.54923247 | G39: =+F39-B39 -> -0.41076753 | I39: 44201 | J39: 3726.8601 | K39: =+(J39-J38)/J38*100 -> 0.70825952 | L39: =+K39-B39 -> -0.25174048 | O39: Coefficients | P39: Standard Error | Q39: t Stat | R39: P-value | S39: Lower 95% | T39: Upper 95% | U39: Lower 95,0% | V39: Upper 95,0%
A40: 44202 | B40: 1.04 | D40: 44202 | E40: 213.89995 | F40: =+(E40-E39)/E39*100 -> -2.4241681 | G40: =+F40-B40 -> -3.4641681 | I40: 44202 | J40: 3748.1399 | K40: =+(J40-J39)/J39*100 -> 0.57098427 | L40: =+K40-B40 -> -0.46901573 | N40: Intercept | O40: 0.3561518 | P40: 0.10933972 | Q40: 3.2572957 | R40: 0.0011549279 | S40: 0.14164268 | T40: 0.57066092 | U40: 0.14164268 | V40: 0.57066092
A41: 44203 | B41: 1.08 | D41: 44203 | E41: 215.71092 | F41: =+(E41-E40)/E40*100 -> 0.84664542 | G41: =+F41-B41 -> -0.23335458 | I41: 44203 | J41: 3803.79 | K41: =+(J41-J40)/J40*100 -> 1.4847404 | L41: =+K41-B41 -> 0.40474038 | N41: X Variable 1 | O41: 1.1217758 | P41: 0.03040939 | Q41: 36.889125 | R41: 2.7461914e-202 | S41: 1.0621168 | T41: 1.1814347 | U41: 1.0621168 | V41: 1.1814347
A42: 44204 | B42: 1.13 | D42: 44204 | E42: 219.72865 | F42: =+(E42-E41)/E41*100 -> 1.8625532 | G42: =+F42-B42 -> 0.73255321 | I42: 44204 | J42: 3824.6799 | K42: =+(J42-J41)/J41*100 -> 0.54918627 | L42: =+K42-B42 -> -0.58081373
A43: 44207 | B43: 1.15 | D43: 44207 | E43: 215.9781 | F43: =+(E43-E42)/E42*100 -> -1.7069004 | G43: =+F43-B43 -> -2.8569004 | I43: 44207 | J43: 3799.6101 | K43: =+(J43-J42)/J42*100 -> -0.65547509 | L43: =+K43-B43 -> -1.8054751
A44: 44208 | B44: 1.15 | D44: 44208 | E44: 213.2765 | F44: =+(E44-E43)/E43*100 -> -1.2508671 | G44: =+F44-B44 -> -2.4008671 | I44: 44208 | J44: 3801.1899 | K44: =+(J44-J43)/J43*100 -> 0.041578845 | L44: =+K44-B44 -> -1.1084212
A45: 44209 | B45: 1.1 | D45: 44209 | E45: 215.90883 | F45: =+(E45-E44)/E44*100 -> 1.2342308 | G45: =+F45-B45 -> 0.13423076 | I45: 44209 | J45: 3809.8401 | K45: =+(J45-J44)/J44*100 -> 0.22756417 | L45: =+K45-B45 -> -0.87243583
A46: 44210 | B46: 1.15 | D46: 44210 | E46: 213.3557 | F46: =+(E46-E45)/E45*100 -> -1.1825043 | G46: =+F46-B46 -> -2.3325043 | I46: 44210 | J46: 3795.54 | K46: =+(J46-J45)/J45*100 -> -0.37534512 | L46: =+K46-B46 -> -1.5253451
A47: 44211 | B47: 1.11 | D47: 44211 | E47: 210.92131 | F47: =+(E47-E46)/E46*100 -> -1.1409994 | G47: =+F47-B47 -> -2.2509994 | I47: 44211 | J47: 3768.25 | K47: =+(J47-J46)/J46*100 -> -0.7190028 | L47: =+K47-B47 -> -1.8290028
A48: 44215 | B48: 1.1 | D48: 44215 | E48: 214.50359 | F48: =+(E48-E47)/E47*100 -> 1.6983942 | G48: =+F48-B48 -> 0.59839424 | I48: 44215 | J48: 3798.9099 | K48: =+(J48-J47)/J47*100 -> 0.81363795 | L48: =+K48-B48 -> -0.28636205
A49: 44216 | B49: 1.1 | D49: 44216 | E49: 221.11406 | F49: =+(E49-E48)/E48*100 -> 3.0817544 | G49: =+F49-B49 -> 1.9817544 | I49: 44216 | J49: 3851.8501 | K49: =+(J49-J48)/J48*100 -> 1.3935625 | L49: =+K49-B49 -> 0.29356254
A50: 44217 | B50: 1.12 | D50: 44217 | E50: 219.85728 | F50: =+(E50-E49)/E49*100 -> -0.56838308 | G50: =+F50-B50 -> -1.6883831 | I50: 44217 | J50: 3853.0701 | K50: =+(J50-J49)/J49*100 -> 0.031672331 | L50: =+K50-B50 -> -1.0883277
A51: 44218 | B51: 1.1 | D51: 44218 | E51: 223.41982 | F51: =+(E51-E50)/E50*100 -> 1.6203832 | G51: =+F51-B51 -> 0.52038321 | I51: 44218 | J51: 3841.47 | K51: =+(J51-J50)/J50*100 -> -0.30106117 | L51: =+K51-B51 -> -1.4010612
A52: 44221 | B52: 1.05 | D52: 44221 | E52: 223.56825 | F52: =+(E52-E51)/E51*100 -> 0.066438825 | G52: =+F52-B52 -> -0.98356117 | I52: 44221 | J52: 3855.3601 | K52: =+(J52-J51)/J51*100 -> 0.36158389 | L52: =+K52-B52 -> -0.68841611
A53: 44222 | B53: 1.05 | D53: 44222 | E53: 223.90471 | F53: =+(E53-E52)/E52*100 -> 0.15049377 | G53: =+F53-B53 -> -0.89950623 | I53: 44222 | J53: 3849.6201 | K53: =+(J53-J52)/J52*100 -> -0.14888337 | L53: =+K53-B53 -> -1.1988834
... A1257: 45971 | B1257: 4.13 | D1257: 45971 | E1257: 241.71001 | F1257: =+(E1257-E1256)/E1256*100 -> 0.76288219 | G1257: =+F1257-B1257 -> -3.3671178 | I1257: 45971 | J1257: 6832.4302 | K1257: =+(J1257-J1256)/J1256*100 -> 1.5401019 | L1257: =+K1257-B1257 -> -2.5898981
A1258: 45972 | D1258: 45972 | E1258: 244.5 | F1258: =+(E1258-E1257)/E1257*100 -> 1.154273 | G1258: =+F1258-B1258 -> 1.154273 | I1258: 45972 | J1258: 6846.6099 | K1258: =+(J1258-J1257)/J1257*100 -> 0.20753505 | L1258: =+K1258-B1258 -> 0.20753505
A1259: 45973 | D1259: 45973 | E1259: 246.355 | F1259: =+(E1259-E1258)/E1258*100 -> 0.75868946 | G1259: =+F1259-B1259 -> 0.75868946 | I1259: 45973 | J1259: 6855.5 | K1259: =+(J1259-J1258)/J1258*100 -> 0.12984728 | L1259: =+K1259-B1259 -> 0.12984728
K1260: =+(J1260-J1259)/J1259*100 -> -100 | L1260: =+K1260-B1260 -> -100
K1261: =+(J1261-J1260)/J1260*100 -> #DIV/0! | L1261: =+K1261-B1261 -> #DIV/0!
K1262: =+(J1262-J1261)/J1261*100 -> #DIV/0! | L1262: =+K1262-B1262 -> #DIV/0!
K1263: =+(J1263-J1262)/J1262*100 -> #DIV/0! | L1263: =+K1263-B1263 -> #DIV/0!
K1264: =+(J1264-J1263)/J1263*100 -> #DIV/0! | L1264: =+K1264-B1264 -> #DIV/0!
K1265: =+(J1265-J1264)/J1264*100 -> #DIV/0! | L1265: =+K1265-B1265 -> #DIV/0!
K1266: =+(J1266-J1265)/J1265*100 -> #DIV/0! | L1266: =+K1266-B1266 -> #DIV/0!
K1267: =+(J1267-J1266)/J1266*100 -> #DIV/0! | L1267: =+K1267-B1267 -> #DIV/0!
K1268: =+(J1268-J1267)/J1267*100 -> #DIV/0! | L1268: =+K1268-B1268 -> #DIV/0!
K1269: =+(J1269-J1268)/J1268*100 -> #DIV/0! | L1269: =+K1269-B1269 -> #DIV/0!
K1270: =+(J1270-J1269)/J1269*100 -> #DIV/0! | L1270: =+K1270-B1270 -> #DIV/0!
K1271: =+(J1271-J1270)/J1270*100 -> #DIV/0! | L1271: =+K1271-B1271 -> #DIV/0!
... K1305: =+(J1305-J1304)/J1304*100 -> #DIV/0! | L1305: =+K1305-B1305 -> #DIV/0!

Sheet BETA Log
A1: Price | D1: Price | E1: Adj Close | F1: Return | G1: Return-rf | H1: Log | J1: Price | K1: Adj Close | L1: Return | M1: Return-rf | N1: Log | Q1: SUMMARY OUTPUT CORRECT
A2: Ticker | B2: Risk free | D2: Ticker | E2: CRM | J2: Ticker | K2: ^GSPC
A3: Date | D3: Date | E3: SALESFORCE DAILY | J3: Date | K3: SP500 DAILY | Q3: Regression Statistics
A4: 44147 | B4: 0.88 | D4: 44147 | E4: 246.82362 | J4: 44147 | K4: 3537.01 | Q4: Multiple R | R4: 0.59548137
A5: 44148 | B5: 0.89 | D5: 44148 | E5: 246.91267 | F5: =+(E5-E4)/E4*100 -> 0.036078513 | G5: =+F5-B5 -> -0.85392149 | H5: =+LOG(1+G5/100) -> -0.0037244586 | J5: 44148 | K5: 3585.1499 | L5: =+(K5-K4)/K4*100 -> 1.3610335 | M5: =+L5-B5 -> 0.47103354 | N5: =+LOG(1+M5/100) -> 0.0020408698 | Q5: R Square | R5: 0.35459806
A6: 44151 | B6: 0.91 | D6: 44151 | E6: 247.28873 | F6: =+(E6-E5)/E5*100 -> 0.15230197 | G6: =+F6-B6 -> -0.75769803 | H6: =+LOG(1+G6/100) -> -0.0033031706 | J6: 44151 | K6: 3626.9099 | L6: =+(K6-K5)/K5*100 -> 1.1648051 | M6: =+L6-B6 -> 0.25480512 | N6: =+LOG(1+M6/100) -> 0.0011051971 | Q6: Adjusted R Square | R6: 0.35332759
A7: 44152 | B7: 0.87 | D7: 44152 | E7: 253.50339 | F7: =+(E7-E6)/E6*100 -> 2.5131193 | G7: =+F7-B7 -> 1.6431193 | H7: =+LOG(1+G7/100) -> 0.0070779844 | J7: 44152 | K7: 3609.53 | L7: =+(K7-K6)/K6*100 -> -0.47919257 | M7: =+L7-B7 -> -1.3491926 | N7: =+LOG(1+M7/100) -> -0.0058993558 | Q7: Standard Error | R7: 0.0083326631
A8: 44153 | B8: 0.88 | D8: 44153 | E8: 254.48305 | F8: =+(E8-E7)/E7*100 -> 0.3864485 | G8: =+F8-B8 -> -0.4935515 | H8: =+LOG(1+G8/100) -> -0.002148774 | J8: 44153 | K8: 3567.79 | L8: =+(K8-K7)/K7*100 -> -1.156383 | M8: =+L8-B8 -> -2.036383 | N8: =+LOG(1+M8/100) -> -0.0089351881 | Q8: Observations | R8: 510
A9: 44154 | B9: 0.86 | D9: 44154 | E9: 261.89508 | F9: =+(E9-E8)/E8*100 -> 2.9125842 | G9: =+F9-B9 -> 2.0525842 | H9: =+LOG(1+G9/100) -> 0.0088240066 | J9: 44154 | K9: 3581.8701 | L9: =+(K9-K8)/K8*100 -> 0.39464425 | M9: =+L9-B9 -> -0.46535575 | N9: =+LOG(1+M9/100) -> -0.0020257315
A10: 44155 | B10: 0.83 | D10: 44155 | E10: 255.35394 | F10: =+(E10-E9)/E9*100 -> -2.4976176 | G10: =+F10-B10 -> -3.3276176 | H10: =+LOG(1+G10/100) -> -0.014697579 | J10: 44155 | K10: 3557.54 | L10: =+(K10-K9)/K9*100 -> -0.67925629 | M10: =+L10-B10 -> -1.5092563 | N10: =+LOG(1+M10/100) -> -0.0066045832 | Q10: ANOVA
A11: 44158 | B11: 0.86 | D11: 44158 | E11: 254.95807 | F11: =+(E11-E10)/E10*100 -> -0.15502953 | G11: =+F11-B11 -> -1.0150295 | H11: =+LOG(1+G11/100) -> -0.0044307422 | J11: 44158 | K11: 3577.5901 | L11: =+(K11-K10)/K10*100 -> 0.56359306 | M11: =+L11-B11 -> -0.29640694 | N11: =+LOG(1+M11/100) -> -0.0012891905 | R11: df | S11: SS | T11: MS | U11: F | V11: Significance F
A12: 44159 | B12: 0.88 | D12: 44159 | E12: 258.12473 | F12: =+(E12-E11)/E11*100 -> 1.2420303 | G12: =+F12-B12 -> 0.36203031 | H12: =+LOG(1+G12/100) -> 0.0015694385 | J12: 44159 | K12: 3635.4099 | L12: =+(K12-K11)/K11*100 -> 1.6161668 | M12: =+L12-B12 -> 0.73616683 | N12: =+LOG(1+M12/100) -> 0.0031854212 | Q12: Regression | R12: 1 | S12: 0.019379272 | T12: 0.019379272 | U12: 279.10641 | V12: 2.9463023e-50
A13: 44160 | B13: 0.88 | D13: 44160 | E13: 244.2507 | F13: =+(E13-E12)/E12*100 -> -5.3749301 | G13: =+F13-B13 -> -6.2549301 | H13: =+LOG(1+G13/100) -> -0.028051563 | J13: 44160 | K13: 3629.6499 | L13: =+(K13-K12)/K12*100 -> -0.15844182 | M13: =+L13-B13 -> -1.0384418 | N13: =+LOG(1+M13/100) -> -0.0045334752 | Q13: Residual | R13: 508 | S13: 0.035272103 | T13: 6.9433274e-05
A14: 44162 | B14: 0.84 | D14: 44162 | E14: 245.05228 | F14: =+(E14-E13)/E13*100 -> 0.32817703 | G14: =+F14-B14 -> -0.51182297 | H14: =+LOG(1+G14/100) -> -0.0022285268 | J14: 44162 | K14: 3638.3501 | L14: =+(K14-K13)/K13*100 -> 0.23969792 | M14: =+L14-B14 -> -0.60030208 | N14: =+LOG(1+M14/100) -> -0.0026149354 | Q14: Total | R14: 509 | S14: 0.054651375
A15: 44165 | B15: 0.84 | D15: 44165 | E15: 243.24132 | F15: =+(E15-E14)/E14*100 -> -0.7390092 | G15: =+F15-B15 -> -1.5790092 | H15: =+LOG(1+G15/100) -> -0.0069122672 | J15: 44165 | K15: 3621.6299 | L15: =+(K15-K14)/K14*100 -> -0.45955486 | M15: =+L15-B15 -> -1.2995549 | N15: =+LOG(1+M15/100) -> -0.0056808887
A16: 44166 | B16: 0.92 | D16: 44166 | E16: 238.83765 | F16: =+(E16-E15)/E15*100 -> -1.8104125 | G16: =+F16-B16 -> -2.7304125 | H16: =+LOG(1+G16/100) -> -0.012022926 | J16: 44166 | K16: 3662.45 | L16: =+(K16-K15)/K15*100 -> 1.1271187 | M16: =+L16-B16 -> 0.20711872 | N16: =+LOG(1+M16/100) -> 0.00089857493 | R16: Coefficients | S16: Standard Error | T16: t Stat | U16: P-value | V16: Lower 95% | W16: Upper 95% | X16: Lower 95,0% | Y16: Upper 95,0%
A17: 44167 | B17: 0.95 | D17: 44167 | E17: 218.48177 | F17: =+(E17-E16)/E16*100 -> -8.5228945 | G17: =+F17-B17 -> -9.4728945 | H17: =+LOG(1+G17/100) -> -0.043221366 | J17: 44167 | K17: 3669.01 | L17: =+(K17-K16)/K16*100 -> 0.17911668 | M17: =+L17-B17 -> -0.77088332 | N17: =+LOG(1+M17/100) -> -0.0033608747 | Q17: Intercept | R17: 0.0038620411 | S17: 0.0013908046 | T17: 2.7768394 | U17: 0.0056917826 | V17: 0.001129604 | W17: 0.0065944781 | X17: 0.001129604 | Y17: 0.0065944781
A18: 44168 | B18: 0.92 | D18: 44168 | E18: 218.66978 | F18: =+(E18-E17)/E17*100 -> 0.086056975 | G18: =+F18-B18 -> -0.83394302 | H18: =+LOG(1+G18/100) -> -0.0036369548 | J18: 44168 | K18: 3666.72 | L18: =+(K18-K17)/K17*100 -> -0.062415721 | M18: =+L18-B18 -> -0.98241572 | N18: =+LOG(1+M18/100) -> -0.0042876733 | Q18: X Variable 1 | R18: 1.2251307 | S18: 0.073332673 | T18: 16.706478 | U18: 2.9463023e-50 | V18: 1.081058 | W18: 1.3692033 | X18: 1.081058 | Y18: 1.3692033
A19: 44169 | B19: 0.97 | D19: 44169 | E19: 223.50888 | F19: =+(E19-E18)/E18*100 -> 2.2129697 | G19: =+F19-B19 -> 1.2429697 | H19: =+LOG(1+G19/100) -> 0.0053648756 | J19: 44169 | K19: 3699.1201 | L19: =+(K19-K18)/K18*100 -> 0.88362751 | M19: =+L19-B19 -> -0.086372487 | N19: =+LOG(1+M19/100) -> -0.00037527303
A20: 44172 | B20: 0.94 | D20: 44172 | E20: 225.32973 | F20: =+(E20-E19)/E19*100 -> 0.81466408 | G20: =+F20-B20 -> -0.12533592 | H20: =+LOG(1+G20/100) -> -0.0005446684 | J20: 44172 | K20: 3691.96 | L20: =+(K20-K19)/K19*100 -> -0.19356377 | M20: =+L20-B20 -> -1.1335638 | N20: =+LOG(1+M20/100) -> -0.0049511203
A21: 44173 | B21: 0.92 | D21: 44173 | E21: 225.48807 | F21: =+(E21-E20)/E20*100 -> 0.070270557 | G21: =+F21-B21 -> -0.84972944 | H21: =+LOG(1+G21/100) -> -0.0037060964 | J21: 44173 | K21: 3702.25 | L21: =+(K21-K20)/K20*100 -> 0.27871481 | M21: =+L21-B21 -> -0.64128519 | N21: =+LOG(1+M21/100) -> -0.0027940347
A22: 44174 | B22: 0.95 | D22: 44174 | E22: 218.27394 | F22: =+(E22-E21)/E21*100 -> -3.1993385 | G22: =+F22-B22 -> -4.1493385 | H22: =+LOG(1+G22/100) -> -0.018404886 | J22: 44174 | K22: 3672.8201 | L22: =+(K22-K21)/K21*100 -> -0.79492016 | M22: =+L22-B22 -> -1.7449202 | N22: =+LOG(1+M22/100) -> -0.0076449871
A23: 44175 | B23: 0.92 | D23: 44175 | E23: 220.59949 | F23: =+(E23-E22)/E22*100 -> 1.0654255 | G23: =+F23-B23 -> 0.14542552 | H23: =+LOG(1+G23/100) -> 0.0006311162 | J23: 44175 | K23: 3668.1001 | L23: =+(K23-K22)/K22*100 -> -0.12851081 | M23: =+L23-B23 -> -1.0485108 | N23: =+LOG(1+M23/100) -> -0.0045776654 | Q23: SUMMARY OUTPUT WITH COVID
A24: 44176 | B24: 0.9 | D24: 44176 | E24: 220.10468 | F24: =+(E24-E23)/E23*100 -> -0.22430334 | G24: =+F24-B24 -> -1.1243033 | H24: =+LOG(1+G24/100) -> -0.0049104435 | J24: 44176 | K24: 3663.46 | L24: =+(K24-K23)/K23*100 -> -0.12649973 | M24: =+L24-B24 -> -1.0264997 | N24: =+LOG(1+M24/100) -> -0.0044810703
A25: 44179 | B25: 0.9 | D25: 44179 | E25: 218.96664 | F25: =+(E25-E24)/E24*100 -> -0.51704081 | G25: =+F25-B25 -> -1.4170408 | H25: =+LOG(1+G25/100) -> -0.0061981497 | J25: 44179 | K25: 3647.49 | L25: =+(K25-K24)/K24*100 -> -0.4359259 | M25: =+L25-B25 -> -1.3359259 | N25: =+LOG(1+M25/100) -> -0.0058409553 | Q25: Regression Statistics
A26: 44180 | B26: 0.92 | D26: 44180 | E26: 217.85832 | F26: =+(E26-E25)/E25*100 -> -0.50616026 | G26: =+F26-B26 -> -1.4261603 | H26: =+LOG(1+G26/100) -> -0.0062383261 | J26: 44180 | K26: 3694.6201 | L26: =+(K26-K25)/K25*100 -> 1.2921249 | M26: =+L26-B26 -> 0.37212492 | N26: =+LOG(1+M26/100) -> 0.0016131184 | Q26: Multiple R | R26: 0.71729337
A27: 44181 | B27: 0.92 | D27: 44181 | E27: 221.29219 | F27: =+(E27-E26)/E26*100 -> 1.5761934 | G27: =+F27-B27 -> 0.65619336 | H27: =+LOG(1+G27/100) -> 0.0028405021 | J27: 44181 | K27: 3701.1699 | L27: =+(K27-K26)/K26*100 -> 0.17727952 | M27: =+L27-B27 -> -0.74272048 | N27: =+LOG(1+M27/100) -> -0.0032376323 | Q27: R Square | R27: 0.51450977
A28: 44182 | B28: 0.94 | D28: 44182 | E28: 223.56825 | F28: =+(E28-E27)/E27*100 -> 1.0285325 | G28: =+F28-B28 -> 0.08853246 | H28: =+LOG(1+G28/100) -> 0.00038432149 | J28: 44182 | K28: 3722.48 | L28: =+(K28-K27)/K27*100 -> 0.57576548 | M28: =+L28-B28 -> -0.36423452 | N28: =+LOG(1+M28/100) -> -0.0015847383 | Q28: Adjusted R Square | R28: 0.51412231
A29: 44183 | B29: 0.95 | D29: 44183 | E29: 225.06252 | F29: =+(E29-E28)/E28*100 -> 0.66836981 | G29: =+F29-B29 -> -0.28163019 | H29: =+LOG(1+G29/100) -> -0.0012248299 | J29: 44183 | K29: 3709.4099 | L29: =+(K29-K28)/K28*100 -> -0.35111185 | M29: =+L29-B29 -> -1.3011119 | N29: =+LOG(1+M29/100) -> -0.0056877397 | Q29: Standard Error | R29: 0.0080227659
A30: 44186 | B30: 0.95 | D30: 44186 | E30: 224.11253 | F30: =+(E30-E29)/E29*100 -> -0.42209681 | G30: =+F30-B30 -> -1.3720968 | H30: =+LOG(1+G30/100) -> -0.0060001998 | J30: 44186 | K30: 3694.9199 | L30: =+(K30-K29)/K29*100 -> -0.39062791 | M30: =+L30-B30 -> -1.3406279 | N30: =+LOG(1+M30/100) -> -0.0058616529 | Q30: Observations | R30: 1255
A31: 44187 | B31: 0.93 | D31: 44187 | E31: 228.76361 | F31: =+(E31-E30)/E30*100 -> 2.0753312 | G31: =+F31-B31 -> 1.1453312 | H31: =+LOG(1+G31/100) -> 0.0049458407 | J31: 44187 | K31: 3687.26 | L31: =+(K31-K30)/K30*100 -> -0.20730929 | M31: =+L31-B31 -> -1.1373093 | N31: =+LOG(1+M31/100) -> -0.0049675737
A32: 44188 | B32: 0.96 | D32: 44188 | E32: 225.06252 | F32: =+(E32-E31)/E31*100 -> -1.617869 | G32: =+F32-B32 -> -2.577869 | H32: =+LOG(1+G32/100) -> -0.011342375 | J32: 44188 | K32: 3690.01 | L32: =+(K32-K31)/K31*100 -> 0.074581125 | M32: =+L32-B32 -> -0.88541887 | N32: =+LOG(1+M32/100) -> -0.0038624501 | Q32: ANOVA
A33: 44189 | B33: 0.94 | D33: 44189 | E33: 223.42972 | F33: =+(E33-E32)/E32*100 -> -0.72548609 | G33: =+F33-B33 -> -1.6654861 | H33: =+LOG(1+G33/100) -> -0.0072940247 | J33: 44189 | K33: 3703.0601 | L33: =+(K33-K32)/K32*100 -> 0.3536589 | M33: =+L33-B33 -> -0.5863411 | N33: =+LOG(1+M33/100) -> -0.0025539418 | R33: df | S33: SS | T33: MS | U33: F | V33: Significance F
A34: 44193 | B34: 0.94 | D34: 44193 | E34: 222.30157 | F34: =+(E34-E33)/E33*100 -> -0.50492089 | G34: =+F34-B34 -> -1.4449209 | H34: =+LOG(1+G34/100) -> -0.0063209891 | J34: 44193 | K34: 3735.3601 | L34: =+(K34-K33)/K33*100 -> 0.8722529 | M34: =+L34-B34 -> -0.067747098 | N34: =+LOG(1+M34/100) -> -0.00029432162 | Q34: Regression | R34: 1 | S34: 0.085469751 | T34: 0.085469751 | U34: 1327.8964 | V34: 7.7434438e-199
A35: 44194 | B35: 0.94 | D35: 44194 | E35: 220.14429 | F35: =+(E35-E34)/E34*100 -> -0.97043289 | G35: =+F35-B35 -> -1.9104329 | H35: =+LOG(1+G35/100) -> -0.0083771821 | J35: 44194 | K35: 3727.04 | L35: =+(K35-K34)/K34*100 -> -0.22273805 | M35: =+L35-B35 -> -1.1627381 | N35: =+LOG(1+M35/100) -> -0.0050792942 | Q35: Residual | R35: 1253 | S35: 0.080649059 | T35: 6.4364772e-05
A36: 44195 | B36: 0.93 | D36: 44195 | E36: 220.08487 | F36: =+(E36-E35)/E35*100 -> -0.026990355 | G36: =+F36-B36 -> -0.95699036 | H36: =+LOG(1+G36/100) -> -0.0041761711 | J36: 44195 | K36: 3732.04 | L36: =+(K36-K35)/K35*100 -> 0.13415472 | M36: =+L36-B36 -> -0.79584528 | N36: =+LOG(1+M36/100) -> -0.003470139 | Q36: Total | R36: 1254 | S36: 0.16611881
A37: 44196 | B37: 0.93 | D37: 44196 | E37: 220.21355 | F37: =+(E37-E36)/E36*100 -> 0.058467158 | G37: =+F37-B37 -> -0.87153284 | H37: =+LOG(1+G37/100) -> -0.0038016093 | J37: 44196 | K37: 3756.0701 | L37: =+(K37-K36)/K36*100 -> 0.64388455 | M37: =+L37-B37 -> -0.28611545 | N37: =+LOG(1+M37/100) -> -0.0012443646
A38: 44200 | B38: 0.93 | D38: 44200 | E38: 218.01665 | F38: =+(E38-E37)/E37*100 -> -0.99762228 | G38: =+F38-B38 -> -1.9276223 | H38: =+LOG(1+G38/100) -> -0.0084532953 | J38: 44200 | K38: 3700.6499 | L38: =+(K38-K37)/K37*100 -> -1.4754828 | M38: =+L38-B38 -> -2.4054828 | N38: =+LOG(1+M38/100) -> -0.01057458 | R38: Coefficients | S38: Standard Error | T38: t Stat | U38: P-value | V38: Lower 95% | W38: Upper 95% | X38: Lower 95,0% | Y38: Upper 95,0%
A39: 44201 | B39: 0.96 | D39: 44201 | E39: 219.21407 | F39: =+(E39-E38)/E38*100 -> 0.54923247 | G39: =+F39-B39 -> -0.41076753 | H39: =+LOG(1+G39/100) -> -0.0017876147 | J39: 44201 | K39: 3726.8601 | L39: =+(K39-K38)/K38*100 -> 0.70825952 | M39: =+L39-B39 -> -0.25174048 | N39: =+LOG(1+M39/100) -> -0.0010946735 | Q39: Intercept | R39: 0.0015174769 | S39: 0.00049262906 | T39: 3.0803642 | U39: 0.0021124958 | V39: 0.00055100813 | W39: 0.0024839457 | X39: 0.00055100813 | Y39: 0.0024839457
A40: 44202 | B40: 1.04 | D40: 44202 | E40: 213.89995 | F40: =+(E40-E39)/E39*100 -> -2.4241681 | G40: =+F40-B40 -> -3.4641681 | H40: =+LOG(1+G40/100) -> -0.015311456 | J40: 44202 | K40: 3748.1399 | L40: =+(K40-K39)/K39*100 -> 0.57098427 | M40: =+L40-B40 -> -0.46901573 | N40: =+LOG(1+M40/100) -> -0.0020417011 | Q40: X Variable 1 | R40: 1.1238871 | S40: 0.03084186 | T40: 36.440313 | U40: 7.7434438e-199 | V40: 1.0633797 | W40: 1.1843944 | X40: 1.0633797 | Y40: 1.1843944
A41: 44203 | B41: 1.08 | D41: 44203 | E41: 215.71092 | F41: =+(E41-E40)/E40*100 -> 0.84664542 | G41: =+F41-B41 -> -0.23335458 | H41: =+LOG(1+G41/100) -> -0.0010146304 | J41: 44203 | K41: 3803.79 | L41: =+(K41-K40)/K40*100 -> 1.4847404 | M41: =+L41-B41 -> 0.40474038 | N41: =+LOG(1+M41/100) -> 0.0017542175
A42: 44204 | B42: 1.13 | D42: 44204 | E42: 219.72865 | F42: =+(E42-E41)/E41*100 -> 1.8625532 | G42: =+F42-B42 -> 0.73255321 | H42: =+LOG(1+G42/100) -> 0.0031698419 | J42: 44204 | K42: 3824.6799 | L42: =+(K42-K41)/K41*100 -> 0.54918627 | M42: =+L42-B42 -> -0.58081373 | N42: =+LOG(1+M42/100) -> -0.0025297958
A43: 44207 | B43: 1.15 | D43: 44207 | E43: 215.9781 | F43: =+(E43-E42)/E42*100 -> -1.7069004 | G43: =+F43-B43 -> -2.8569004 | H43: =+LOG(1+G43/100) -> -0.012588043 | J43: 44207 | K43: 3799.6101 | L43: =+(K43-K42)/K42*100 -> -0.65547509 | M43: =+L43-B43 -> -1.8054751 | N43: =+LOG(1+M43/100) -> -0.0079127268
A44: 44208 | B44: 1.15 | D44: 44208 | E44: 213.2765 | F44: =+(E44-E43)/E43*100 -> -1.2508671 | G44: =+F44-B44 -> -2.4008671 | H44: =+LOG(1+G44/100) -> -0.010554041 | J44: 44208 | K44: 3801.1899 | L44: =+(K44-K43)/K43*100 -> 0.041578845 | M44: =+L44-B44 -> -1.1084212 | N44: =+LOG(1+M44/100) -> -0.0048406894
A45: 44209 | B45: 1.1 | D45: 44209 | E45: 215.90883 | F45: =+(E45-E44)/E44*100 -> 1.2342308 | G45: =+F45-B45 -> 0.13423076 | H45: =+LOG(1+G45/100) -> 0.00058256587 | J45: 44209 | K45: 3809.8401 | L45: =+(K45-K44)/K44*100 -> 0.22756417 | M45: =+L45-B45 -> -0.87243583 | N45: =+LOG(1+M45/100) -> -0.0038055655
A46: 44210 | B46: 1.15 | D46: 44210 | E46: 213.3557 | F46: =+(E46-E45)/E45*100 -> -1.1825043 | G46: =+F46-B46 -> -2.3325043 | H46: =+LOG(1+G46/100) -> -0.010249948 | J46: 44210 | K46: 3795.54 | L46: =+(K46-K45)/K45*100 -> -0.37534512 | M46: =+L46-B46 -> -1.5253451 | N46: =+LOG(1+M46/100) -> -0.0066755326
A47: 44211 | B47: 1.11 | D47: 44211 | E47: 210.92131 | F47: =+(E47-E46)/E46*100 -> -1.1409994 | G47: =+F47-B47 -> -2.2509994 | H47: =+LOG(1+G47/100) -> -0.0098876742 | J47: 44211 | K47: 3768.25 | L47: =+(K47-K46)/K46*100 -> -0.7190028 | M47: =+L47-B47 -> -1.8290028 | N47: =+LOG(1+M47/100) -> -0.0080167975
A48: 44215 | B48: 1.1 | D48: 44215 | E48: 214.50359 | F48: =+(E48-E47)/E47*100 -> 1.6983942 | G48: =+F48-B48 -> 0.59839424 | H48: =+LOG(1+G48/100) -> 0.0025910485 | J48: 44215 | K48: 3798.9099 | L48: =+(K48-K47)/K47*100 -> 0.81363795 | M48: =+L48-B48 -> -0.28636205 | N48: =+LOG(1+M48/100) -> -0.0012454387
A49: 44216 | B49: 1.1 | D49: 44216 | E49: 221.11406 | F49: =+(E49-E48)/E48*100 -> 3.0817544 | G49: =+F49-B49 -> 1.9817544 | H49: =+LOG(1+G49/100) -> 0.0085224788 | J49: 44216 | K49: 3851.8501 | L49: =+(K49-K48)/K48*100 -> 1.3935625 | M49: =+L49-B49 -> 0.29356254 | N49: =+LOG(1+M49/100) -> 0.0012730582
A50: 44217 | B50: 1.12 | D50: 44217 | E50: 219.85728 | F50: =+(E50-E49)/E49*100 -> -0.56838308 | G50: =+F50-B50 -> -1.6883831 | H50: =+LOG(1+G50/100) -> -0.007395161 | J50: 44217 | K50: 3853.0701 | L50: =+(K50-K49)/K49*100 -> 0.031672331 | M50: =+L50-B50 -> -1.0883277 | N50: =+LOG(1+M50/100) -> -0.0047524553
A51: 44218 | B51: 1.1 | D51: 44218 | E51: 223.41982 | F51: =+(E51-E50)/E50*100 -> 1.6203832 | G51: =+F51-B51 -> 0.52038321 | H51: =+LOG(1+G51/100) -> 0.0022541356 | J51: 44218 | K51: 3841.47 | L51: =+(K51-K50)/K50*100 -> -0.30106117 | M51: =+L51-B51 -> -1.4010612 | N51: =+LOG(1+M51/100) -> -0.0061277591
A52: 44221 | B52: 1.05 | D52: 44221 | E52: 223.56825 | F52: =+(E52-E51)/E51*100 -> 0.066438825 | G52: =+F52-B52 -> -0.98356117 | H52: =+LOG(1+G52/100) -> -0.0042926973 | J52: 44221 | K52: 3855.3601 | L52: =+(K52-K51)/K51*100 -> 0.36158389 | M52: =+L52-B52 -> -0.68841611 | N52: =+LOG(1+M52/100) -> -0.0030000916
... A1257: 45971 | B1257: 4.13 | D1257: 45971 | E1257: 241.71001 | F1257: =+(E1257-E1256)/E1256*100 -> 0.76288219 | G1257: =+F1257-B1257 -> -3.3671178 | H1257: =+LOG(1+G1257/100) -> -0.014875067 | J1257: 45971 | K1257: 6832.4302 | L1257: =+(K1257-K1256)/K1256*100 -> 1.5401019 | M1257: =+L1257-B1257 -> -2.5898981 | N1257: =+LOG(1+M1257/100) -> -0.011396003
A1258: 45972 | D1258: 45972 | E1258: 244.5 | F1258: =+(E1258-E1257)/E1257*100 -> 1.154273 | G1258: =+F1258-B1258 -> 1.154273 | H1258: =+LOG(1+G1258/100) -> 0.004984233 | J1258: 45972 | K1258: 6846.6099 | L1258: =+(K1258-K1257)/K1257*100 -> 0.20753505 | M1258: =+L1258-B1258 -> 0.20753505 | N1258: =+LOG(1+M1258/100) -> 0.0009003793
A1259: 45973 | D1259: 45973 | E1259: 246.355 | F1259: =+(E1259-E1258)/E1258*100 -> 0.75868946 | G1259: =+F1259-B1259 -> 0.75868946 | H1259: =+LOG(1+G1259/100) -> 0.0032825101 | J1259: 45973 | K1259: 6855.5 | L1259: =+(K1259-K1258)/K1258*100 -> 0.12984728 | M1259: =+L1259-B1259 -> 0.12984728 | N1259: =+LOG(1+M1259/100) -> 0.00056355377

Sheet Beta comparables
A1: Competitor | B1: Beta Equity | C1: Net Debt | D1: Market Cap | E1: Tax Rate | F1: D/E Ratio | G1: Beta Unlevered
A2: Adobe Inc. (NasdaqGS:ADBE) | B2: 1.54 | C2: 710 | D2: 135128.3 | E2: 0.21 | F2: =C2/D2 -> 0.0052542658 | G2: =B2/(1-(1-E2)*(C2/D2)) -> 1.546419
A3: HubSpot, Inc. (NYSE:HUBS) | B3: 1.46 | C3: -1214 | D3: 19556.6 | E3: 0.21 | F3: =C3/D3 -> -0.06207623 | G3: =B3/(1-(1-E3)*(C3/D3)) -> 1.3917484
A4: SAP SE (XTRA:SAP) | B4: 0.81 | C4: -943.3 | D4: 280847.1 | E4: 0.3 | F4: =C4/D4 -> -0.0033587671 | G4: =B4/(1-(1-E4)*(C4/D4)) -> 0.80810005
A5: Workday, Inc. (NasdaqGS:WDAY) | B5: 1.15 | C5: -3050 | D5: 56034.8 | E5: 0.21 | F5: =C5/D5 -> -0.054430461 | G5: =B5/(1-(1-E5)*(C5/D5)) -> 1.1025886
A6: Datadog, Inc. (NasdaqGS:DDOG) | B6: 1.23 | C6: -2861 | D6: 54873 | E6: 0.21 | F6: =C6/D6 -> -0.052138575 | G6: =B6/(1-(1-E6)*(C6/D6)) -> 1.1813412
A7: Intuit Inc. (NasdaqGS:INTU) | B7: 1.27 | C7: 3165 | D7: 176879.4 | E7: 0.21 | F7: =C7/D7 -> 0.017893548 | G7: =B7/(1-(1-E7)*(C7/D7)) -> 1.28821
A8: DocuSign, Inc. (NasdaqGS:DOCU) | B8: 0.99 | C8: -717.5 | D8: 13848 | E8: 0.21 | F8: =C8/D8 -> -0.051812536 | G8: =B8/(1-(1-E8)*(C8/D8)) -> 0.95107086
A9: ServiceNow, Inc. (NYSE:NOW) | B9: 0.97 | C9: -7275 | D9: 171043.6 | E9: 0.21 | F9: =C9/D9 -> -0.042533015 | G9: =B9/(1-(1-E9)*(C9/D9)) -> 0.93846651
A10: Salesforce, Inc. (NYSE:CRM) | B10: =B12 * (1 + (1 - E10) * F10) -> 1.1691896 | C10: ='Unlevered Cost of Capital'!D13 -> 4693.8 | D10: 247910 | E10: 0.165 | F10: =C10/D10 -> 0.018933484 | G10: =B13/(1-(1-E10)*(C10/D10)) -> 1.1879708
A12: Industry Beta asset (average) | B12: =AVERAGE(G2:G9) -> 1.1509931
A13: Salesforce Beta Equity | B13: =B12 * (1 + (1 - E10) * F10) -> 1.1691896

Sheet Graphs
C3: 2025 | D3: 2026 | E3: 2027 | F3: 2028 | G3: 2029 | H3: 2030 | I3: 2031 | J3: 2032 | K3: 2033 | L3: 2034 | M3: 2035
B4: PV of tax shields | C4: =+'Leverage finale'!C50 -> 11136.895 | D4: =+'Leverage finale'!D50 -> 11180.054 | E4: =+'Leverage finale'!E50 -> 11248.506 | F4: =+'Leverage finale'!F50 -> 11330.027 | G4: =+'Leverage finale'!G50 -> 11423.829 | H4: =+'Leverage finale'!H50 -> 11529.122 | I4: =+'Leverage finale'!I50 -> 11645.678 | J4: =+'Leverage finale'!J50 -> 11774.986 | ... M4: =+'Leverage finale'!M50 -> 12238.649
B5: PV of bankruptcy costs | C5: =+'Leverage finale'!C51 -> 43855.372 | D5: =+'Leverage finale'!D51 -> 35030.58 | E5: =+'Leverage finale'!E51 -> 27922.654 | F5: =+'Leverage finale'!F51 -> 17874.355 | G5: =+'Leverage finale'!G51 -> 13901.388 | H5: =+'Leverage finale'!H51 -> 11110.28 | I5: =+'Leverage finale'!I51 -> 7685.2424 | J5: =+'Leverage finale'!J51 -> 7974.8297 | ... M5: =+'Leverage finale'!M51 -> 8853.6237

Sheet Beta
A1: Price | B1: Adj Close | C1: Close | D1: High | E1: Low | F1: Open | G1: Volume | K1: Price | L1: Adj Close | M1: Close | N1: High | O1: Low | P1: Open | Q1: Volume | U1: Price | V1: Adj Close | W1: Close | X1: High | Y1: Low | Z1: Open | AA1: Volume | AE1: Price | AF1: Adj Close | AG1: Close | AH1: High | AI1: Low | AJ1: Open | AK1: Volume | AN1: observation_date | AO1: DGS10
A2: Ticker | B2: CRM | C2: CRM | D2: CRM | E2: CRM | F2: CRM | G2: CRM | K2: Ticker | L2: CRM | M2: CRM | N2: CRM | O2: CRM | P2: CRM | Q2: CRM | U2: Ticker | V2: ^GSPC | W2: ^GSPC | X2: ^GSPC | Y2: ^GSPC | Z2: ^GSPC | AA2: ^GSPC | AE2: Ticker | AF2: ^GSPC | AG2: ^GSPC | AH2: ^GSPC | AI2: ^GSPC | AJ2: ^GSPC | AK2: ^GSPC | AN2: 44145 | AO2: 0.98
A3: Date | B3: SALESFORCE DAILY | K3: Date | L3: SALESFORCE MONTHLY | U3: Date | V3: SP500 DAILY | AE3: Date | AF3: SP500 MONTHLY | AN3: 44146
A4: 44147 | B4: 246.82362 | C4: 249.42 | D4: 254.97 | E4: 246.36 | F4: 247.39999 | G4: 5607000 | K4: 44166 | L4: 220.21355 | M4: 222.53 | N4: 246.7 | O4: 215.63 | P4: 245 | Q4: 277067700 | U4: 44147 | V4: 3537.01 | W4: 3537.01 | X4: 3569.02 | Y4: 3518.5801 | Z4: 3562.6699 | AA4: 4909660000 | AE4: 44166 | AF4: 3756.0701 | AG4: 3756.0701 | AH4: 3760.2 | AI4: 3633.3999 | AJ4: 3645.8701 | AK4: 96375680000 | AN4: 44147 | AO4: 0.88
A5: 44148 | B5: 246.91267 | C5: 249.50999 | D5: 253.78999 | E5: 247.56 | F5: 252.84 | G5: 5160000 | K5: 44197 | L5: 223.21202 | M5: 225.56 | N5: 230.3 | O5: 212.99001 | P5: 222.64 | Q5: 153537600 | U5: 44148 | V5: 3585.1499 | W5: 3585.1499 | X5: 3593.6599 | Y5: 3552.5701 | Z5: 3552.5701 | AA5: 4719580000 | AE5: 44197 | AF5: 3714.24 | AG5: 3714.24 | AH5: 3870.8999 | AI5: 3662.71 | AJ5: 3764.6101 | AK5: 106117800000 | AN5: 44148 | AO5: 0.89
A6: 44151 | B6: 247.28873 | C6: 249.89 | D6: 253.49001 | E6: 248.17999 | F6: 249.52 | G6: 5712600 | K6: 44228 | L6: 214.24631 | M6: 216.5 | N6: 251.23 | O6: 216.34 | P6: 227.21001 | Q6: 127959100 | U6: 44151 | V6: 3626.9099 | W6: 3626.9099 | X6: 3628.51 | Y6: 3600.1599 | Z6: 3600.1599 | AA6: 5295510000 | AE6: 44228 | AF6: 3811.1499 | AG6: 3811.1499 | AH6: 3950.4299 | AI6: 3725.6201 | AJ6: 3731.1699 | AK6: 99082320000 | AN6: 44151 | AO6: 0.91
A7: 44152 | B7: 253.50339 | C7: 256.17001 | D7: 258.26999 | E7: 250.46001 | F7: 253.74001 | G7: 5090700 | K7: 44256 | L7: 209.66451 | M7: 211.87 | N7: 220.2 | O7: 201.50999 | P7: 219.89999 | Q7: 175215000 | U7: 44152 | V7: 3609.53 | W7: 3609.53 | X7: 3623.1101 | Y7: 3588.6799 | Z7: 3610.3101 | AA7: 4812180000 | AE7: 44256 | AF7: 3972.8899 | AG7: 3972.8899 | AH7: 3994.4099 | AI7: 3723.3401 | AJ7: 3842.51 | AK7: 122371150000 | AN7: 44152 | AO7: 0.87
A8: 44153 | B8: 254.48305 | C8: 257.16 | D8: 262.66 | E8: 255.85001 | F8: 256.39999 | G8: 5880500 | K8: 44287 | L8: 227.92245 | M8: 230.32001 | N8: 238.33 | O8: 213.37 | P8: 213.60001 | Q8: 106170300 | U8: 44153 | V8: 3567.79 | W8: 3567.79 | X8: 3619.0901 | Y8: 3567.3301 | Z8: 3612.0901 | AA8: 5284810000 | AE8: 44287 | AF8: 4181.1699 | AG8: 4181.1699 | AH8: 4218.7798 | AI8: 3992.78 | AJ8: 3992.78 | AK8: 83124090000 | AN8: 44153 | AO8: 0.88
A9: 44154 | B9: 261.89508 | C9: 264.64999 | D9: 267.09 | E9: 255.66 | F9: 256.84 | G9: 8084600 | K9: 44317 | L9: 235.62146 | M9: 238.10001 | N9: 243.5 | O9: 208.91 | P9: 230.77 | Q9: 131928300 | U9: 44154 | V9: 3581.8701 | W9: 3581.8701 | X9: 3585.22 | Y9: 3543.8401 | Z9: 3559.4099 | AA9: 4363370000 | AE9: 44317 | AF9: 4204.1099 | AG9: 4204.1099 | AH9: 4238.04 | AI9: 4056.8799 | AJ9: 4191.98 | AK9: 88321860000 | AN9: 44154 | AO9: 0.86
A10: 44155 | B10: 255.35394 | C10: 258.04001 | D10: 265.01999 | E10: 257.82001 | F10: 263.59 | G10: 7286100 | K10: 44348 | L10: 241.72723 | M10: 244.27 | N10: 247.69 | O10: 229.42999 | P10: 238 | Q10: 124445700 | U10: 44155 | V10: 3557.54 | W10: 3557.54 | X10: 3581.23 | Y10: 3556.8501 | Z10: 3579.3101 | AA10: 4236370000 | AE10: 44348 | AF10: 4297.5 | AG10: 4297.5 | AH10: 4302.4302 | AI10: 4164.3999 | AJ10: 4216.52 | AK10: 102544180000 | AN10: 44155 | AO10: 0.83
A11: 44158 | B11: 254.95807 | C11: 257.64001 | D11: 261.73999 | E11: 254.61 | F11: 261.23001 | G11: 5383600 | K11: 44378 | L11: 239.41158 | M11: 241.92999 | N11: 253.5 | O11: 234.31 | P11: 244.5 | Q11: 129733200 | U11: 44158 | V11: 3577.5901 | W11: 3577.5901 | X11: 3589.8101 | Y11: 3552.77 | Z11: 3566.8201 | AA11: 5057550000 | AE11: 44378 | AF11: 4395.2598 | AG11: 4395.2598 | AH11: 4429.9702 | AI11: 4233.1299 | AJ11: 4300.73 | AK11: 84255620000 | AN11: 44158 | AO11: 0.86
A12: 44159 | B12: 258.12473 | C12: 260.84 | D12: 262.31 | E12: 257.82001 | F12: 260 | G12: 5797300 | K12: 44409 | L12: 262.50864 | M12: 265.26999 | N12: 275.22 | O12: 238.88 | P12: 242.31 | Q12: 132741000 | U12: 44159 | V12: 3635.4099 | W12: 3635.4099 | X12: 3642.3101 | Y12: 3594.52 | Z12: 3594.52 | AA12: 6280290000 | AE12: 44409 | AF12: 4522.6802 | AG12: 4522.6802 | AH12: 4537.3599 | AI12: 4367.73 | AJ12: 4406.8599 | AK12: 80500760000 | AN12: 44159 | AO12: 0.88
A13: 44160 | B13: 244.2507 | C13: 246.82001 | D13: 266.10001 | E13: 245.05 | F13: 263.73001 | G13: 26394900 | K13: 44440 | L13: 268.39673 | M13: 271.22 | N13: 286.35999 | O13: 252.19 | P13: 266.26999 | Q13: 131289200 | U13: 44160 | V13: 3629.6499 | W13: 3629.6499 | X13: 3635.5 | Y13: 3617.76 | Z13: 3635.5 | AA13: 4910440000 | AE13: 44440 | AF13: 4307.54 | AG13: 4307.54 | AH13: 4545.8501 | AI13: 4305.9102 | AJ13: 4528.7998 | AK13: 85528860000 | AN13: 44160 | AO13: 0.88
A14: 44162 | B14: 245.05228 | C14: 247.63 | D14: 251.84 | E14: 247.03 | F14: 251 | G14: 7395000 | K14: 44470 | L14: 296.57034 | M14: 299.69 | N14: 300.78 | O14: 266.14001 | P14: 271.5 | Q14: 90870800 | U14: 44162 | V14: 3638.3501 | W14: 3638.3501 | X14: 3644.3101 | Y14: 3629.3301 | Z14: 3638.55 | AA14: 2778390000 | AE14: 44470 | AF14: 4605.3799 | AG14: 4605.3799 | AH14: 4608.0801 | AI14: 4278.9399 | AJ14: 4317.1602 | AK14: 80253600000 | AN14: 44161
A15: 44165 | B15: 243.24132 | C15: 245.8 | D15: 247.63 | E15: 236.07001 | F15: 245.48 | G15: 18966400 | K15: 44501 | L15: 281.99368 | M15: 284.95999 | N15: 311.75 | O15: 283.04001 | P15: 301.5 | Q15: 99291500 | U15: 44165 | V15: 3621.6299 | W15: 3621.6299 | X15: 3634.1799 | Y15: 3594.3899 | Z15: 3634.1799 | AA15: 6308410000 | AE15: 44501 | AF15: 4567 | AG15: 4567 | AH15: 4743.8301 | AI15: 4560 | AJ15: 4610.6201 | AK15: 88268840000 | AN15: 44162 | AO15: 0.84
A16: 44166 | B16: 238.83765 | C16: 241.35001 | D16: 246.7 | E16: 238.7 | F16: 245 | G16: 18872000 | K16: 44531 | L16: 251.4846 | M16: 254.13 | N16: 276.94 | O16: 245.25 | P16: 271.26001 | Q16: 149738000 | U16: 44166 | V16: 3662.45 | W16: 3662.45 | X16: 3678.45 | Y16: 3645.8701 | Z16: 3645.8701 | AA16: 5418480000 | AE16: 44531 | AF16: 4766.1802 | AG16: 4766.1802 | AH16: 4808.9302 | AI16: 4495.1201 | AJ16: 4602.8198 | AK16: 92750180000 | AN16: 44165 | AO16: 0.84
A17: 44167 | B17: 218.48177 | C17: 220.78 | D17: 226 | E17: 215.63 | F17: 225.48 | G17: 52225500 | K17: 44562 | L17: 230.2084 | M17: 232.63 | N17: 256.87 | O17: 207.50999 | P17: 255.00999 | Q17: 162490700 | U17: 44167 | V17: 3669.01 | W17: 3669.01 | X17: 3670.96 | Y17: 3644.8401 | Z17: 3653.78 | AA17: 5041250000 | AE17: 44562 | AF17: 4515.5498 | AG17: 4515.5498 | AH17: 4818.6201 | AI17: 4222.6201 | AJ17: 4778.1401 | AK17: 95562890000 | AN17: 44166 | AO17: 0.92
A18: 44168 | B18: 218.66978 | C18: 220.97 | D18: 226.11 | E18: 220.13 | F18: 226.11 | G18: 21395300 | K18: 44593 | L18: 208.33844 | M18: 210.53 | N18: 234.49001 | O18: 184.44 | P18: 232.37 | Q18: 141619500 | U18: 44168 | V18: 3666.72 | W18: 3666.72 | X18: 3682.73 | Y18: 3657.1699 | Z18: 3668.28 | AA18: 5065340000 | AE18: 44593 | AF18: 4373.9399 | AG18: 4373.9399 | AH18: 4595.3101 | AI18: 4114.6499 | AJ18: 4519.5698 | AK18: 92667710000 | AN18: 44167 | AO18: 0.95
